[
    {
        "title": "述怀 其一",
        "type": "五言律诗",
        "paragraph": [
            "青门聊极望，何事久离群。",
            "芳草失归路，故乡空暮云。",
            "信回陵树老，梦断灞流分。",
            "兄弟正南北，鸿声堪独闻。"
        ],
        "translate": [
            "姑且在长安城外极目远望,为什么长久地离开了朋友呢?",
            "芳草萋萋,我已迷失了归路;暮云笼罩着故乡,一片空寂。",
            "书信已经寄回,陵园中的树木已渐渐衰老;我从梦中醒来,只见灞水与江流分流。",
            "我们兄弟俩正处在南北两地之间,鸿雁的鸣叫声怎么能够独自听到呢?"
        ]
    },
    {
        "title": "赠王道士",
        "type": "五言诗",
        "paragraph": [
            "玉洞秋有花，蓬山夜无鬼。",
            "岂知浮云世，生死逐流水。",
            "瑶台歌一曲，曲尽五烟起。",
            "悠然望虚路，玉京在海里。",
            "青箓秘不闻，黄鹤去不止。",
            "愿随执轻策，往结周太子。"
        ],
        "translate": [
            "秋天的玉洞里开满了鲜花,蓬莱仙山的夜晚却没有鬼怪作怪。",
            "谁知道混沌无知这个世界上,人的生死都跟随着流水而去。",
            "瑶台仙女唱了一首歌,一曲唱完五彩云烟四起。",
            "悠然地眺望那茫茫的天街大道,只见那玉京城隐没在浩瀚的大海里。",
            "皇帝的青箓秘而不宣,黄鹤一去不复返。",
            "我愿意跟随你,手执轻便的马鞭,去结交东周的太子。"
        ]
    },
    {
        "title": "感萤",
        "type": "五言诗",
        "paragraph": [
            "爱尔持照书，临书叹吾道。",
            "青荧一点光，曾误几人老。",
            "夜久独此心，环垣闭秋草。"
        ],
        "translate": [
            "我喜爱你手里拿着照亮我的书,面对着书叹息我的道义。",
            "荧惑星的光芒,曾经误导过多少人,使他们衰老。",
            "长夜漫漫,独守空闺,思念之情涌上心头。围墙紧闭,秋草丛生,一片荒凉冷清。"
        ]
    },
    {
        "title": "感古",
        "type": "五言律诗",
        "paragraph": [
            "九折无停波，三光如转烛。",
            "玄珠人不识，徒爱燕赵玉。",
            "祖龙已深惑，汉氏远徇欲。",
            "骊山与茂陵，相对秋草绿。"
        ],
        "translate": [
            "九条曲折的江水不会停滞不前,日月星辰放射出的光芒就像转动的蜡烛。",
            "玄色珍珠一般人是不认识的,只喜欢燕赵一带出产的美玉。",
            "祖龙已经深受迷惑,汉代的君主却疏远了顺从自己的欲望。",
            "骊山与茂陵,相对而立,只见秋草一片碧绿。"
        ]
    },
    {
        "title": "锄草怨",
        "type": "五言诗",
        "paragraph": [
            "种田望雨多，雨多长蓬蒿。",
            "亦念官赋急，宁知荷锄劳。",
            "亭午霁日明，邻翁醉陶陶。",
            "乡吏不到门，禾黍苗自高。",
            "独有辛苦者，屡为州县徭。",
            "罢锄田又废，恋乡不忍逃。",
            "出门吏相促，邻家满仓谷。",
            "邻翁不可告，尽日向田哭。"
        ],
        "translate": [
            "种田的人盼望着下雨,雨下得好就长满了蓬蒿。",
            "也顾念官府的赋税催逼得很急,难道知道负担着锄头的辛劳?",
            "中午时分,雨后初晴,阳光很明亮,邻居老翁喝得酩酊大醉。",
            "乡吏不到家门,庄稼的苗子自然长得高大。",
            "唯独有最辛苦的人,屡次去州县服徭役。",
            "刚刚停下锄头,又一次荒废了农活,我留恋故乡不忍心逃离。",
            "小吏出门催促,邻家粮仓里装满了谷子。",
            "邻居的老人不能把情况告诉我,整天对着田地痛哭。"
        ]
    },
    {
        "title": "道中早发",
        "type": "五言诗",
        "paragraph": [
            "野店鸡一声，萧萧客车动。",
            "西峰带晓月，十里犹相送。",
            "繁弦满长道，羸马四蹄重。",
            "遥羡青楼人，锦衾方远梦。",
            "功名不我与，孤剑何所用。",
            "行役难自休，家山忆秋洞。"
        ],
        "translate": [
            "在一个荒野的旅店,忽然传来公鸡的叫声,客人坐的车子在萧萧地响动。",
            "拂晓时分西边的山峰上笼罩着一轮明月,远隔十里之遥还依依惜别相送。",
            "繁密的乐器飘满了长长的道路,瘦弱的马儿四蹄又沉又重。",
            "我真羡慕高楼上长相厮守的人,可惜只有锦被飘飘洒洒才能做个圆满的梦。",
            "功名都不能给我,这把宝剑又有什么用处呢?",
            "在外奔波劳作难以自己停止,回望故乡的山总是怀念那秋天的洞穴。"
        ]
    },
    {
        "title": "筑台",
        "type": "五言诗",
        "paragraph": [
            "魏国昔强盛，宫中金玉多。",
            "徵丁筑层台，唯恐不巍峨。",
            "结构切星汉，跻攀横绮罗。",
            "朝观细腰舞，夜听皓齿歌。",
            "讵念人力劳，安问黍与禾。",
            "一朝国既倾，千仞堂亦平。",
            "舞模衰柳影，歌留草虫声。",
            "月照白露寒，苍苍故邺城。",
            "汉文有遗美，对此清飙生。"
        ],
        "translate": [
            "魏国从前很强盛,宫殿里金玉财宝很多。",
            "征调民工修筑层台,唯恐不够高大巍峨。",
            "房屋的结构像弯曲的星星,楼阁的栏杆横列着华丽的罗绮。",
            "早晨看她细腰曼舞,夜晚听她皓齿美妙歌唱。",
            "哪里还顾念劳动人民的辛劳,又何必去询问庄稼的收成呢?",
            "一个早晨,国家就垮台了,高耸入云的大堂也被平定了。",
            "舞姿像衰败的柳树影子,歌声伴随着草丛中的虫鸣。",
            "皎洁的月光照耀着白色的露珠,寒气袭人,那苍茫的故都邺城啊。",
            "汉文帝留有遗留下来的美德,就凭藉着这风起云涌的时节而产生了。"
        ]
    },
    {
        "title": "猎客",
        "type": "五言诗",
        "paragraph": [
            "五陵射雕客，走马占春光。",
            "下马青楼前，华裾独煌煌。",
            "自言家咸京，世族如金张。",
            "击钟传鼎食，尔来八十强。",
            "朱门争先开，车轮满路傍。",
            "娥娥燕赵人，珠箔闭高堂。",
            "清歌杂妙舞，临欢度曲长。",
            "朝游园花新，夜宴池月凉。",
            "更以驰骤多，意气事彊梁。",
            "君王正年少，终日在长杨。"
        ],
        "translate": [
            "五陵的射雕之客,骑着骏马占尽了春光。",
            "她下马来到青楼前,身着华丽的衣裙独自显得格外光彩夺目。",
            "他自己说家在咸京,世世代代都像金张那样富有声望。",
            "敲钟传鼎吃饭,从那时到现在已经八十多岁了。",
            "红色的大门争先恐后地打开,车子的轮子挤满了路边。",
            "美丽动人的燕赵姑娘,头戴珠帘紧闭高堂。",
            "清雅的歌声和各种美妙的舞蹈,在欢乐的时候演奏出悠扬的曲子。",
            "清晨在园子里游玩,看到的都是新鲜的花草;夜晚在池塘边饮宴,月光下感到很凉爽。",
            "战车频繁地奔驰,意志和气概都想侍奉强暴的君主。",
            "君王正值青春年少,整天站在长杨树上等候。"
        ]
    },
    {
        "title": "弹琴",
        "type": "五言律诗",
        "paragraph": [
            "凉室无外响，空桑七弦分。",
            "所弹非新声，俗耳安肯闻。",
            "月落未终曲，暗中泣湘君。",
            "如传我心苦，千里苍梧云。"
        ],
        "translate": [
            "凉爽的屋子里没有外边的响声,只有桑树上的七根弦管发出了声音。",
            "她弹奏的不是新曲,一般人的耳朵怎么会听见呢?",
            "月亮慢慢落下,曲子还未唱完,我默默地在黑暗中哭泣着对着湘君。",
            "如果能把我内心的痛苦告诉你,那就是那远在千里之外的苍梧山上的白云。"
        ]
    },
    {
        "title": "蚕女",
        "type": "五言诗",
        "paragraph": [
            "养蚕先养桑，蚕老人亦衰。",
            "苟无园中叶，安得机上丝。",
            "妾家非豪门，官赋日相追。",
            "鸣梭夜达晓，犹恐不及时。",
            "但忧蚕与桑，敢问结发期。",
            "东邻女新嫁，照镜弄蛾眉。"
        ],
        "translate": [
            "养蚕首先要养蚕桑,养蚕的老翁也会衰老了。",
            "如果没有园子里的树叶,怎么会有织布机上的丝呢?",
            "我的家不是豪门世族,但官府的赋税却天天来追讨。",
            "织布机在黑夜里一直响到天亮,还担心纺织娘来得不早点。",
            "只忧虑养蚕和种桑,敢问人生结发之期?",
            "东边邻居的女儿刚出嫁,照着镜子玩弄着蛾眉。"
        ]
    },
    {
        "title": "效陶彭泽",
        "type": "五言诗",
        "paragraph": [
            "一梦倏已尽，百年如露草。",
            "独有南山高，不与人共老。",
            "尊中贮灵味，无事即醉倒。",
            "何必鸣鼓钟，然后乐怀抱。",
            "轻波向海疾，浮云归谷早。",
            "形役良可嗟，唯能徇天道。"
        ],
        "translate": [
            "一场美梦一下子就过去了,人生百年就像一棵枯萎的野草一样短暂无边。",
            "唯独有南山高高在上,它不与人一起衰老。",
            "酒杯里盛满了甘甜的香味,只要是无缘无故地喝醉就倒在地上。",
            "何必敲响战鼓和钟鼓,然后才能使心怀抱负得到快乐。",
            "轻微的水波奔向大海很快,浮云回到山谷也早早归来。",
            "人的形体被人役使实在令人叹息,只不过是能够顺从天道罢了。"
        ]
    },
    {
        "title": "送进士苗纵归紫逻山居",
        "type": "五言诗",
        "paragraph": [
            "汝上多奇山，高怀惬清境。",
            "强来干名地，冠带不能整。",
            "常言梦归处，泉石寒更静。",
            "鹤声夜无人，空月随松影。",
            "今朝抛我去，春物伤明景。",
            "怅望相送还，微阳在东岭。"
        ],
        "translate": [
            "汝水之滨有许多奇异的山峰,高耸入云的山峰使我心胸开阔,感到非常惬意。",
            "努力追求功名利禄,却连帽子和衣带都不能整齐。",
            "我常说,在梦中归来之处,泉水和岩石虽然寒冷,却格外安静。",
            "寂静的夜里,只有一只鹤在鸣叫,月亮随着松林的影子升起。",
            "今天你抛弃我离去,春天的景物伤感这明丽的景色。",
            "惆怅地盼望着你送我返回故乡,只见东岭上已是夕阳西下。"
        ]
    },
    {
        "title": "送孔恂入洛",
        "type": "七言律诗",
        "paragraph": [
            "洛阳古城秋色多，送君此去心如何。",
            "青山欲暮惜别酒，碧草未尽伤离歌。",
            "前朝冠带掩金谷，旧游花月经铜驼。",
            "行人正苦奈分手，日落远水生微波。"
        ],
        "translate": [
            "洛阳古城里秋天的景色多么美好,送你到这里离去我的心情怎么呢?",
            "暮色苍茫,青山欲落,不忍饮酒送别;碧草萋萋,离歌难唱,更增添伤感。",
            "前朝的王公贵族穿着官服守卫着金谷关,从前游赏花月时路过铜驼。",
            "行路之人正苦于无可奈何地与心上人分手,夕阳西下,江面水面泛起微弱的波纹。"
        ]
    },
    {
        "title": "美刘太保",
        "type": "五言诗",
        "paragraph": [
            "常爱鲁仲连，退身得其趣。",
            "不知鸱夷子，更入五湖去。",
            "云霞恣摇曳，鸿鹄无低翥。",
            "万里天地空，清飙在平楚。",
            "藏名向宠节，辞疾去公务。",
            "夜尽醉弦歌，日高卧烟树。",
            "岂嗤生前乐，千载自垂裕。",
            "论道复论功，皆可黄金铸。"
        ],
        "translate": [
            "我常常喜爱鲁仲连,他隐退避让能够领会其中的奥妙。",
            "却不知道鸱夷子是怎么回事,反而要逃入五湖去。",
            "云霞在空中随意飘摇,天鹅在空中飞翔没有停留的时候。",
            "纵横万里,天地之间一片空旷,清冷的狂风吹拂着平原和楚地。",
            "隐藏自己的名声,追求受宠的节操,以有病为由辞去公务。",
            "夜色将尽,我沉醉在弹琴唱歌中,太阳升得很高了,我躺在烟雾弥漫的树上。",
            "难道可以嗤笑人生在世时的快乐吗?千百年后自然会流芳千古。",
            "无论是论道还是论功,都可以用黄金来铸造。"
        ]
    },
    {
        "title": "秋日怀储嗣宗",
        "type": "七言绝句",
        "paragraph": [
            "故人北游久不回，塞雁南渡声何哀。",
            "相思闻雁更惆怅，却向单于台下来。"
        ],
        "translate": [
            "老朋友我北游已经很久没有回来,塞北的大雁向南飞去叫得多么悲哀!",
            "听到鸿雁南飞的消息更觉惆怅,这回我却要从单于台下来了。"
        ]
    },
    {
        "title": "夜听李山人弹琴",
        "type": "七言绝句",
        "paragraph": [
            "瑶琴夜久弦秋清，楚客一奏湘烟生。",
            "曲中声尽意不尽，月照竹轩红叶明。"
        ],
        "translate": [
            "夜已深了,瑶琴弹奏得瑟声清脆悦耳;楚地的客人一听琴声,湘水茫茫烟雾四起。",
            "这支曲子音调流畅,但意境却绵绵不绝。月光照着竹林的窗子,红叶在月光下更加明亮。"
        ]
    },
    {
        "title": "卖花者",
        "type": "五言诗",
        "paragraph": [
            "少壮彼何人，种花荒苑外。",
            "不知力田苦，却笑耕耘辈。",
            "当春卖春色，来往经几代。",
            "长安甲第多，处处花堪爱。",
            "良金不惜费，竞取园中最。",
            "一蕊才占烟，歌声已高会。",
            "自言种花地，终日拥轩盖。",
            "农夫官役时，独与花相对。",
            "那令卖花者，久为生人害。",
            "贵粟不贵花，生人自应泰。"
        ],
        "translate": [
            "年轻力壮的年轻人究竟是什么人呢?在荒凉的皇家园林里种花。",
            "不懂得种田的辛苦,却嘲笑那些辛勤耕耘的农民。",
            "在春天卖春色,来来往往的春花经历了几代?",
            "长安城中富丽堂皇的宅第很多,到处都盛开着美丽的花朵,令人喜爱。",
            "花费不少的良金,人们都争相去买园中最好的。",
            "一枝梅花刚刚占尽了烟雾,歌声已经在高空回荡。",
            "她自称是在种花的土地上,整天拥抱着华丽的车盖。",
            "农夫在服劳役的时候,独自与花相对。",
            "怎么能让卖花的人,长久地成为百姓的祸害呢?",
            "人们看重粮食而不看重鲜花,活着的人自然就应该平安无事。"
        ]
    },
    {
        "title": "近别",
        "type": "五言律诗",
        "paragraph": [
            "咫尺不相见，便同天一涯。",
            "何必隔关山，乃言伤别离。",
            "君心与我心，脉脉无由知。",
            "谁堪近别苦，远别犹有期。"
        ],
        "translate": [
            "两个人相隔近在咫尺,却不能见面,就好像天上和地上一样遥远。",
            "何必关山阻隔,就说我伤心别离。",
            "你的心和我的心,脉脉相承没有人知道。",
            "谁能忍受眼前的离别之苦,即使是远别的离别,也还是会有日期。"
        ]
    },
    {
        "title": "沧浪峡",
        "type": "五言诗",
        "paragraph": [
            "山下水声深，水边山色聚。",
            "月照秋自清，花名春不去。",
            "似非人间境，又近红尘路。",
            "乍入洞中天，更移云外步。",
            "我殊惺惺者，犹得沧浪趣。",
            "可以濯吾缨，斯言诚所慕。"
        ],
        "translate": [
            "山脚下水声响个不停,水边一望无际的青山簇拥而立。",
            "皎洁的月光照耀着秋天的景色自然是清明的,可是春天却没有开放的花朵在它面前盛开。",
            "这似乎不是人世间所能见到的景象,但它又近似尘世间的路途。",
            "我忽然进入了洞中的蓝天,脚步又移动到云层之外。",
            "我不同于那些虚怀若谷的人,仍然能领略到隐居山林的乐趣。",
            "可以用它来洗涤我的帽缨,这话我实在仰慕。"
        ]
    },
    {
        "title": "自渭南晚次华州",
        "type": "五言诗",
        "paragraph": [
            "前楼仙鼎原，西经赤水渡。",
            "火云入村巷，馀雨依驿树。",
            "我行伤去国，疲马屡回顾。",
            "有如无窠鸟，触热不得住。",
            "峨峨华峰近，城郭生夕雾。",
            "逆旅何人寻，行客暗中住。",
            "却思林丘卧，自惬平生素。",
            "劳役今若兹，羞吟招隐句。"
        ],
        "translate": [
            "从前楼登上仙鼎原,往西经过赤水渡。",
            "火焰般的乌云飘入村中的小巷,残余的雨滴落在驿站旁的树上。",
            "我独自一人在旅途感到离别家乡的伤感,疲惫的马儿不时地回头看。",
            "好比没有窝巢的鸟,一遇到酷热就不能停留。",
            "巍峨的华山近在眼前,夕阳西下,城墙上弥漫着迷蒙的雾气。",
            "旅店是谁去找的?是行路之客在暗中居住。",
            "回想起隐居在山林之中,觉得自己平生清白无为而感到很满足。",
            "劳役之苦如今竟是这样,我羞于吟诵《招隐》这首诗。"
        ]
    },
    {
        "title": "古思",
        "type": "五言律诗",
        "paragraph": [
            "春华惜妾态，秋草念妾心。",
            "始知井边桐，不如堂上琴。",
            "月落却羡镜，花飞犹委苔。",
            "门前长江水，一去终不回。"
        ],
        "translate": [
            "春天的花儿怜惜我的姿态,秋天的草儿思念我的心。",
            "这才知道井边的梧桐树,不如堂上的琴声美妙动听。",
            "月亮落下却羡慕明镜,花儿在空中飞舞还委弃在青苔上。",
            "门前那滔滔的长江水,一去永不回还。"
        ]
    },
    {
        "title": "古边卒思归",
        "type": "五言诗",
        "paragraph": [
            "有田不得耕，身卧辽阳城。",
            "梦中稻花香，觉后战血腥。",
            "汉武在深殿，唯思廓寰瀛。",
            "中原半烽火，此屋皆点行。",
            "边土无膏腴，闲地何必争。",
            "徒令执耒者，刀下死纵横。"
        ],
        "translate": [
            "我有田地却不能耕种,我躺在辽阳城里劳碌不堪。",
            "梦中只闻到稻花的芳香,醒来感觉到血腥味更浓。",
            "汉武帝高卧在深宫殿堂之上,心中只想着使天下大治。",
            "中原地区烽火连天,这里的房屋都点燃了烽火台。",
            "边疆的土地并不肥沃富饶,安闲无事又何必去争夺呢?",
            "白白地让那些拿着耒耜的人,在刀下被砍死的尸体纵横交错。"
        ]
    },
    {
        "title": "山中晚兴寄裴侍御",
        "type": "五言诗",
        "paragraph": [
            "雷息疏雨散，空山夏云晴。",
            "南轩对林晚，篱落新蛩鸣。",
            "白酒一樽满，坐歌天地清。",
            "十年身未闲，心在人间名。",
            "永怀君亲恩，久贱难退情。",
            "安得蓬丘侣，提携采瑶英。"
        ],
        "translate": [
            "雷声已经停息,稀疏的雨水也散了,空旷的山林中夏云密布,天气放晴。",
            "傍晚时分,我登上南边的窗子面对着树林,篱笆旁新传来蟋蟀的鸣叫声。",
            "满满一樽美酒,悠闲地坐着高歌,天地一片清明。",
            "十年来,我还没有闲过身子,心中一心想着人世间的名声。",
            "我永远怀念着您对我的恩惠,长期被您轻贱也难以排斥我的情怀。",
            "从哪里找来蓬莱仙山的伴侣,携手采撷瑶花?"
        ]
    },
    {
        "title": "题清上人",
        "type": "五言律诗",
        "paragraph": [
            "古院闭松色，入门人自闲。",
            "罢经来宿鸟，支策对秋山。",
            "客念蓬梗外，禅心烟雾间。",
            "空怜濯缨处，阶下水潺潺。"
        ],
        "translate": [
            "古老的庭院静静地关闭着松树的枝叶,进门的人觉得很安闲自在。",
            "诵读完毕,栖息在山林中的鸟儿飞来飞去;我拄着手杖,面对着秋日的群山。",
            "客居他乡的念头寄托在荒草野径之外,禅心却隐藏在烟雾弥漫的山林之中。",
            "徒然地怜悯那浣纱帽的地方,阶下的流水潺潺流淌。"
        ]
    },
    {
        "title": "漾陂晚望",
        "type": "五言律诗",
        "paragraph": [
            "远客家水国，此来如到乡。",
            "何人垂白发，一叶钓残阳。",
            "柳暗鸟乍起，渚深兰自芳。",
            "因知帝城下，有路向沧浪。"
        ],
        "translate": [
            "我是远方的异乡人,住在水乡,到这里来就像回到故乡一样。",
            "是谁垂下满头白发,在夕阳的余晖下垂钓呢?",
            "柳树昏暗鸟儿突然飞起,小洲深处兰花独自开得正芳。",
            "因此知道从长安城下,有条路通向沧浪。"
        ]
    },
    {
        "title": "登河中鹳雀楼",
        "type": "五言律诗",
        "paragraph": [
            "楼中见千里，楼影入通津。",
            "烟树遥分陕，山河曲向秦。",
            "兴亡留白日，今古共红尘。",
            "鹳雀飞何处，城隅草自春。"
        ],
        "translate": [
            "登上高楼远望千里,楼影映入水中的渡口。",
            "烟雾笼罩的树木远远地把陕州隔开,山河弯弯曲曲地向着秦国伸去。",
            "历史的兴亡只留下片刻的白日,从古到今人世间都是一样的红尘。",
            "鹳雀鸟在什么地方飞来飞去呢?城角的青草自是一片春意盎然。"
        ]
    },
    {
        "title": "隐者",
        "type": "五言律诗",
        "paragraph": [
            "松间开一径，秋草自相依。",
            "终日不冠带，空山无是非。",
            "投纶溪鸟伴，曝药谷云飞。",
            "时向邻家去，狂歌夜醉归。"
        ],
        "translate": [
            "松林间开辟出一条小路,秋天的野草在静静地依偎着我。",
            "我整天不戴帽子也不系带子,在空旷的山林里没有什么是非。",
            "在溪流中与鸟儿投下钓丝结伴而游,在山谷中曝晒着药草乌云四处飘飞。",
            "不时地到邻居家去,趁着夜晚狂歌一曲醉酒而归。"
        ]
    },
    {
        "title": "涂中寄薛中裕",
        "type": "五言律诗",
        "paragraph": [
            "贫交千里外，失路更伤离。",
            "晓泪芳草尽，夜魂明月知。",
            "空山连野外，寒鸟下霜枝。",
            "此景正寥落，为君玄发衰。"
        ],
        "translate": [
            "在千里之外的异乡结交一个贫穷的朋友,一旦迷失了道路就更使人伤感别离。",
            "拂晓时分我的眼泪已洒尽在芳草上,夜里我思念的心灵只有明月知道。",
            "一座座空旷的山峰连接着远处的荒野,寒冷的鸟儿飞下霜冻的树枝。",
            "我的容颜如今正处在一片寂寥的景象之中,我特意为你梳理一下头发,使它变得稀疏衰老。"
        ]
    },
    {
        "title": "晓过伊水寄龙门僧",
        "type": "七言律诗",
        "paragraph": [
            "龙门树色暗苍苍，伊水东流客恨长。",
            "病马独嘶残夜月，行人欲渡满船霜。",
            "几家烟火依村步，何处渔歌似故乡？",
            "山下禅庵老师在，愿将形役问空王。"
        ],
        "translate": [
            "龙门关外的树色一片苍茫,伊水滔滔东流我的愁恨绵绵不绝。",
            "病马独自嘶叫在残夜的月光下,远行的人们正要渡河,满船的霜雪已经结成一片。",
            "几户人家依傍着炊烟袅袅的村庄漫步,何处渔歌悠扬好像是故乡?",
            "山下的禅庵里,我的师傅还健在,我愿意用自己的形体去驱使和问候那无所作为的天帝。"
        ]
    },
    {
        "title": "送友人下第东游",
        "type": "五言律诗",
        "paragraph": [
            "出门皆有托，君去独何亲。",
            "阙下新交少，天涯旧业贫。",
            "烟寒岳树暝，雪后岭梅春。",
            "圣代留昆玉，那令愧郤诜。"
        ],
        "translate": [
            "出门在外都会有所嘱托,你离去又有什么可亲近的呢?",
            "京城里新结交的朋友很少,远在天涯的旧友也因贫困而贫穷。",
            "山上的树木笼罩在浓密的烟雾之中,天色已晚。雪后初放的山岭上,一株梅花绽放,一片春意盎然。",
            "圣明的时代留下了像昆玉一样的美玉,怎么能让郤诜那样的人感到惭愧呢?"
        ]
    },
    {
        "title": "南徐夕眺",
        "type": "五言律诗",
        "paragraph": [
            "行吟向暮天，何处不悽然？",
            "岸影几家柳，笛声何处船。",
            "楼分瓜步月，鸟入秣陵烟。",
            "故里无人到，乡书谁为传。"
        ],
        "translate": [
            "我一边走一边吟诗,一直到天色将晚,哪儿不感到悲伤凄凉呢?",
            "岸边的柳树影子映照着几户人家的房屋,远处传来阵阵笛声,仿佛是那艘坐落在岸上的船。",
            "月光从瓜步楼分开了,秣陵城的烟雾笼罩着鸟儿自由飞翔。",
            "故乡没有人到过,家乡的书信又有谁来为我传达呢?"
        ]
    },
    {
        "title": "江上秋夕",
        "type": "五言律诗",
        "paragraph": [
            "茂陵归路绝，谁念此淹留。",
            "极目月沈浦，苦吟霜满舟。",
            "孤猿啼后夜，久客病高秋。",
            "欲寄乡关恨，寒江无北流。"
        ],
        "translate": [
            "从茂陵返回的路已经断绝,有谁会想到我在这里滞留呢?",
            "极目远望,只见月亮隐没在水滨;我苦苦地吟诵着《霜满舟》这首诗。",
            "孤零零的猿猴在深夜里不停地啼叫,在这深秋高爽的季节我久客他乡得了重病。",
            "想要把家乡的遗憾寄托给远方的朋友,可惜这寒冷的江水不能向北流去。"
        ]
    },
    {
        "title": "白马津阻雨",
        "type": "七言律诗",
        "paragraph": [
            "津树萧萧旅馆空，坐看疏叶绕阶红。",
            "故乡千里楚云外，归雁一声烟雨中。",
            "漳浦病多愁易老，茂陵书在信难通。",
            "功名傥遂身无事，终向溪头伴钓翁。"
        ],
        "translate": [
            "渡口边的树木萧萧作响,旅店里一片空寂。我静静地坐着,看着稀疏的落叶,绕着台阶变红。",
            "故乡在千里之外的楚天云海之外,一声嘹亮的大雁从烟雨中归来。",
            "漳浦病多忧愁易于衰老,茂陵的书信虽在音信却难以相通。",
            "功名利禄如果能够随心所欲地得到实现,那么我终究会和溪头钓鱼的渔翁相伴。"
        ]
    },
    {
        "title": "山斋会别",
        "type": "五言律诗",
        "paragraph": [
            "春草平陵路，荷衣醉别离。",
            "将寻洛阳友，共结洞庭期。",
            "星月半山尽，天鸡出海迟。",
            "无轻此分手，他日重相思。"
        ],
        "translate": [
            "平陵路上长满了春草,穿着荷叶做的衣服喝得酩酊大醉才决定离开。",
            "我将要寻找到洛阳的朋友,与他相约在洞庭湖畔相会。",
            "月亮在半山腰上隐没了,天鸡从海上升起很晚才出来。",
            "不要轻易地放弃这次分手,以后会重新互相思念。"
        ]
    },
    {
        "title": "上巳日曲江有感",
        "type": "五言律诗",
        "paragraph": [
            "万花明曲水，车马动秦川。",
            "此日不得意，青春徒少年。",
            "晴沙下鸥鹭，幽沚生兰荃。",
            "向晚积归念，江湖心渺然。"
        ],
        "translate": [
            "弯弯曲曲的河道上,万花齐放,鲜艳夺目;秦川大地,车水马龙,波光粼粼。",
            "今天我不得意,青春不过是虚度光阴罢了。",
            "阳光照耀下沙滩上白鹭飞来飞去,幽静的沚水边长满了兰花和荃草。",
            "日暮时分,我深深地怀念着故乡,虽然漂泊江湖,但心中却依然渺然无依。"
        ]
    },
    {
        "title": "宫怨",
        "type": "七言绝句",
        "paragraph": [
            "柳色参差掩画楼，晓莺啼送满宫愁。",
            "年年花落无人见，空逐春泉出御沟。"
        ],
        "translate": [
            "参差不齐的柳色掩映着华丽的画楼,早晨的黄莺婉转地啼叫着送走了满宫的忧愁。",
            "年复一年,暮春时节百花凋零无人欣赏,白白地漂浮在御沟里流淌。"
        ]
    },
    {
        "title": "观郊礼",
        "type": "七言绝句",
        "paragraph": [
            "钟鼓旌旗引六飞，玉皇初著画龙衣。",
            "泰坛烟尽星河晓，万国心随彩仗归。"
        ],
        "translate": [
            "玉皇大帝开始穿着画龙衣裳飞升天宫,敲响钟鼓挥动旌旗率领六军南下。",
            "泰坛上的炊烟已经散尽,银河也已破晓。万国之心都随着朝廷的仪仗凯旋而归。"
        ]
    }
]