[
    {
        "title": "送危方逸之京",
        "type": "七言律诗",
        "paragraph": [
            "石门江上送危郎，好上神京北斗旁。",
            "汉代文章须贾马，周家道德并虞唐。",
            "柳林马过沉云黑，沙碛驼鸣落日黄。",
            "为计游程二千里，朔风吹雪正茫茫。"
        ],
        "translate": [
            "在石门江上送别高官厚禄的郎君,最好是登上神京站在北斗星旁。",
            "汉代的文人墨客需要像贾谊、司马相如那样有才华,周代的道德风尚和虞舜、唐尧时代一样完美无缺。",
            "柳树林里的马儿在黑暗中奔驰,沙漠边上骆驼在落日的余晖中嘶鸣。",
            "估计这二千里的路程,却正好是北风大作,狂风大作,雪花纷纷扬扬。"
        ]
    },
    {
        "title": "二银女祠",
        "type": "五言诗",
        "paragraph": [
            "银冶二女祠，抚州之金溪。",
            "其家姓葛氏，无字年未笄。",
            "羞颜不出户，宛娈守礼仪。",
            "在唐宝历岁，其父为胥吏。",
            "官家起银场，日夜遭箠楚。",
            "勤红问父苦，玉颊啼朱雨。",
            "父命斯易活，誓以死相许。",
            "禽兽尚知义，报父宁死心。",
            "投身入银冶，遂化成白金。",
            "郡县惊且叹，奏名上朝端。",
            "下诏罢炉冶，鸡犬皆平安。",
            "已经五百岁，历历人犹传。",
            "荒祠俯流水，像设还俨然。",
            "世间尽儿女，此事谁能前？",
            "缇萦费娥去，未有堪比伦。",
            "可比惟英皇，双魂抱烦冤。",
            "至今湘江竹，出土含泪痕。"
        ],
        "translate": [
            "抚州的金溪有两位冶炼女工的祠庙,她们修炼的铜冶炼出来的矿石就在这座金溪。",
            "他家姓葛,没有字,年纪还不到二十岁。",
            "容貌丑陋的人不愿出门,温文尔雅地遵守礼仪。",
            "在唐朝宝历年间,他的父亲做过一个小吏。",
            "官府兴建了冶炼银子的场地,人们日夜都要遭到刑杖的拷打。",
            "红梅勤劳地问候父亲的疾苦,泪水打湿了红梅的脸颊,好似在哭泣。",
            "承受父亲的旨意才容易获得生路,发誓要以死相许。",
            "禽兽尚且懂得道义,为报答父亲宁愿以死相报。",
            "投身到冶炼银子的地方,很快就变成了白银。",
            "郡县官吏对此感到震惊和叹息,纷纷将名单上报给朝廷。",
            "唐玄宗颁布诏书,命令停止冶炼铁炉,这样一来,家里的鸡犬都平安无事了。",
            "现在已经五百多年了,历代的名人还在不停地流传着。",
            "荒废的祠堂俯视着流水,祭祀的塑像还是那么庄严肃穆。",
            "世上的人都不过是儿女罢了,这件事有谁能够办到呢?",
            "缇萦和费娥都已逝去,再也没有人能与她们相比。",
            "可以和她相比的只有英明的君主,可惜她的双魂却怀有许多烦恼冤屈。",
            "到现在湘江边的竹子,出土后还留有遗泪的痕迹。"
        ]
    }
]