[
    {
        "title": "扇图",
        "type": "七言绝句",
        "paragraph": [
            "云压溪塘小雪春，融融和气浥轻尘。",
            "山禽共作梅花梦，物性由来懒是真。"
        ],
        "translate": [
            "乌云密布在溪塘上,一场小雪迎接着春天的到来,融融的春风吹散了轻尘。",
            "山中的鸟儿都在做梅花盛开的梦,它们的本性本来就是懒洋洋的,这才是真正的梅花啊!"
        ]
    },
    {
        "title": "被召过少室",
        "type": "七言绝句",
        "paragraph": [
            "老病无堪合退休，伊川久巳得菟裘。",
            "如今又上长安道，好被青山笑白头。"
        ],
        "translate": [
            "我年老多病,实在不配再出来做官了,已经在伊川得到一件裘皮制成的衣服了。",
            "今天又登上了通往长安的大道,我真想被青山嘲笑,使我白发苍苍。"
        ]
    }
]