[
    {
        "title": "青铜峡",
        "type": "七言绝句",
        "paragraph": [
            "青铜峡口过轻舟，百八亭亭塔影浮。",
            "奇绝两山中擘处，黄河千古自东流。"
        ],
        "translate": [
            "从青铜峡口划过小船,只见百八亭亭玉立的塔影在水面上浮动。",
            "那两座山从中间裂开,雄伟壮丽的地方,黄河滔滔千古不绝地向东奔流。"
        ]
    },
    {
        "title": "题鸣沙城",
        "type": "七言绝句",
        "paragraph": [
            "蹀躞霜蹄沙自鸣，环州形胜旧隋城。",
            "云楼壮压河流激，时听蛟龙怒吼声。"
        ],
        "translate": [
            "行走在霜雪覆盖的路上,脚步声在沙滩上自然地响起,环绕着州城的地形胜过旧时的隋城。",
            "高耸入云的楼阁威严雄壮,河水汹涌澎湃,不时地传来蛟龙怒吼之声。"
        ]
    },
    {
        "title": "宿虞山逍遥游是先文靖公读书馆",
        "type": "五言律诗",
        "paragraph": [
            "萧然一丘壑，明哲此幽栖。",
            "墙借悬崖匝，轩因荫桂低。",
            "月明松鼠啸，林暗草虫啼。",
            "烦抱清风涤，中宵梦不迷。"
        ],
        "translate": [
            "山丘沟壑一片萧条,贤明的君主就住在这里幽静地栖身。",
            "墙借着悬崖环绕,窗户因为桂树的树荫低垂。",
            "明亮的月光下,松鼠发出凄厉的叫声;幽暗的树林里,草虫在不停地啼叫。",
            "烦闷之情怀抱着清风来进行洗涤,半夜里做梦却没有迷路。"
        ]
    },
    {
        "title": "客夜",
        "type": "五言律诗",
        "paragraph": [
            "一身镫共影，相对亦何为。",
            "世故天涯见，乡心岁暮知。",
            "虚窗落残月，宿鸟动寒枝。",
            "容易明朝看，萧萧生鬓丝。"
        ],
        "translate": [
            "像镫子一样的身子与影子相伴,互相对望又有什么意义呢?",
            "世间的往事远隔天涯却能见到,思乡之情到了晚年才能领悟。",
            "虚空的窗户上落下残月,栖息在树枝上的鸟儿在寒冷的树枝上飞动。",
            "明天早晨一看,满头白发萧萧生出两鬓斑痕。"
        ]
    }
]