[
    {
        "title": "兴平",
        "type": "七言绝句",
        "paragraph": [
            "棠梨瑟瑟水无波，词客千秋托兴多。",
            "汉庙唐陵残照里，路人偏指马嵬坡。"
        ],
        "translate": [
            "棠梨花瑟瑟开放,清澈的河水静静地流淌着,文人雅士千秋万代都来寄托情怀。",
            "夕阳的余晖洒在汉庙和唐尧的陵墓上,路上的行人偏偏指向马嵬坡。"
        ]
    },
    {
        "title": "宝鸡",
        "type": "七言绝句",
        "paragraph": [
            "矗矗西山万玉篸，塔河津渡晓霜含。",
            "樵夫指点秋林外，桥栈连云三十三。"
        ],
        "translate": [
            "西山高耸入云,犹如万道玉篸;塔河渡口清晨满含霜露。",
            "樵夫在秋天的树林外指点着,那座连绵不断的桥梁和栈道有三十三座。"
        ]
    },
    {
        "title": "沔阳谒诸葛武侯祠",
        "type": "七言律诗",
        "paragraph": [
            "遭逢鱼水自南阳，将相才兼管乐长。",
            "祠树能回万牛首，臣家本有百株桑。",
            "卧龙地近乡山古，筹笔人遥驿路荒。",
            "庙貌嵯峨一瞻拜，到门沔水鉴清光。"
        ],
        "translate": [
            "从南阳我与你相逢,你有将相之才,又能管乐而长。",
            "祭祀的桑树能挽回一万头牛的脑袋,我家本来就有一百棵桑树。",
            "我的家乡离卧龙山很近,但这里的山还很古老,我这个筹划文书的人却在遥远的驿道上,路途太荒凉。",
            "古庙巍峨壮观一瞻仰,到庙门前沔水清澈明净光照四方。"
        ]
    },
    {
        "title": "春草",
        "type": "七言律诗",
        "paragraph": [
            "不辨江蓠与杜蘅，东风吹处一时生。",
            "西河冉冉寻芳路，南浦萋萋送客情。",
            "细雨迷离添杳霭，夕阳掩映更分明。",
            "垂鞭最忆花时节，河畔青青纵马行。"
        ],
        "translate": [
            "分不清江蓠和杜蘅,都是在春风吹拂下一齐盛开。",
            "沿着西河缓缓前行寻找芳草萋萋的河道,南浦长满了繁茂的野草送走了远行的客人。",
            "细雨迷离,增添了层层云气,夕阳的余晖掩映着天空,显得格外分明。",
            "策马垂鞭最是怀念花开时节,河畔春意盎然纵马驰骋。"
        ]
    },
    {
        "title": "铜雀台",
        "type": "七言律诗",
        "paragraph": [
            "台荒人去杳难留，遗迹苍茫不可求。",
            "当日桥陵尽西望，于今漳水自东流。",
            "香消罗绮寒云合，地歇笙歌野草秋。",
            "毕竟君王归未得，空余烟外夕阳愁。"
        ],
        "translate": [
            "高台已经荒凉,人已离去,杳无踪迹,难以再留。遗迹苍茫,无法寻觅。",
            "当年从桥陵一直向西眺望,到现在漳水却依旧向东流。",
            "香消玉殒的罗绮已经散尽,寒云又聚合在一起;笙歌停歇了,秋天的野草也变得枯萎。",
            "君王啊,你最终还是没有归来,只剩下夕阳余晖洒在烟雾缭绕的天边,引起我无限的忧愁。"
        ]
    },
    {
        "title": "金山",
        "type": "七言律诗",
        "paragraph": [
            "雪浪东来万里流，孤悬金碧照沧洲。",
            "秋生极浦平分外，人语诸天最上头。",
            "京口帆樯残照远，海门烟树落潮浮。",
            "六朝遗迹知多少，付与诗人一倚楼。"
        ],
        "translate": [
            "滚滚的雪浪从东方涌来,向万里之外奔流;它孤零零地悬挂着,闪耀着金色和碧绿的光芒,映照在辽阔的沙洲上。",
            "秋天降临在极远的水边平分之外,人们说秋天的最高处是天上头。",
            "京口的帆船在夕阳的余晖中渐渐向远处驶去,海门关前的树木在潮水的消散和沉浮下显得格外凄清。",
            "六朝的遗迹不知有多少呢?现在就让诗人在这高楼上独自凭栏远眺。"
        ]
    },
    {
        "title": "蒲州",
        "type": "五言律诗",
        "paragraph": [
            "龙门一曲处，风气萃蒲津。",
            "关险全临晋，山形半入秦。",
            "楼窥飞鸟上，柏郁大河滨。",
            "祇有重华日，环回万古新。"
        ],
        "translate": [
            "在龙门山弯弯曲曲的地方,清风吹拂着蒲津渡口的风光。",
            "函谷关的险要之处一直延伸到晋国边境,山势却一半被秦国夺取了过来。",
            "登上高楼从飞鸟之上远望,河边长满了郁郁苍苍的柏树和郁林。",
            "只有重阳节这一天,它环绕着大地,呈现出万古千秋的全新景象。"
        ]
    },
    {
        "title": "乌夜啼",
        "type": "七言律诗",
        "paragraph": [
            "白日已尽庭栖乌，将子八九名相呼。",
            "曲房沈沈绮疏闭，流苏宝帐宵眠孤。",
            "一啼烛泪红珠滴，再啼月落青林黑。",
            "啼到天明窥镜奁，乌头未白人头白。"
        ],
        "translate": [
            "太阳已经落山了,庭院里栖息着的乌鸦,它们一个个地叫着自己的小鸟儿的名字。",
            "幽静的小屋里,绮罗窗户紧紧关上,独守空房,手执流苏和宝帐,夜里独自睡去。",
            "她在烛光下哭泣,泪水像红珠一样滴落;她在月亮落下的夜晚再次哭泣,青林一片漆黑。",
            "哭到天亮时,我偷偷地看着镜子,发现乌鸦的头还未变白,而我的头却已经变白。"
        ]
    },
    {
        "title": "九折坂",
        "type": "五言诗",
        "paragraph": [
            "蜀险历益奇，卬崃扩西臂。",
            "昔年峻坂名，九折今躬莅。",
            "冰凌夏犹结，况躔婺女次。",
            "鞚冻支策登，列骑束如猬。",
            "鼓勇跻其颠，雺雾开目眦。",
            "群山次第出，俯瞰等平地。",
            "豁达关徼通，华羌指掌视。",
            "如披枕秘书，标新复领异。"
        ],
        "translate": [
            "蜀地经历的艰难险阻更加奇特,卬崃山巍峨雄伟拓展了西边的疆域。",
            "当年登临险峻的山坡早已闻名,今天我亲临九转弯处的山坡已然历尽艰难。",
            "冰雪凌驾在夏天仍然会冻结,更何况是婺女走在最下层呢。",
            "战马冻僵了,拄着拐杖登上城墙,队列中的骑兵像刺猬一样被捆绑起来。",
            "鼓足勇气登上山顶,浓雾散开眼睛睁开双眼。",
            "群山依次伸展出来,从远处俯瞰就像站在平地上一样。",
            "函谷关与边塞相通,华夏和羌族人可以指手可得。",
            "就像披开枕头翻阅经史典籍,读起来既觉得新颖有趣又领悟到新的道理。"
        ]
    },
    {
        "title": "西安",
        "type": "五言诗",
        "paragraph": [
            "横鞭上灞桥，回眺秦封域。",
            "五纬非昔辉，八川犹湜湜。",
            "林表隐终南，高秀仙都匹。",
            "绵延带埤堄，平掌对门阈。",
            "遥想虎踞年，雄视小八极。",
            "缇绣大照耀，土木天偪仄。",
            "五陵竞豪奢，九衢恣崇饰。",
            "香车斗风游，华屋鸣钟食。",
            "王气盛蓟门，鹑野遂寡色。",
            "当年西笑人，回望燕台日。"
        ],
        "translate": [
            "横鞭策马登上灞桥,回头眺望秦朝的疆域。",
            "五星和北斗星已经不是往日的光辉了,八条河流仍然在不停地奔流不息。",
            "林表隐居在终南山上,他的风采高雅秀美可与仙女们相媲美。",
            "弯弯曲曲的小路环绕着陡峭的山堄,门坎上我拱手行走面对着门槛。",
            "遥想当年猛虎盘踞在天上,雄视八方极远无边。",
            "灿烂的阳光照耀着华丽的丝织品,高耸入云的土木建筑仿佛要被天所阻挡。",
            "皇宫和五陵竞相奢华,大街小巷恣意修饰豪华。",
            "华丽的车子在微风中自由自在地行走,豪华的房屋里传来悠扬的钟声供人饮宴吃饭。",
            "蓟门的王气正旺盛,鹌鹑在野外嬉戏,神色顿时变得孤单寡闻。",
            "当年在西边嘲笑我的时候,回头眺望那燕台的太阳。"
        ]
    }
]