[
    {
        "title": "外子辞昌延榷务归里喜面赋此四首",
        "type": "七言诗",
        "paragraph": [
            "十载京华鬓未丝，归来笑语共相嬉。",
            "田园乐趣家庭福，侥倖年来事事宜。",
            "当年抑塞事难忘，双凤腾空恨渺茫。",
            "留得青山终不老，阶前玉树已成行。",
            "一径蒿莱手自锄，小园花木已扶疏。",
            "自甘荆布心如水，不羡繁华戚里居。",
            "举杯又见月当头，竟夕清谈互唱酬。",
            "出处何如安处好，鹿车鸿案自风流。"
        ],
        "translate": [
            "呆呆呆呆呆呆呆呆呆呆呆呆呆呆呆呆呆呆呆呆呆呆呆呆在京城十多年了,回到了家乡和朋友们谈笑风生,共同欢乐。",
            "田园的乐趣是家庭的福分,希望今年一切事情都办得恰到好处。",
            "当年在边塞的艰难困苦中被俘获的事我永远难以忘怀,像那双凤凰飞向遥远的天空,使我的遗憾变得渺茫无穷。",
            "留得青山终究不会衰老,台阶前的玉树已经长成行。",
            "一条小路边长满了野蒿,我亲手把它锄掉;小小的园子里花草树木也已经渐渐稀疏。",
            "我甘愿身穿荆棘布衣而心如水,不羡慕富贵荣华的戚里之居。",
            "举起酒杯又看见皎洁的月亮正好挂在头上,我们整夜在一起清谈,互相唱着歌相互赠送。",
            "出门与隐居哪样好呢?坐着鹿车,坐在鸿雁的案桌上自然是风流。"
        ]
    },
    {
        "title": "依韵答外子寄怀诗二首",
        "type": "七言律诗",
        "paragraph": [
            "去住京华年复年，沧桑未缓祖生鞭。",
            "漫将迟暮伤蒲柳，事业从今定胜前。",
            "山城料得多孤寂，两地情怀各自知。",
            "一瓣心香君健饭，耦耕有日漫相思。"
        ],
        "translate": [
            "离开和留在京城一年又一年,岁月流逝却没有放松祖逖为我赶路的马鞭。",
            "白白地让迟暮之年伤心蒲柳,从今以后的事业一定胜过以前。",
            "我料想你住在深山老城中一定非常孤寂,两地的情怀各有各的区别。",
            "一朵花瓣散发出阵阵香味,希望你能好好地吃饱饭。我和你一起耕作的日子里,只能徒然地思念着你。"
        ]
    },
    {
        "title": "咏史十首 杨妃",
        "type": "五言诗",
        "paragraph": [
            "宠赐温泉浴，长生记定情。",
            "忽惊鼙鼓至，空自玉颜倾。",
            "卧虎识英雄，沙场立大功。",
            "蛾眉能奋武，桴鼓助元戎。",
            "续史成兄志，经师重汉宫。",
            "上书因雁序，孝友仰家风。",
            "一曲琵琶怨，伤心别汉宫。",
            "回头望故国，日暮白云空。",
            "御赐书成诵，黄金赎魏公。",
            "至今边塞上，茄拍和秋风。",
            "咏絮才无匹，深闺独擅奇。",
            "青绫围解处，佳客竟无辞。",
            "巾帼全忠孝，辞亲跨锦鞯。",
            "功成归绣阁，奇事至今传。",
            "失节心深愧，蛾眉锁日颦。",
            "本来倾国貌，寂寞也生春。",
            "一曲琴心递，潜奔邸舍时。",
            "求凰虽遂愿，名节已全亏。",
            "一笑能倾国，夫差宠遇隆。",
            "至今吴士女，犹说馆娃宫。"
        ],
        "translate": [
            "皇上恩赐我温泉沐浴,让我长生不老记住这份心意。",
            "忽然间战鼓声传来,使人感到震惊,不由得脸色顿时变白。",
            "卧虎能识别英雄,在战场上立下大功。",
            "美人的眉毛能奋勇挥舞武力,敲响桴鼓协助统帅大军作战。",
            "续写史书完成哥哥的志向,经学大师看重汉代的宫殿。",
            "我写了一篇《上书》给大雁作序,孝顺父母和友爱兄弟都仰慕家乡的风范。",
            "听到一曲《琵琶行》的哀怨之音,伤心离别了汉宫。",
            "回头眺望故乡,暮色中白云飘荡一片空旷。",
            "魏公把皇帝赏赐给他的书读完了,就用黄金来赎回了魏公。",
            "一直到现在,在边塞上,人们还在采茄和秋风中享受着这美好的时光。",
            "吟咏柳絮的才华没有人能与之匹敌,只有在深闺里她才能独具奇特。",
            "当青色绫罗的围裙被解开的时候,美丽的客人竟然毫不推辞地走了。",
            "年轻力壮的妇女要竭尽忠孝,告别双亲就要跨上锦缎做的褥子。",
            "建功立业之后,他把绣阁的神主归还给皇上,他的奇事至今还在世间流传。",
            "因为失去节操而心中深感惭愧,整天紧锁的眉毛在皱纹中皱起。",
            "柳树本来就是倾国倾城的姿态,尽管寂寞却能生出春色来。",
            "弹奏一曲美妙的琴声,我的心思随着琴声流转。我悄悄地跑到你住过的客舍去吧。",
            "我虽然实现了追求凤凰的愿望,但是名声和节操已经全都丧失了。",
            "一笑就能使国家倾覆,吴王夫差得到的宠爱和礼遇真是太隆重了。",
            "到现在吴地的男女老少,还在谈论馆娃宫的事。"
        ]
    },
    {
        "title": "久雨初晴",
        "type": "五言绝句",
        "paragraph": [
            "阴雨连绵下，檐前溜滴声。",
            "今朝天忽霁，日照满窗晴。"
        ],
        "translate": [
            "阴雨连绵不断地下个不停,屋檐下滴水声阵阵传来。",
            "今天忽然间天色放晴,阳光照耀着窗户,一片晴朗。"
        ]
    },
    {
        "title": "月色",
        "type": "五言绝句",
        "paragraph": [
            "百鸟声俱绝，长空月正横。",
            "窗前如白日，云尽倍光明。"
        ],
        "translate": [
            "百鸟的鸣叫声全都断绝了,天空中的明月正好横在天上。",
            "窗前像白天一样明亮,云层消散后一轮新月升起,比平时更亮了。"
        ]
    },
    {
        "title": "即景",
        "type": "五言绝句",
        "paragraph": [
            "四月天光好，韶华丽景多。",
            "蔷薇娇欲滴，佳节正清和。"
        ],
        "translate": [
            "四月的天气多么美好,一年中最美好的景象很多。",
            "蔷薇花娇艳欲滴,在这美好的节日里,天气清明和暖。"
        ]
    },
    {
        "title": "蔷薇",
        "type": "五言绝句",
        "paragraph": [
            "院外蔷薇好，风吹扑面芳。",
            "摘来瓶内供，馥郁似兰香。"
        ],
        "translate": [
            "庭院外蔷薇花格外美丽,春风吹来,扑面而来,散发着阵阵清香。",
            "摘下来放入瓶中供品,味道醇厚馥郁有如兰花的芳香。"
        ]
    },
    {
        "title": "夏雨",
        "type": "五言绝句",
        "paragraph": [
            "细雨窗前落，刚逢四月朝。",
            "无边生众绿，瑟瑟上芭蕉。"
        ],
        "translate": [
            "细雨从窗户前洒落,刚好赶上四月的清晨。",
            "无边无际的树木都长满了绿色,连绵不断地生长在芭蕉叶上。"
        ]
    },
    {
        "title": "夏日",
        "type": "五言绝句",
        "paragraph": [
            "夏日诚堪畏，朝来照满扉。",
            "行天如火赤，愈觉助炎威。"
        ],
        "translate": [
            "炎热的夏天实在令人害怕,清晨起来阳光照得门窗通红。",
            "烈火在天上燃烧,红得像火一样,人们越发感觉到它助长了炎热的威力。"
        ]
    },
    {
        "title": "咏史十首 其一 杨妃",
        "type": "五言绝句",
        "paragraph": [
            "宠赐温泉浴，长生记定情。",
            "忽惊鼙鼓至，空自玉颜倾。"
        ],
        "translate": [
            "皇上恩赐我温泉沐浴,让我长生不老记住这份心意。",
            "忽然间战鼓声传来,使人感到震惊,不由得脸色顿时变白。"
        ]
    },
    {
        "title": "咏史十首 其二 梁夫人",
        "type": "五言绝句",
        "paragraph": [
            "卧虎识英雄，沙场立大功。",
            "蛾眉能奋武，桴鼓助元戎。"
        ],
        "translate": [
            "卧虎能识别英雄,在战场上立下大功。",
            "美人的眉毛能奋勇挥舞武力,敲响桴鼓协助统帅大军作战。"
        ]
    },
    {
        "title": "咏史十首 其三 曹昭",
        "type": "五言绝句",
        "paragraph": [
            "续史成兄志，经师重汉宫。",
            "上书因雁序，孝友仰家风。"
        ],
        "translate": [
            "续写史书完成哥哥的志向,经学大师看重汉代的宫殿。",
            "我写了一篇《上书》给大雁作序,孝顺父母和友爱兄弟都仰慕家乡的风范。"
        ]
    },
    {
        "title": "咏史十首 其四 昭君",
        "type": "五言绝句",
        "paragraph": [
            "一曲琵琶怨，伤心别汉宫。",
            "回头望故国，日暮白云空。"
        ],
        "translate": [
            "听到一曲《琵琶行》的哀怨之音,伤心离别了汉宫。",
            "回头眺望故乡,暮色中白云飘荡一片空旷。"
        ]
    },
    {
        "title": "咏史十首 其五 蔡文姬",
        "type": "五言绝句",
        "paragraph": [
            "御赐书成诵，黄金赎魏公。",
            "至今边塞上，茄拍和秋风。"
        ],
        "translate": [
            "魏公把皇帝赏赐给他的书读完了,就用黄金来赎回了魏公。",
            "一直到现在,在边塞上,人们还在采茄和秋风中享受着这美好的时光。"
        ]
    },
    {
        "title": "咏史十首 其六 谢道韫",
        "type": "五言绝句",
        "paragraph": [
            "咏絮才无匹，深闺独擅奇。",
            "青绫围解处，佳客竟无辞。"
        ],
        "translate": [
            "吟咏柳絮的才华没有人能与之匹敌,只有在深闺里她才能独具奇特。",
            "当青色绫罗的围裙被解开的时候,美丽的客人竟然毫不推辞地走了。"
        ]
    },
    {
        "title": "咏史十首 其七 木兰",
        "type": "五言绝句",
        "paragraph": [
            "巾帼全忠孝，辞亲跨锦鞯。",
            "功成归绣阁，奇事至今传。"
        ],
        "translate": [
            "年轻力壮的妇女要竭尽忠孝,告别双亲就要跨上锦缎做的褥子。",
            "建功立业之后,他把绣阁的神主归还给皇上,他的奇事至今还在世间流传。"
        ]
    },
    {
        "title": "咏史十首 其八 息夫人",
        "type": "五言绝句",
        "paragraph": [
            "失节心深愧，蛾眉锁日颦。",
            "本来倾国貌，寂寞也生春。"
        ],
        "translate": [
            "因为失去节操而心中深感惭愧,整天紧锁的眉毛在皱纹中皱起。",
            "柳树本来就是倾国倾城的姿态,尽管寂寞却能生出春色来。"
        ]
    },
    {
        "title": "咏史十首 其九 卓文君",
        "type": "五言绝句",
        "paragraph": [
            "一曲琴心递，潜奔邸舍时。",
            "求凰虽遂愿，名节已全亏。"
        ],
        "translate": [
            "弹奏一曲美妙的琴声,我的心思随着琴声流转。我悄悄地跑到你住过的客舍去吧。",
            "我虽然实现了追求凤凰的愿望,但是名声和节操已经全都丧失了。"
        ]
    },
    {
        "title": "咏史十首 其十 西施",
        "type": "五言绝句",
        "paragraph": [
            "一笑能倾国，夫差宠遇隆。",
            "至今吴士女，犹说馆娃宫。"
        ],
        "translate": [
            "一笑就能使国家倾覆,吴王夫差得到的宠爱和礼遇真是太隆重了。",
            "到现在吴地的男女老少,还在谈论馆娃宫的事。"
        ]
    },
    {
        "title": "寄怀莲荪姊",
        "type": "五言律诗",
        "paragraph": [
            "记得同居日，相携笑语投。",
            "随肩常伴读，握手共閒游。",
            "未别心先醉，临歧泪满流。",
            "何时重聚首，并坐诉离愁。"
        ],
        "translate": [
            "还记得我们一起生活的时候,互相携带着笑语嬉闹交谈。",
            "肩膀上常常陪伴着我读书,握着手一起悠闲地游玩。",
            "还没等到分别心已沉醉,临近分手泪水满面流淌。",
            "什么时候我们才能再次聚首,一起坐着倾诉离别的愁绪。"
        ]
    },
    {
        "title": "望慈亲回署",
        "type": "五言律诗",
        "paragraph": [
            "慈母还乡日，于今数月离。",
            "晨昏增孺慕，风雨阻归期。",
            "少小常相侍，暌违愈觉思。",
            "何时回濑水，谨奉洗尘卮。"
        ],
        "translate": [
            "从我慈母回乡的那一天开始,到现在已经几个月没有见到她了。",
            "从早到晚,我对孩子更加思念,风雨交加,阻断了回家的日期。",
            "从小我就常常陪伴你,每次离开你我越发觉得思念你。",
            "何时才能把河中的清水倒入江中呢?我恭敬地捧上洁净的酒杯,以便洗涤尘土。"
        ]
    },
    {
        "title": "暑夜玩月不寐",
        "type": "五言律诗",
        "paragraph": [
            "皎皎晴天月，今宵喜又圆。",
            "无灯辉自满，有树影常穿。",
            "为爱频留盼，因炎愈怕眠。",
            "一轮如赤日，冷署也烘然。"
        ],
        "translate": [
            "晴空万里,一轮明月皎洁照耀,今天晚上又喜出望外,好一个圆满的圆月。",
            "夜晚没有灯,月光照得满屋都是,只有树影在月光下时时穿过。",
            "为了喜爱你我频频地注视着你,因为天气越发炎热我越发害怕睡觉。",
            "月亮像红日一样明亮,即使在寒冷的官署里,也显得温暖而温热。"
        ]
    },
    {
        "title": "学署废园即景",
        "type": "五言律诗",
        "paragraph": [
            "半亩园虽小，徘徊景亦清。",
            "榴花红日映，蔬菜绿畦平。",
            "灌溉人宜力，栽培物自荣。",
            "梧桐荫满径，风透袷衣轻。"
        ],
        "translate": [
            "半亩大的园子虽然狭小,但在园中徘徊,看到的景致还是那样的清丽。",
            "红日当空,石榴花在阳光的照耀下灿烂绽放,菜园里的绿肥红瘦,一片平坦。",
            "用水浇灌,人们应当尽力去浇灌;培育万物,自然会滋长发达。",
            "梧桐树荫遮盖了小路,微风吹拂着单薄的衣衫,显得格外轻盈。"
        ]
    },
    {
        "title": "七夕",
        "type": "五言律诗",
        "paragraph": [
            "玉露金风夜，良宵七夕宜。",
            "人间逢令节，天上亦佳期。",
            "银汉填桥候，琼筵设果时。",
            "穿针思乞巧，月影小楼移。"
        ],
        "translate": [
            "金风习习的七夕佳节,像玉露那样清凉爽朗,这美好的夜晚特别适宜。",
            "人世间每逢美好的节日,天上也总有美好的时节。",
            "银白色的银河填满了桥梁等待着,豪华的筵席上摆上了丰盛的果品。",
            "思妇在小楼上穿针乞巧,月影随着小楼的移动而移动。"
        ]
    },
    {
        "title": "中秋",
        "type": "五言律诗",
        "paragraph": [
            "一样团圞月，今宵觉倍明。",
            "登楼怀谢脁，泛渚忆袁宏。",
            "镜喜菱花澈，轮看桂子盈。",
            "家家当此际，瓜果满筵呈。"
        ],
        "translate": [
            "月亮像一团圆月,今天晚上觉得比昨天还要明亮。",
            "登上高楼怀念谢脁,在沙洲上泛舟思念袁宏。",
            "镜子喜欢菱花清澈见底,转眼间又看到满地桂树的果实。",
            "家家都在农忙时节,盛满了筵席,摆满了瓜果。"
        ]
    },
    {
        "title": "重阳",
        "type": "五言绝句",
        "paragraph": [
            "节已重阳近，登高共举觞。",
            "茱萸应遍插，菊放几枝黄。"
        ],
        "translate": [
            "重阳佳节临近,大家登上高处共同举杯庆贺。",
            "茱萸应该全都插好,菊花也该开出几枝嫩黄的花朵。"
        ]
    },
    {
        "title": "望雪",
        "type": "五言律诗",
        "paragraph": [
            "未下霏霏雪，遥空属望奇。",
            "天光何黯淡，云影亦迷离。",
            "消息连朝递，般勤几度思。",
            "寻梅清兴动，个里好吟诗。"
        ],
        "translate": [
            "大雪还没有下完,我独自一人在遥远的天空中凝望着奇异景象。",
            "天空的月光多么的暗淡,云彩的影子也显得格外迷离。",
            "消息一个个早晨传来,像我这样辛勤地思考了多少次。",
            "寻觅到清幽的梅花让我的兴致勃发,这地方特别适合我吟诗。"
        ]
    },
    {
        "title": "感怀四首 其一",
        "type": "七言律诗",
        "paragraph": [
            "闺中乐事记髫年，同侍重闱得爱怜。",
            "累叶清芬绵孝弟，一门和蔼胜神仙。",
            "庭前玉树枝枝秀，林下琼花朵朵妍。",
            "最好藏书楼畔坐，惠峰晴翠扑帘前。"
        ],
        "translate": [
            "闺房中最快乐的事情是记住小孩子,他们一起陪伴着我进入了重闱,受到我的喜爱和怜爱。",
            "几代子孙家风清雅,孝顺父母,友爱兄弟,一家人和睦相处,胜过神仙。",
            "庭院前的玉树枝枝秀美,林下的琼花朵朵鲜艳美丽。",
            "在藏书楼畔最适宜坐着,阳光下惠山的翠绿扑打在帘子前面。"
        ]
    },
    {
        "title": "感怀四首 其二",
        "type": "七言律诗",
        "paragraph": [
            "濑水前游迹已陈，十年冷署梦尘尘。",
            "春风教士心堪白，夜雨横经意倍殷。",
            "小乐园林饶兴趣，天生花草亦精神。",
            "绛纱惯向慈帏立，手把吟篇问字频。"
        ],
        "translate": [
            "昔日在濑水边游玩过的足迹早已陈列,十年来冷清的官署里梦中也只见到尘土飞扬。",
            "春风吹拂让人心灰意冷,夜晚的雨不停地下着,使人倍感忧愁。",
            "小小的园林里充满了无限的乐趣,自然而然地产生出许多花草,使人倍感兴致。",
            "身着深红色的纱窗,整天站在慈祥的帏帐旁,手里拿着诗篇,频频地问我写什么。"
        ]
    },
    {
        "title": "感怀四首 其三",
        "type": "七言律诗",
        "paragraph": [
            "萱花遽折痛如何，椿荫偏蒙爱护多。",
            "弱妹于归怜远道，阿兄释褐喜登科。",
            "相期共效莱衣舞，罔极俄惊薤露歌。",
            "此后亲颜悲永隔，蓼莪兴感涕滂沱。"
        ],
        "translate": [
            "萱草花突然折断让人感到悲痛又有什么办法呢?而椿树的树荫却偏偏要受到人们的喜爱和保护。",
            "年幼的妹妹远离家乡可怜她路途遥远,哥哥脱去布衣喜好考中进士。",
            "我们约定一起仿效莱衣舞,一会儿就被薤露的歌声惊醒。",
            "从此以后,我与双亲的面容永不相见,每当想起思念远方的亲人时,总是感慨万千,泪水滂沱。"
        ]
    },
    {
        "title": "感怀四首 其四",
        "type": "七言律诗",
        "paragraph": [
            "诗咏关睢七载馀，蘋蘩修洁愧难如。",
            "倡随愿勉梁鸿案，春汲心钦桓氏车。",
            "差喜兰枝双绕膝，何堪荆树各分疏。",
            "几时手足重团聚，共话西窗月上初。"
        ],
        "translate": [
            "我吟诵《关睢赋》已经七年多了,像那洁白的蘋蘩草那样修长的诗篇,真是惭愧极了。",
            "唱着随从的歌声勉励梁朝的大鸿案,春天来临我虔诚地敬佩桓氏的车马。",
            "我正高兴兰花成双成对地缠绕着我的膝盖,怎么忍心看到荆条和绿树各自被疏远了呢?",
            "什么时候才能手足再次团聚,一起在西窗下面细细倾诉初衷呢?"
        ]
    },
    {
        "title": "续断肠词十首",
        "type": "七言诗",
        "paragraph": [
            "古人曾赋断肠诗，犹记镫前展卷时。",
            "修到清才多缺陷，岂知我续断肠词。",
            "昔年曾痛兰芽折，玉燕重来吉梦符。",
            "珍重明珠双入手，奇姿竞说是家驹。",
            "毛诗初授诵琅琅，每听斋声彻内堂。",
            "此日紫荆花外望，案头空剩读书囊。",
            "不惯酣眠耐晓寒，便从寝室问爷安。",
            "童年也解晨昏意，无怪西河泪不乾。",
            "更比童乌少一龄，八年短梦霎时醒。",
            "丸熊有志今何望，雏凤声残不可听。",
            "泡影空花悟夙因，重翻边箧更酸辛。",
            "零笺碎墨依然在，不见牵衣问字人。",
            "阿连嬉戏恰随肩，玉质温温亦可怜。",
            "岂是夜坛悲寂寞，要他同赋棣华篇。",
            "晓镜台前索果从，夜窗围绕一灯红。",
            "当时笑语浑閒事，此际追思似梦中。",
            "碧梧双凤已腾空，望断云霄路不通。",
            "碧落黄泉真缥缈，不知何处是儿踪。",
            "人到伤心百念灰，愁肠华发暗相催。",
            "此生福慧成虚语，且把哀情抒写来。"
        ],
        "translate": [
            "古人曾经作过《断肠诗》,我还记得在镫前展开诗卷的时候。",
            "我修养到清高才华却有很多缺陷,谁知道我写的这首《断肠词》是多么令人伤感啊!",
            "往年我曾为兰草折断感到悲痛,如今燕子又来归来这吉梦正好应验。",
            "两颗珍贵的明珠你双双得到,它那奇特的姿态人人都说它是自家的马驹。",
            "刚开始传授《毛诗》,诵读起来琅琅有声,每当听到斋戒的诵读声,就听得内堂响彻云霄。",
            "今天在紫荆花丛外眺望,书桌上空空地放着一副书囊。",
            "没习惯于酣睡而忍受清晨的寒冷,就到寝室里去问候爷爷是否平安。",
            "孩童的时候也懂得早晨和黄昏的含义,不要责怪流着泪在西河哭泣不干。",
            "我比童乌还小一岁,八年的短梦刚一觉就醒来了。",
            "小小的熊有远大的志向,现在还指望什么呢?雏凤的叫声已经残缺不全了,再也听不下去了。",
            "泡在水中的影子像一朵朵空荡荡的花,我早就明白了其中的缘故。重翻旧书时发现书箱里的东西更加酸辛。",
            "破损的纸张和墨迹依然存在,却看不见那拿着衣裳来问字的人。",
            "娇美的阿连在肩膀上嬉戏,那温润的玉质也令人喜爱。",
            "难道是夜坛里我悲叹寂寞吗?请你和我一起作《棣华篇》吧!",
            "清晨在镜台前寻找美味的果品,夜晚窗户周围一盏红灯闪烁。",
            "当年的笑谈都是些平常的事情,到现在回忆起来就像是在梦中。",
            "碧绿的梧桐树下,一对凤凰飞上了高空,我登上云霄,一直望到天边,却找不到通向天空的路。",
            "碧绿的黄泉啊,你看它那缥缈的踪迹。不知道何处是我儿的踪迹?",
            "人生一去不返,百感交集都化为灰烬,愁肠百结,满头白发,暗中催人老去。",
            "这一生的福分和智慧都成了虚言,姑且把我的哀伤情怀写下来吧。"
        ]
    },
    {
        "title": "续断肠词十首 其一",
        "type": "七言绝句",
        "paragraph": [
            "蓟树燕云一望青，凤城又见客踪停。",
            "香残锁殿春光闇，话到前游不忍听。"
        ],
        "translate": [
            "蓟门外的树木和燕子飞来的云彩一望就变得青翠起来,京城里我又见到了你的行踪,不由自主地停下了脚步。",
            "香炉中的残香已经燃尽,宫殿里的春光也变得黯然无光。话说到前世的游子我实在不忍心听。"
        ]
    },
    {
        "title": "依韵答外子寄怀诗二首 其一",
        "type": "七言绝句",
        "paragraph": [
            "去住京华年复年，沧桑未缓祖生鞭。",
            "漫将迟暮伤蒲柳，事业从今定胜前。"
        ],
        "translate": [
            "离开和留在京城一年又一年,岁月流逝却没有放松祖逖为我赶路的马鞭。",
            "白白地让迟暮之年伤心蒲柳,从今以后的事业一定胜过以前。"
        ]
    },
    {
        "title": "依韵答外子寄怀诗二首 其二",
        "type": "七言绝句",
        "paragraph": [
            "山城料得多孤寂，两地情怀各自知。",
            "一瓣心香君健饭，耦耕有日漫相思。"
        ],
        "translate": [
            "我料想你住在深山老城中一定非常孤寂,两地的情怀各有各的区别。",
            "一朵花瓣散发出阵阵香味,希望你能好好地吃饱饭。我和你一起耕作的日子里,只能徒然地思念着你。"
        ]
    },
    {
        "title": "闻味云家兄简任长芦运使寄呈七律二首 其一",
        "type": "七言律诗",
        "paragraph": [
            "荆树分枝已十年，欣闻旌节又高骞。",
            "家声自古推清白，治行当年重蓟燕。",
            "名宦勋华能继武，中朝物望久称贤。",
            "芦纲端赖长才理，两世循良万口传。"
        ],
        "translate": [
            "荆条已经分开了枝头,已经有十年了,我高兴地听说旌节又高挂起来了。",
            "家风自古以来就被推崇为清白之人,他的品行就像当年的蓟花和燕子一样可贵。",
            "你身居高位,功勋卓著,又能继承先辈的英武事业,在朝中享有盛名,人们对你的称赞很久以来就是因为你贤能。",
            "芦苇的枝叶端正,依赖萧长有才干和道理,两代遵循良种传统,被万口之家传颂。"
        ]
    },
    {
        "title": "闻味云家兄简任长芦运使寄呈七律二首 其二",
        "type": "七言律诗",
        "paragraph": [
            "诗礼趋庭早有成，左家兄妹并知名。",
            "羡君云路高千丈，愧我蓬门了一生。",
            "触绪更深风水恨，关心犹感友于情。",
            "他年画锦归来日，雅集埙篪载酒迎。"
        ],
        "translate": [
            "《诗经》、《礼记》等学问早就学成了,左家兄弟和妹妹们都很有名气。",
            "羡慕你登上云霄万丈高路,惭愧我闭门在家度过一生。",
            "触景生情更觉心胸开阔,心中充满了无尽的离愁别恨,我对你的关怀仍然使我像对待朋友那样深情厚谊。",
            "等到他年我画完锦缎归来的时候,我在雅集里吹奏着乐器,带着美酒去迎接他。"
        ]
    },
    {
        "title": "后园即景",
        "type": "五言律诗",
        "paragraph": [
            "隐地三弓小，春光一望中。",
            "蔬畦相间接，树木已茏葱。",
            "嫩柳园池绿，夭桃夹岸红。",
            "几多培植意，爱护比儿童。"
        ],
        "translate": [
            "隐蔽在地上的三根弓很小,一眼望去,春光正浓。",
            "菜园的畦田接连不断,周围的树木已经长得青翠茂盛。",
            "嫩绿的柳条铺满了园中的池塘,娇艳的桃花夹岸绽放鲜红。",
            "我有多少爱护自己的心思,爱护孩子要比爱护儿童还要多。"
        ]
    },
    {
        "title": "读外子昌延榷署寄诗原韵答之二首 其一",
        "type": "七言律诗",
        "paragraph": [
            "纡君内顾勉持家，敢说蘋蘩四德嘉。",
            "井臼操馀还展卷，米盐量罢偶栽花。",
            "廿年甘苦心相印，千里巡遥望更赊。",
            "锦字何须织离恨，平安勤报慰天涯。"
        ],
        "translate": [
            "纡君对内顾念家国,努力持家,我敢于谈论《蘋蘩》这四种品德的美好。",
            "整理好井台和石臼后,又重新展开书卷;量好米和盐之后,偶尔栽上几朵花。",
            "二十年辛勤劳苦与我的心相印,远行千里盼望着你的归来,你却迟疑不决。",
            "用锦绣的字条写下离别的愁恨,只要平安无事,勤勉地报答祖国,就可以安慰远在天涯的人了。"
        ]
    },
    {
        "title": "读外子昌延榷署寄诗原韵答之二首 其二",
        "type": "七言律诗",
        "paragraph": [
            "数首新诗寄早春，浣薇雒诵净无尘。",
            "文通作赋偏言别，王粲依人未为贫。",
            "莫把繁华纷雅意，要从事业见精神。",
            "相期眉案吟偕老，梁孟同心證夙因。"
        ],
        "translate": [
            "几首新诗寄托给早春的友人,像浣花草那样在洛水中朗诵,洁净得没有一点尘土。",
            "文通作赋专门谈论别人的离别,王粲依附他人并不算贫穷。",
            "不要因为追求功名利禄而产生繁华富丽的雅兴,要通过做官来体现自己的精神。",
            "我們相約坐在眉間案頭吟誦《偕老》的曲子,梁孟同心同德實在證明是因為早就有緣分。"
        ]
    },
    {
        "title": "外子辞昌延榷务归里喜面赋此四首 其一",
        "type": "七言绝句",
        "paragraph": [
            "十载京华鬓未丝，归来笑语共相嬉。",
            "田园乐趣家庭福，侥倖年来事事宜。"
        ],
        "translate": [
            "呆呆呆呆呆呆呆呆呆呆呆呆呆呆呆呆呆呆呆呆呆呆呆呆在京城十多年了,回到了家乡和朋友们谈笑风生,共同欢乐。",
            "田园的乐趣是家庭的福分,希望今年一切事情都办得恰到好处。"
        ]
    },
    {
        "title": "外子辞昌延榷务归里喜面赋此四首 其二",
        "type": "七言绝句",
        "paragraph": [
            "当年抑塞事难忘，双凤腾空恨渺茫。",
            "留得青山终不老，阶前玉树已成行。"
        ],
        "translate": [
            "当年在边塞的艰难困苦中被俘获的事我永远难以忘怀,像那双凤凰飞向遥远的天空,使我的遗憾变得渺茫无穷。",
            "留得青山终究不会衰老,台阶前的玉树已经长成行。"
        ]
    },
    {
        "title": "外子辞昌延榷务归里喜面赋此四首 其三",
        "type": "七言绝句",
        "paragraph": [
            "一径蒿莱手自锄，小园花木已扶疏。",
            "自甘荆布心如水，不羡繁华戚里居。"
        ],
        "translate": [
            "一条小路边长满了野蒿,我亲手把它锄掉;小小的园子里花草树木也已经渐渐稀疏。",
            "我甘愿身穿荆棘布衣而心如水,不羡慕富贵荣华的戚里之居。"
        ]
    },
    {
        "title": "外子辞昌延榷务归里喜面赋此四首 其四",
        "type": "七言绝句",
        "paragraph": [
            "举杯又见月当头，竟夕清谈互唱酬。",
            "出处何如安处好，鹿车鸿案自风流。"
        ],
        "translate": [
            "举起酒杯又看见皎洁的月亮正好挂在头上,我们整夜在一起清谈,互相唱着歌相互赠送。",
            "出门与隐居哪样好呢?坐着鹿车,坐在鸿雁的案桌上自然是风流。"
        ]
    },
    {
        "title": "得外子南安书作此解慰",
        "type": "七言律诗",
        "paragraph": [
            "南天睽隔盼归鸿，沈滞音书匝月中。",
            "一纸平安深慰藉，千丝情绪暂消融。",
            "蛮方民俗难为治，乱世财源渐告穷。",
            "治谱承家宜勉力，好凭清德化顽蒙。"
        ],
        "translate": [
            "在遥远的南方盼望着鸿雁归来,月亮被遮住了,音讯和书信都在月光下滞留。",
            "一封平安的信深表慰藉,千丝万缕的忧愁情绪一下子消融。",
            "蛮荒之地的民风习俗很难治理好,战乱年代财源逐渐枯竭。",
            "治理家谱、继承家业应该尽力,最好是靠清廉的品德来感化那些顽固不化的世俗之人。"
        ]
    },
    {
        "title": "和外子留别南安士绅原韵二首 其一",
        "type": "七言律诗",
        "paragraph": [
            "十年京国荷传薪，初领河阳一县春。",
            "治谱当年能继志，循声此日果超伦。",
            "幸留棠荫称廉吏，好课楹书启后人。",
            "柳色青青无限意，骊歌竞唱惜抽身。"
        ],
        "translate": [
            "来到京城已经十年,肩负着运送柴薪的重任;刚开始领受河阳一县的春意,就进入了春天。",
            "当年编纂国史能够继承先辈的志向,今天遵循前人的名声果然超越常人。",
            "希望您能留下像李棠那样的荫庇而被称为廉洁的官吏,好好地考查您的楹柱上的书籍,以便启发后人。",
            "柳色青青,有无限情意,骊歌竞唱,痛惜抽身离去。"
        ]
    },
    {
        "title": "和外子留别南安士绅原韵二首 其二",
        "type": "七言律诗",
        "paragraph": [
            "书剑飘零惯别离，故园梅鹤未追随。",
            "江乡景物催归棹，闽海行藏感弈棋。",
            "载道讴驮传惠政，全家儿女盼归期。",
            "莫言五月匆匆甚，德泽长留去后思。"
        ],
        "translate": [
            "书剑飘零,习惯于别离,故园里的梅树和仙鹤我都没有去追随。",
            "江乡的景物催促着我的归棹,闽海一带的行踪和隐居生活使我感慨万分。",
            "车水马龙,一路歌声载歌载舞,传布着朝廷的恩惠和政令。全家儿女都盼望着皇上回乡的日期。",
            "不要说五月的时光太匆忙了,美好的德行和恩泽永远留在人世间后再来思念。"
        ]
    },
    {
        "title": "外子属和生日口占",
        "type": "七言绝句",
        "paragraph": [
            "历尽艰辛转自怜，箕裘世业幸重延。",
            "此心俯仰俱无愧，仁者从来享大年。"
        ],
        "translate": [
            "历尽了艰难困苦反而感到可怜,像箕裘那样的世家大业有幸得以重新延长。",
            "胸怀这样的仁慈之心无论俯仰都不会感到惭愧,有仁德的人从古到今都能享尽天年。"
        ]
    },
    {
        "title": "感怀四首",
        "type": "七言诗",
        "paragraph": [
            "闺中乐事记髫年，同侍重闱得爱怜。",
            "累叶清芬绵孝弟，一门和蔼胜神仙。",
            "庭前玉树枝枝秀，林下琼花朵朵妍。",
            "最好藏书楼畔坐，惠峰晴翠扑帘前。",
            "濑水前游迹已陈，十年冷署梦尘尘。",
            "春风教士心堪白，夜雨横经意倍殷。",
            "小乐园林饶兴趣，天生花草亦精神。",
            "绛纱惯向慈帏立，手把吟篇问字频。",
            "萱花遽折痛如何，椿荫偏蒙爱护多。",
            "弱妹于归怜远道，阿兄释褐喜登科。",
            "相期共效莱衣舞，罔极俄惊薤露歌。",
            "此后亲颜悲永隔，蓼莪兴感涕滂沱。",
            "诗咏关睢七载馀，蘋蘩修洁愧难如。",
            "倡随愿勉梁鸿案，春汲心钦桓氏车。",
            "差喜兰枝双绕膝，何堪荆树各分疏。",
            "几时手足重团聚，共话西窗月上初。"
        ],
        "translate": [
            "闺房中最快乐的事情是记住小孩子,他们一起陪伴着我进入了重闱,受到我的喜爱和怜爱。",
            "几代子孙家风清雅,孝顺父母,友爱兄弟,一家人和睦相处,胜过神仙。",
            "庭院前的玉树枝枝秀美,林下的琼花朵朵鲜艳美丽。",
            "在藏书楼畔最适宜坐着,阳光下惠山的翠绿扑打在帘子前面。",
            "昔日在濑水边游玩过的足迹早已陈列,十年来冷清的官署里梦中也只见到尘土飞扬。",
            "春风吹拂让人心灰意冷,夜晚的雨不停地下着,使人倍感忧愁。",
            "小小的园林里充满了无限的乐趣,自然而然地产生出许多花草,使人倍感兴致。",
            "身着深红色的纱窗,整天站在慈祥的帏帐旁,手里拿着诗篇,频频地问我写什么。",
            "萱草花突然折断让人感到悲痛又有什么办法呢?而椿树的树荫却偏偏要受到人们的喜爱和保护。",
            "年幼的妹妹远离家乡可怜她路途遥远,哥哥脱去布衣喜好考中进士。",
            "我们约定一起仿效莱衣舞,一会儿就被薤露的歌声惊醒。",
            "从此以后,我与双亲的面容永不相见,每当想起思念远方的亲人时,总是感慨万千,泪水滂沱。",
            "我吟诵《关睢赋》已经七年多了,像那洁白的蘋蘩草那样修长的诗篇,真是惭愧极了。",
            "唱着随从的歌声勉励梁朝的大鸿案,春天来临我虔诚地敬佩桓氏的车马。",
            "我正高兴兰花成双成对地缠绕着我的膝盖,怎么忍心看到荆条和绿树各自被疏远了呢?",
            "什么时候才能手足再次团聚,一起在西窗下面细细倾诉初衷呢?"
        ]
    },
    {
        "title": "闻味云家兄简任长芦运使寄呈七律二首",
        "type": "七言诗",
        "paragraph": [
            "荆树分枝已十年，欣闻旌节又高骞。",
            "家声自古推清白，治行当年重蓟燕。",
            "名宦勋华能继武，中朝物望久称贤。",
            "芦纲端赖长才理，两世循良万口传。",
            "诗礼趋庭早有成，左家兄妹并知名。",
            "羡君云路高千丈，愧我蓬门了一生。",
            "触绪更深风水恨，关心犹感友于情。",
            "他年画锦归来日，雅集埙篪载酒迎。"
        ],
        "translate": [
            "荆条已经分开了枝头,已经有十年了,我高兴地听说旌节又高挂起来了。",
            "家风自古以来就被推崇为清白之人,他的品行就像当年的蓟花和燕子一样可贵。",
            "你身居高位,功勋卓著,又能继承先辈的英武事业,在朝中享有盛名,人们对你的称赞很久以来就是因为你贤能。",
            "芦苇的枝叶端正,依赖萧长有才干和道理,两代遵循良种传统,被万口之家传颂。",
            "《诗经》、《礼记》等学问早就学成了,左家兄弟和妹妹们都很有名气。",
            "羡慕你登上云霄万丈高路,惭愧我闭门在家度过一生。",
            "触景生情更觉心胸开阔,心中充满了无尽的离愁别恨,我对你的关怀仍然使我像对待朋友那样深情厚谊。",
            "等到他年我画完锦缎归来的时候,我在雅集里吹奏着乐器,带着美酒去迎接他。"
        ]
    },
    {
        "title": "读外子昌延榷署寄诗原韵答之二首",
        "type": "七言诗",
        "paragraph": [
            "纡君内顾勉持家，敢说蘋蘩四德嘉。",
            "井臼操馀还展卷，米盐量罢偶栽花。",
            "廿年甘苦心相印，千里巡遥望更赊。",
            "锦字何须织离恨，平安勤报慰天涯。",
            "数首新诗寄早春，浣薇雒诵净无尘。",
            "文通作赋偏言别，王粲依人未为贫。",
            "莫把繁华纷雅意，要从事业见精神。",
            "相期眉案吟偕老，梁孟同心證夙因。"
        ],
        "translate": [
            "纡君对内顾念家国,努力持家,我敢于谈论《蘋蘩》这四种品德的美好。",
            "整理好井台和石臼后,又重新展开书卷;量好米和盐之后,偶尔栽上几朵花。",
            "二十年辛勤劳苦与我的心相印,远行千里盼望着你的归来,你却迟疑不决。",
            "用锦绣的字条写下离别的愁恨,只要平安无事,勤勉地报答祖国,就可以安慰远在天涯的人了。",
            "几首新诗寄托给早春的友人,像浣花草那样在洛水中朗诵,洁净得没有一点尘土。",
            "文通作赋专门谈论别人的离别,王粲依附他人并不算贫穷。",
            "不要因为追求功名利禄而产生繁华富丽的雅兴,要通过做官来体现自己的精神。",
            "我們相約坐在眉間案頭吟誦《偕老》的曲子,梁孟同心同德實在證明是因為早就有緣分。"
        ]
    },
    {
        "title": "和外子留别南安士绅原韵二首",
        "type": "七言诗",
        "paragraph": [
            "十年京国荷传薪，初领河阳一县春。",
            "治谱当年能继志，循声此日果超伦。",
            "幸留棠荫称廉吏，好课楹书启后人。",
            "柳色青青无限意，骊歌竞唱惜抽身。",
            "书剑飘零惯别离，故园梅鹤未追随。",
            "江乡景物催归棹，闽海行藏感弈棋。",
            "载道讴驮传惠政，全家儿女盼归期。",
            "莫言五月匆匆甚，德泽长留去后思。"
        ],
        "translate": [
            "来到京城已经十年,肩负着运送柴薪的重任;刚开始领受河阳一县的春意,就进入了春天。",
            "当年编纂国史能够继承先辈的志向,今天遵循前人的名声果然超越常人。",
            "希望您能留下像李棠那样的荫庇而被称为廉洁的官吏,好好地考查您的楹柱上的书籍,以便启发后人。",
            "柳色青青,有无限情意,骊歌竞唱,痛惜抽身离去。",
            "书剑飘零,习惯于别离,故园里的梅树和仙鹤我都没有去追随。",
            "江乡的景物催促着我的归棹,闽海一带的行踪和隐居生活使我感慨万分。",
            "车水马龙,一路歌声载歌载舞,传布着朝廷的恩惠和政令。全家儿女都盼望着皇上回乡的日期。",
            "不要说五月的时光太匆忙了,美好的德行和恩泽永远留在人世间后再来思念。"
        ]
    }
]