[
    {
        "title": "台阳笔记题词",
        "type": "七言律诗",
        "paragraph": [
            "海色天风路渺茫，蛮云犵鸟自成乡。",
            "从今不读舆图记，一管生花写大荒。",
            "蛋雨闽风四十秋，潜蛟宫室蜃中楼。",
            "知君碧眼过犀烛，不学词人记十洲。"
        ],
        "translate": [
            "海色苍茫,天风浩荡,路途遥远迷茫,蛮族的云雾缭绕,鸟儿自由自在地栖息在自己的故乡。",
            "从今以后不再读《舆图记》,只管看那繁花似锦的春天景色来描绘祖国的疆土。",
            "像鸡蛋般的雨,像闽地的风,已经经历了四十个春秋;就像潜藏在蛟龙的宫室和蜃中楼一样,历经沧桑。",
            "我知道你的碧绿的眼珠比犀牛角的蜡烛还要明亮,却不像词人那样记忆力强,能记住十洲美景。"
        ]
    },
    {
        "title": "台阳笔记题词 其二",
        "type": "七言绝句",
        "paragraph": [
            "蛋雨闽风四十秋，潜蛟宫室蜃中楼。",
            "知君碧眼过犀烛，不学词人记十洲。"
        ],
        "translate": [
            "像鸡蛋般的雨,像闽地的风,已经经历了四十个春秋;就像潜藏在蛟龙的宫室和蜃中楼一样,历经沧桑。",
            "我知道你的碧绿的眼珠比犀牛角的蜡烛还要明亮,却不像词人那样记忆力强,能记住十洲美景。"
        ]
    },
    {
        "title": "台阳笔记题词 其一",
        "type": "七言绝句",
        "paragraph": [
            "海色天风路渺茫，蛮云犵鸟自成乡。",
            "从今不读舆图记，一管生花写大荒。"
        ],
        "translate": [
            "海色苍茫,天风浩荡,路途遥远迷茫,蛮族的云雾缭绕,鸟儿自由自在地栖息在自己的故乡。",
            "从今以后不再读《舆图记》,只管看那繁花似锦的春天景色来描绘祖国的疆土。"
        ]
    },
    {
        "title": "晚步",
        "type": "五言诗",
        "paragraph": [
            "出门看斜阳，忽已上高树。",
            "携手同心欢，城隅散轻步。",
            "秋风一夕来，衣袂改轻素。",
            "木叶脱何迟，芳草色非故。",
            "悠悠远水明，霭霭苍烟暮。",
            "牧晚笛归村，渔寒镫隐渡。",
            "登高畅幽怀，感逝戚内顾。",
            "新欢不在眼，陈人复谁慕。",
            "存悲思浩歌，念别感征路。",
            "辽天廓无边，惟有寒鸦去。"
        ],
        "translate": [
            "出门远望斜阳,忽然登上高高的树林。",
            "大家携手同心同德,在城墙角落散步尽情欢快。",
            "一夜之间,阵阵秋风吹来,我的衣袖被吹得格外轻盈、素雅。",
            "树叶为什么这样快要落叶了呢?芳草的颜色也不是故意的那样美丽。",
            "远处水天相连,波光粼粼;暮色苍茫,烟霭迷蒙。",
            "牧童傍晚吹着笛子回到村里,渔翁在寒冷的夜晚放下镫子隐藏在渡口。",
            "登上高处抒发内心的幽思,感慨远去的亲人哀伤地回头看我。",
            "陈后主的《新欢》已经不在眼里了,像陈后主那样的人又有谁会仰慕他呢?",
            "我怀着悲伤的心情想着高歌一曲,想到与心上人离别感慨万千,在征途跋涉。",
            "辽阔的天空广阔无边,只有几只寒鸦飞向远方。"
        ]
    },
    {
        "title": "小楼晚望",
        "type": "七言律诗",
        "paragraph": [
            "江城坐老绿苔矶，郭外青山望处微。",
            "落日昏鸦争树急，西风黄叶向人飞。",
            "半天秋远欹吟帽，九月霜寒赋授衣。",
            "独有高楼延草色，几家临水掩柴扉。"
        ],
        "translate": [
            "我坐落在江城的长满青苔的石头上,远望城外青山隐约可见。",
            "夕阳西下,黄昏时分,乌鸦在树上飞来飞去,显得格外急促。秋风萧瑟,落叶纷纷,扑向远方,仿佛要向人扑去一般。",
            "我斜倚着帽子仰望远方的秋色,九月的霜寒让我吟诵这首《授衣赋》。",
            "唯有高楼向远处延展着草色,几户人家临水紧闭着柴门。"
        ]
    }
]