[
    {
        "title": "还家",
        "type": "五言诗",
        "paragraph": [
            "旅梦犹京国，归程已越山。",
            "津亭银杏步，烟水铁林关。",
            "乡树中流辨，征云极浦还。",
            "土音经耳熟，入听足怡颜。",
            "俊秀怜予弟，艰难怅女媭。",
            "昔年双泪别，此日一樽俱。",
            "问字奇同赏，谈诗兴不孤。",
            "老亲宽大惯，相顾转欢娱。"
        ],
        "translate": [
            "在旅途的梦中,我仍然住在京城;回家的路程已经越过终南山。",
            "在渡口的亭子上踏着银杏树的脚步,烟波浩渺的江水穿过铁林关。",
            "山乡的树木在江流中分明辨别,远处的云彩从水边飘到岸上又回来。",
            "当地的音乐已经很熟练了,一听就满面愉悦的神色。",
            "你美丽俊秀可怜我的小弟弟,艰难困苦让我对你的陪伴感到惆怅。",
            "去年我们泪流满面地告别,今天我们举杯共饮一场又一次。",
            "问字有新奇之处大家共同欣赏,谈论诗兴也同样不分彼此。",
            "年迈的双亲性格宽厚老实习惯于这样,彼此相视而笑反而更加欢欣鼓舞。"
        ]
    },
    {
        "title": "秋日南湖即事",
        "type": "七言绝句",
        "paragraph": [
            "楼台宜雨复宜烟，一片湖光抱镜圆。",
            "错怪鸳鸯飞不定，兰桡催动采菱船。"
        ],
        "translate": [
            "湖光山色好雨又好烟,一片湖光像一面镜子那么圆。",
            "一对鸳鸯在水面交错地飞舞着,逗得我心惊胆战。船夫摇动木桨催促着采菱女乘坐的小船。"
        ]
    },
    {
        "title": "还家 其二",
        "type": "五言律诗",
        "paragraph": [
            "俊秀怜予弟，艰难怅女媭。",
            "昔年双泪别，此日一樽俱。",
            "问字奇同赏，谈诗兴不孤。",
            "老亲宽大惯，相顾转欢娱。"
        ],
        "translate": [
            "你美丽俊秀可怜我的小弟弟,艰难困苦让我对你的陪伴感到惆怅。",
            "去年我们泪流满面地告别,今天我们举杯共饮一场又一次。",
            "问字有新奇之处大家共同欣赏,谈论诗兴也同样不分彼此。",
            "年迈的双亲性格宽厚老实习惯于这样,彼此相视而笑反而更加欢欣鼓舞。"
        ]
    },
    {
        "title": "还家 其一",
        "type": "五言律诗",
        "paragraph": [
            "旅梦犹京国，归程已越山。",
            "津亭银杏步，烟水铁林关。",
            "乡树中流辨，征云极浦还。",
            "土音经耳熟，入听足怡颜。"
        ],
        "translate": [
            "在旅途的梦中,我仍然住在京城;回家的路程已经越过终南山。",
            "在渡口的亭子上踏着银杏树的脚步,烟波浩渺的江水穿过铁林关。",
            "山乡的树木在江流中分明辨别,远处的云彩从水边飘到岸上又回来。",
            "当地的音乐已经很熟练了,一听就满面愉悦的神色。"
        ]
    }
]