[
    {
        "title": "送瘟神",
        "type": "七言诗",
        "paragraph": [
            "绿水青山枉自多，华佗无奈小虫何！",
            "千村薜荔人遗矢，万户萧疏鬼唱歌。",
            "坐地日行八万里，巡天遥看一千河。",
            "牛郎欲问瘟神事，一样悲欢逐逝波。",
            "春风杨柳万千条，六亿神州尽舜尧。",
            "红雨随心翻作浪，青山着意化为桥。",
            "天连五岭银锄落，地动三河铁臂摇。",
            "借问瘟君欲何往，纸船明烛照天烧。"
        ],
        "translate": [
            "绿水青山白白地多了,可华佗却对小虫无可奈何。",
            "千村的薜荔被敌人射死,家家户户萧条冷落,只有鬼在唱歌。",
            "坐在地上一天可以行走八万里,在天上远望可以看见一千条河流。",
            "牛郎要问关于瘟神的事,悲欢离合的情感随着时光的流逝而消失。",
            "春风中杨柳千条万条,中国的六亿人民都成为舜、尧、禹的后代。",
            "红花般的细雨随心所欲地翻腾成波浪,青山有意地把它当作桥梁。",
            "天连着五岭,银锄就掉落了;地动了三河,铁臂就摇动了。",
            "请问瘟君你要去哪里?我用明烛照天把纸船烧了。"
        ]
    },
    {
        "title": "虞美人·枕上",
        "type": "七言律诗",
        "paragraph": [
            "堆来枕上愁何状，江海翻波浪。",
            "夜长天色怎难明，无奈披衣起坐薄寒中。",
            "晓来百念皆灰烬，倦极身无凭。",
            "一勾残月向西流，对此不抛眼泪也无由。"
        ],
        "translate": [
            "枕上堆积着的忧愁是什么样子呢?是江海翻滚的波浪。",
            "夜晚漫长,天色怎么这样难于发亮呢?无可奈何地披上衣服起来坐在微寒中。",
            "清晨以来,我百般思念都化为灰烬,疲倦到极点,身体也无所依凭。",
            "一弯残月向西流去,面对这种情景不抛下眼泪也是没有缘由的。"
        ]
    },
    {
        "title": "浣溪沙·和柳亚子先生",
        "type": "七言诗",
        "paragraph": [
            "颜斶齐王各命前，多年矛盾廓无边，而今一扫纪新元。",
            "最喜诗人高唱至，正和前线捷音联，妙香山上战旗妍。"
        ],
        "translate": [
            "颜斶和齐王分别受命于前,多年间矛盾层出不穷,而今朝廷将它们全部清除,改年号为新元。",
            "最令人高兴的是诗人高声唱到,正好和前线胜利的音信相联,妙香山上战旗艳丽夺目。"
        ]
    },
    {
        "title": "戏改杜甫《咏怀古迹》其三",
        "type": "七言绝句",
        "paragraph": [
            "群山万壑赴荆门，生长林彪尚有村。",
            "一去紫台连朔漠，独留青冢向黄昏。"
        ],
        "translate": [
            "群山万壑奔赴荆门,生长茂盛的林彪还有村庄。",
            "一离开紫台就与北方的沙漠相连,唯独留下那青冢向着黄昏延伸。"
        ]
    },
    {
        "title": "为女民兵题照",
        "type": "七言绝句",
        "paragraph": [
            "飒爽英姿五尺枪，曙光初照演兵场。",
            "中华儿女多奇志，不爱红装爱武装。"
        ],
        "translate": [
            "英姿飒爽手持五尺枪,拂晓初照演习武艺的场面。",
            "中华儿女志向不凡,不爱红艳艳的服饰,而爱武装的战士。"
        ]
    },
    {
        "title": "为李进同志题所摄庐山仙人洞照",
        "type": "七言绝句",
        "paragraph": [
            "暮色苍茫看劲松，乱云飞渡仍从容。",
            "天生一个仙人洞，无限风光在险峰。"
        ],
        "translate": [
            "暮色苍茫中仰望那挺拔挺拔的松树,它在乱云中飞渡时依然神态从容不迫。",
            "上天降下一个仙人洞,在险峻的山峰上展现出无限的风光。"
        ]
    },
    {
        "title": "五云山",
        "type": "七言绝句",
        "paragraph": [
            "五云山上五云飞，远接群峰近拂堤。",
            "若问杭州何处好，此中听得野莺啼。"
        ],
        "translate": [
            "五云山上飘着五色云彩,远处与群峰相连,近处轻拂着长堤。",
            "如果有人问杭州什么地方最好,在这儿你可以听到野莺的啼叫声。"
        ]
    },
    {
        "title": "仿陆放翁",
        "type": "七言绝句",
        "paragraph": [
            "人类今娴上太空，但悲不见五洲同。",
            "愚公尽扫饕蚊日，公祭无忘告马翁。"
        ],
        "translate": [
            "如今人类安闲自在地生活在太空,只可惜看不到五洲的人们都像我们一样。",
            "愚公每天都在扫除蚊子,祭祀时千万不要忘记告诉马翁。"
        ]
    },
    {
        "title": "刘蕡",
        "type": "七言绝句",
        "paragraph": [
            "千载长天起大云，中唐俊伟有刘蕡。",
            "孤鸿铩羽悲鸣镝，万马齐喑叫一声。"
        ],
        "translate": [
            "千载长空万里涌起层层云朵,中唐时期的俊杰之士有刘蕡这样的人。",
            "一只孤雁被射中了翅膀,悲伤地用响箭射击它。所有的战马都停止了鸣叫,只听到鸿雁一声声的嘶叫。"
        ]
    },
    {
        "title": "戏改李攀龙《怀明卿》",
        "type": "七言绝句",
        "paragraph": [
            "豫章西望彩云间，九派长江九叠山。",
            "高卧不须窥石镜，秋风怒在叛徒颜。"
        ],
        "translate": [
            "从豫章城向西望去,只见江水像九条支流,两岸是重重叠叠的青山。",
            "高卧在山上不必窥视石镜,秋风怒容满面地扑打着叛徒的面容。"
        ]
    },
    {
        "title": "纪念鲁迅八十寿辰",
        "type": "七言绝句",
        "paragraph": [
            "博大胆识铁石坚，刀光剑影任翔旋。",
            "龙华喋血不眠夜，犹制小诗赋管弦。"
        ],
        "translate": [
            "张博胆大如虎,铁石坚硬无比,刀光剑影任凭他飞翔旋转。",
            "龙华殿的神女在夜里喋血不眠,她还在不停地写着小诗赋和弹奏着管弦。"
        ]
    },
    {
        "title": "观潮",
        "type": "七言绝句",
        "paragraph": [
            "千里波涛滚滚来，雪花飞向钓鱼台。",
            "人山纷赞阵容阔，铁马从容杀敌回。"
        ],
        "translate": [
            "千里波涛汹涌澎湃,滚滚而来,浪花如雪飞向钓鱼台。",
            "人们在山上纷纷赞叹我军阵容壮阔,战士们骑着铁甲的战马从容地杀敌回来。"
        ]
    },
    {
        "title": "改诗赠父亲",
        "type": "七言绝句",
        "paragraph": [
            "孩儿立志出乡关，学不成名誓不还。",
            "埋骨何须桑梓地，人生无处不青山。"
        ],
        "translate": [
            "孩儿立下志向走出家乡,学习不取得成绩就发誓不再回来。",
            "埋葬尸骨何必非要家乡的土地,人生到处都是秀丽的山河。"
        ]
    },
    {
        "title": "咏蛙",
        "type": "七言绝句",
        "paragraph": [
            "独坐池塘如虎踞，绿荫树下养精神。",
            "春来我不先开口，哪个虫儿敢作声。"
        ],
        "translate": [
            "独自坐在池塘上好似猛虎盘踞,在绿树荫下养精蓄锐。",
            "春天来了,如果我不先开口说话,还有什么虫子敢发声呢?"
        ]
    },
    {
        "title": "屈原",
        "type": "七言绝句",
        "paragraph": [
            "屈子当年赋楚骚，手中握有杀人刀。",
            "艾萧太盛椒兰少，一跃冲向万里涛。"
        ],
        "translate": [
            "屈原当年写下《楚辞》,手里还握着一把杀人刀。",
            "艾蒿的香气太盛,椒兰的香气太少,我却一跃冲向那万里的波涛。"
        ]
    },
    {
        "title": "莫干山",
        "type": "七言绝句",
        "paragraph": [
            "翻身跃入七人房，回首峰峦入莽苍。",
            "四十八盘才走过，风驰又已到钱塘。"
        ],
        "translate": [
            "翻身跃入七人房中,回头眺望远处的群峰隐没在苍茫的草木之中。",
            "刚走过四十八盘山,风驰电掣般地又到了钱塘江。"
        ]
    },
    {
        "title": "贾谊",
        "type": "七言绝句",
        "paragraph": [
            "贾生才调世无伦，哭泣情怀吊屈文。",
            "梁王堕马寻常事，何用哀伤付一生。"
        ],
        "translate": [
            "贾谊的才华和气度在当时没有人能与之匹敌,他痛哭流涕地用悲伤的情怀来凭吊屈原。",
            "梁王从马上掉下来是寻常之事,哪里用得着悲伤地度过一生呢?"
        ]
    },
    {
        "title": "赠刘翰林联句",
        "type": "七言绝句",
        "paragraph": [
            "翻山渡水之名郡，竹杖草履谒学尊。",
            "途见白云如晶海，沾衣晨露浸饿身。"
        ],
        "translate": [
            "来到这座名山大川的扬州,拄着竹杖穿着草鞋去拜访老师。",
            "半路上只见白云如一片晶莹的海洋,早晨的露水沾湿了衣裳,浸湿了饥饿的身体。"
        ]
    },
    {
        "title": "送瘟神 其一",
        "type": "七言律诗",
        "paragraph": [
            "绿水青山枉自多，华佗无奈小虫何！",
            "千村薜荔人遗矢，万户萧疏鬼唱歌。",
            "坐地日行八万里，巡天遥看一千河。",
            "牛郎欲问瘟神事，一样悲欢逐逝波。"
        ],
        "translate": [
            "绿水青山白白地多了,可华佗却对小虫无可奈何。",
            "千村的薜荔被敌人射死,家家户户萧条冷落,只有鬼在唱歌。",
            "坐在地上一天可以行走八万里,在天上远望可以看见一千条河流。",
            "牛郎要问关于瘟神的事,悲欢离合的情感随着时光的流逝而消失。"
        ]
    },
    {
        "title": "送瘟神 其二",
        "type": "七言律诗",
        "paragraph": [
            "春风杨柳万千条，六亿神州尽舜尧。",
            "红雨随心翻作浪，青山着意化为桥。",
            "天连五岭银锄落，地动三河铁臂摇。",
            "借问瘟君欲何往，纸船明烛照天烧。"
        ],
        "translate": [
            "春风中杨柳千条万条,中国的六亿人民都成为舜、尧、禹的后代。",
            "红花般的细雨随心所欲地翻腾成波浪,青山有意地把它当作桥梁。",
            "天连着五岭,银锄就掉落了;地动了三河,铁臂就摇动了。",
            "请问瘟君你要去哪里?我用明烛照天把纸船烧了。"
        ]
    },
    {
        "title": "人民解放军占领南京",
        "type": "七言律诗",
        "paragraph": [
            "钟山风雨起苍黄，百万雄师过大江。",
            "虎踞龙盘今胜昔，天翻地覆慨而慷。",
            "宜将剩勇追穷寇，不可沽名学霸王。",
            "天若有情天亦老，人间正道是沧桑。"
        ],
        "translate": [
            "钟山在风雨中苍茫壮丽,百万雄师渡过长江奔腾不息。",
            "虎踞龙盘的今天胜过往昔,天翻地覆令人感慨而慷慨。",
            "应该用剩余的勇气追击穷途末路的强盗,不能沽名钓誉学那些称霸称王的人。",
            "老天如果有情,也该衰老;人世间正道就是这样,一去不复返。"
        ]
    },
    {
        "title": "忆重庆谈判",
        "type": "七言律诗",
        "paragraph": [
            "有田有地皆吾主，无法无天是为民。",
            "重庆有官皆墨吏，延安无屎不黄金。",
            "炸桥挖路为团结，夺地争城是斗争。",
            "遍地哀鸿满城血，无非一念救苍生。"
        ],
        "translate": [
            "有田有地都是我们的主人,没有法无天却是我们的臣民。",
            "在重庆做官的都是些污吏,在延安做官的没有一滴不染上黄金。",
            "炸毁桥梁、开辟道路是为了团结,夺取土地、争夺城池是为了斗争。",
            "遍地都是哀鸿,满城都是鲜血,这无非是思念着拯救黎民百姓的原故。"
        ]
    },
    {
        "title": "长征",
        "type": "七言律诗",
        "paragraph": [
            "红军不怕远征难，万水千山只等闲。",
            "五岭逶迤腾细浪，乌蒙磅礴走泥丸。",
            "金沙水拍云崖暖，大渡桥横铁索寒。",
            "更喜岷山千里雪，三军过后尽开颜。"
        ],
        "translate": [
            "红军不怕远征的艰难,把跋涉在万水千山之间看作是件平常的事。",
            "五岭的山脉曲折绵延好似在腾起细小的波浪,乌蒙山磅礴雄伟好像行走在泥丸中。",
            "金沙江水拍击着云崖,使山崖变得温和;大渡桥横架着铁索,使人感到寒冷。",
            "更喜的是岷山上千里积雪,三军过后全都面带喜色。"
        ]
    },
    {
        "title": "吊罗荣桓同志",
        "type": "七言律诗",
        "paragraph": [
            "记得当年草上飞，红军队里每相违。",
            "长征不是难堪日，战锦方为大问题。",
            "斥鴳每闻欺大鸟，昆鸡长笑老鹰非。",
            "君今不幸离人世，国有疑难可问谁？"
        ],
        "translate": [
            "还记得当年在草丛中飞翔,在军营里与红军常常相逢。",
            "长途跋涉,征战的日子并不算艰难,要想打败敌人,锦绣战袍才是最大的困难。",
            "斥鴳常常听到有人欺骗大鸟的声音,公鸡总是嘲笑老鹰说错了话。",
            "你现在不幸离开人世,国家有疑难之事可以向谁请教呢?"
        ]
    },
    {
        "title": "有所思",
        "type": "七言律诗",
        "paragraph": [
            "正是神都有事时，又来南国踏芳枝。",
            "青松怒向苍天发，败叶纷随碧水驰。",
            "一阵风雷惊世界，满街红绿走旌旗。",
            "凭阑静听潇潇雨，故国人民有所思。"
        ],
        "translate": [
            "正赶上神都有事的时候,我又来到南方踏青赏花。",
            "青松怒气冲冲向苍天,枯败的树叶纷纷随着碧绿的江水奔流。",
            "一阵狂风暴雷震惊了整个世界,满街都是红绿相间的旌旗在奔走。",
            "靠着栏杆静静地听那潇潇细雨,故乡的人民都在思念着我。"
        ]
    },
    {
        "title": "到韶山",
        "type": "七言律诗",
        "paragraph": [
            "别梦依稀咒逝川，故园三十二年前。",
            "红旗卷起农奴戟，黑手高悬霸主鞭。",
            "为有牺牲多壮志，敢叫日月换新天。",
            "喜看稻菽千重浪，遍地英雄下夕烟。"
        ],
        "translate": [
            "离别后的梦境依稀像是在诅咒逝去的河川,回想起故乡已经有三十二年了。",
            "红旗卷起农奴的戟,黑手高悬霸主的马鞭。",
            "为了多杀敌人的壮志,我敢叫日月换新天。",
            "我高兴地看着千重浪涛滚滚的稻子和庄稼,看到满地的英雄豪杰都像夕阳下的炊烟一样从四面八方归来。"
        ]
    },
    {
        "title": "和周世钊同志",
        "type": "七言律诗",
        "paragraph": [
            "春风浩荡暂徘徊，又踏层峰望眼开。",
            "风起绿洲吹浪去，雨从青野上山来。",
            "尊前谈笑人依旧，域外鸡虫事可哀。",
            "莫叹韶华容易逝，卅年仍到赫曦台。"
        ],
        "translate": [
            "在浩荡的春风中我暂且徘徊,又踏着层层山峰望眼欲穿。",
            "春风从绿水洲上吹起,把江中的波浪吹走;雨从青翠的原野上飘洒到高山上。",
            "酒宴上谈笑风生的人依旧像往常一样,世外鸡虫之类的事实在令人悲哀。",
            "不要感叹时光易逝,即使过了三十年,仍然可以登上赫曦台。"
        ]
    },
    {
        "title": "和柳亚子先生",
        "type": "七言律诗",
        "paragraph": [
            "饮茶粤海未能忘，索句渝州叶正黄。",
            "三十一年还旧国，落花时节读华章。",
            "牢骚太盛防肠断，风物长宜放眼量。",
            "莫道昆明池水浅，观鱼胜过富春江。"
        ],
        "translate": [
            "曾在粤海喝茶,至今仍不能忘怀;到渝州去寻找佳句,此时落叶已是黄昏。",
            "三十一年后回到故乡,在落花纷飞的时节诵读你的诗章。",
            "牢骚过于激烈要防患于未然,对待世间万事应该放开眼界来衡量。",
            "不要说昆明池水太浅,观看鱼儿的游兴胜过游玩富春江。"
        ]
    },
    {
        "title": "和郭沫若同志",
        "type": "七言律诗",
        "paragraph": [
            "一从大地起风雷，便有精生白骨堆。",
            "僧是愚氓犹可训，妖为鬼蜮必成灾。",
            "金猴奋起千钧棒，玉宇澄清万里埃。",
            "今日欢呼孙大圣，只缘妖雾又重来。"
        ],
        "translate": [
            "自从天地间刮起了风雷之后,白骨堆里就有精气产生了。",
            "僧人不过是个愚蠢的人,尚且可以教训他;如果妖怪变成鬼蜮,必然会成为灾祸。",
            "金猴王奋力挥舞着千钧的棒子,天宇澄清了万里尘埃。",
            "今天我们欢呼孙大圣,只因为妖雾又重来。"
        ]
    },
    {
        "title": "咏贾谊",
        "type": "七言律诗",
        "paragraph": [
            "少年倜傥廊庙才，壮志未酬事堪哀。",
            "胸罗文章兵百万，胆照华国树千台。",
            "雄英无计倾圣主，高节终竟受疑猜。",
            "千古同惜长沙傅，空白汨罗步尘埃。"
        ],
        "translate": [
            "少年时风流倜傥,是朝廷栋梁之才,但壮志未酬,实在令人悲哀。",
            "胸中包罗着丰富的文化知识,拥有百万雄兵;胆气照耀着国家,修建了千座高台。",
            "英雄豪杰没有办法颠覆圣明的君主,高尚的节操最终却遭到猜疑。",
            "千秋万代都同情长沙王傅,徒然地说汨罗江行走已化为尘埃。"
        ]
    },
    {
        "title": "洪都",
        "type": "七言律诗",
        "paragraph": [
            "到得洪都又一年，祖生击楫至今传。",
            "闻鸡久听南天雨，立马曾挥北地鞭。",
            "鬓雪飞来成废料，彩云长在有新天。",
            "年年后浪推前浪，江草江花处处鲜。"
        ],
        "translate": [
            "到洪都后又过了一年,祖逖击楫的乐声至今还在流传。",
            "鸡叫了很久才听到南天下雨的声音,我骑在马上曾经挥动过北地的马鞭。",
            "满头白发的雪花飞来,把它当作废弃的原料堆积起来;而天空中的彩云却长久地存在着,这才有新的一天。",
            "年复一年,江水的波浪推翻了以前的波浪,江边的草和江边的花到处都新鲜。"
        ]
    },
    {
        "title": "读报诗之一",
        "type": "七言律诗",
        "paragraph": [
            "反苏忆昔闹群蛙，今日欣看大反华。",
            "恶煞腐心兴鼓吹，凶神张口吐烟霞。",
            "神州岂止千重恶，赤县原藏万种邪。",
            "遍寻全球侵略者，惟余此处一孤家。"
        ],
        "translate": [
            "回想起从前一群群的蛙,今天我欣喜地看到了大反华。",
            "凶恶的魔鬼腐烂了心性就兴起鼓吹乐,凶恶的神灵张开嘴巴吐出烟霞。",
            "中原地区难道只有千种罪恶,赤县原野上藏着万种邪恶。",
            "到处寻找被金人侵略的国家,只剩下这座孤零零的人家。"
        ]
    },
    {
        "title": "读《封建论》，呈郭老",
        "type": "七言律诗",
        "paragraph": [
            "劝君少骂秦始皇，焚坑事业要商量。",
            "祖龙魂死秦犹在，孔学名高实秕糠。",
            "百代都行秦政法，十批不是好文章。",
            "熟读唐人封建论，莫从子厚返文王。"
        ],
        "translate": [
            "我劝你不要大骂秦始皇,要和他一起商量焚烧秦始皇的坟墓的事。",
            "祖龙的魂魄死后秦朝仍然存在,孔子的学问名声虽高但实际上只是个秕糠。",
            "历代都实行秦朝的残暴政令和刑法,即使有十篇文章也不能算是好文章。",
            "仔细阅读《唐人·封建论》,切记不要听从子厚劝说周文王返归周朝。"
        ]
    },
    {
        "title": "登庐山",
        "type": "七言律诗",
        "paragraph": [
            "一山飞峙大江边，跃上葱茏四百旋。",
            "冷眼向洋看世界，热风吹雨洒江天。",
            "云横九派浮黄鹤，浪下三吴起白烟。",
            "陶令不知何处去，桃花源里可耕田？"
        ],
        "translate": [
            "一座大山高高耸立在大江边上,它从茂密的树林中飞跃而上,盘旋在四百里长的江面上。",
            "我用冷眼向着大海看世界,热风吹来,大雨倾盆落在江面上。",
            "高耸入云的九条支流上,一只黄鹤在浮游;波涛滚滚,从三吴江面上涌来,弥漫着白色的烟雾。",
            "陶渊明不知道要到哪里去,桃花源里还能耕田吗?"
        ]
    },
    {
        "title": "答友人",
        "type": "七言律诗",
        "paragraph": [
            "九嶷山上白云飞，帝子乘风下翠微。",
            "斑竹一枝千滴泪，红霞万朵百重衣。",
            "洞庭波涌连天雪，长岛人歌动地诗。",
            "我欲因之梦寥廓，芙蓉国里尽朝晖。"
        ],
        "translate": [
            "九嶷山上空白云在飞翔,仙子乘风从翠微山上升腾。",
            "一枝斑竹让人伤心落泪,万朵红霞惹人怜爱穿上百层衣裳。",
            "洞庭湖水波涛汹涌,与天上的白雪相连;长岛上的人唱着动地的歌谣,使诗句更加动听。",
            "我想借着这美妙的梦境,在寥廓的世界里做个梦,那繁花似锦的荷花园里,早晨都沐浴在阳光的照耀下。"
        ]
    },
    {
        "title": "湘江漫游联句",
        "type": "五言律诗",
        "paragraph": [
            "晚霭峰间起，归人江上行。",
            "云流千里远，人对一帆轻。",
            "落日荒林暗，寒钟古寺生。",
            "深林归倦鸟，高阁倚佳人。"
        ],
        "translate": [
            "傍晚雾气从山峰间升起,归人沿着江岸行走。",
            "云彩在空中飘荡,千里迢迢;人面对着一叶孤舟,只觉风帆十分轻盈。",
            "夕阳西下,荒凉的树林显得格外幽暗,古老寺庙里传来阵阵寒钟。",
            "疲倦的鸟儿从幽深的树林中归来,在高高的楼阁上依偎着美丽的人。"
        ]
    },
    {
        "title": "张冠道中",
        "type": "五言律诗",
        "paragraph": [
            "朝雾弥琼宇，征马嘶北风。",
            "露湿尘难染，霜笼鸦不惊。",
            "戎衣犹铁甲，须眉等银冰。",
            "踟蹰张冠道，恍若塞上行。"
        ],
        "translate": [
            "清晨雾气弥漫了整个天宇,北风呼啸,马儿在北风中嘶叫。",
            "露水打湿了衣服,灰尘难以染上;严霜笼罩着乌鸦,它们也不被寒气所惊动。",
            "身穿军装的战士还穿着坚固的铠甲,胡须和眉毛都洁白如银冰。",
            "在张冠道上踟蹰徘徊,恍惚间就像在边塞上行走。"
        ]
    },
    {
        "title": "看山",
        "type": "五言律诗",
        "paragraph": [
            "三上北高峰，杭州一望空。",
            "飞凤亭边树，桃花岭上风。",
            "热来寻扇子，冷去对美人。",
            "一片飘飘下，欢迎有晓莺。"
        ],
        "translate": [
            "我三次登上北高峰,眺望杭州,只见杭州城一片空旷。",
            "飞凤亭旁边的树木,桃花岭上吹来阵阵清风。",
            "天气炎热的时候去寻找扇子,天气寒冷的时候面对着美人。",
            "黄莺儿从天而降,飞来飞去地迎接晨莺啼叫。"
        ]
    },
    {
        "title": "挽戴安澜将军",
        "type": "五言律诗",
        "paragraph": [
            "外侮需人御，将军赋采薇。",
            "师称机械化，勇夺虎罴威。",
            "浴血冬瓜守，驱倭棠吉归。",
            "沙场竟殒命，壮志也无违。"
        ],
        "translate": [
            "外敌入侵需要用武力抵御,将军赋诗赞美采薇。",
            "他的军队以精明强干著称,勇猛果敢地战胜了老虎和熊掌大的敌人。",
            "像浴血奋战一样坚守冬瓜,又像驱逐倭寇那样率领棠吉军返回。",
            "即使在战场上牺牲性命,壮志也决不会违背啊!"
        ]
    },
    {
        "title": "喜闻捷报",
        "type": "五言律诗",
        "paragraph": [
            "秋风度河上，大野入苍穹。",
            "佳令随人至，明月傍云生。",
            "故里鸿音绝，妻儿信未通。",
            "满宇频翘望，凯歌奏边城。"
        ],
        "translate": [
            "秋风从黄河上升起,浩瀚的原野映入了蓝天。",
            "美好的时令随着人到来,就像那皎洁的月光傍着浮动的白云一样。",
            "故乡的音信早已断绝,妻子儿女的书信也未能相通。",
            "全国上下高高地翘首盼望,胜利的歌声在边疆城池上传来。"
        ]
    },
    {
        "title": "送纵宇一郎东行",
        "type": "七言诗",
        "paragraph": [
            "云开衡岳积阴止，天马凤凰春树里。",
            "年少峥嵘屈贾才，山川奇气曾钟此。",
            "君行吾为发浩歌，鲲鹏击浪从兹始。",
            "洞庭湘水涨连天，艟艨巨舰直东指。",
            "无端散出一天愁，幸被东风吹万里。",
            "丈夫何事足萦怀，要将宇宙看秭米。",
            "沧海横流安足虑，世事纷纭何足理。",
            "管却自家身与心，胸中日月常新美。",
            "名世于今五百年，诸公碌碌皆余子。",
            "平浪官前友谊多，崇明对马衣带水。",
            "东瀛濯剑有书还，我返自崖君去矣。"
        ],
        "translate": [
            "衡山顶上云雾散开,阴云渐渐消散。天马和凤凰都隐藏在春天的树林里。",
            "屈原、贾谊年轻时就很有才华,他曾经把山川的奇异气质集中到这里来。",
            "你走吧,我为你高唱一曲《浩歌》。鲲鹏击浪飞翔,就是从这里开始的。",
            "洞庭湖和湘江的水涨得与天相连,大船和战舰一直向东驶去。",
            "无缘无故地散发出一天的忧愁,幸好被春风吹到万里之外。",
            "大丈夫有什么事情值得怀念萦绕心头呢?应该把整个宇宙看成是一块小小的稻米。",
            "沧海横流,有什么值得忧虑的呢?世间纷纭之事,又有什么值得去理会呢?",
            "不要管束自己的身体和心灵,要使胸中日月如梭,永远充满新的美好时光。",
            "名世到现在已经五百年了,各位英雄豪杰碌碌无为都成了我的遗民。",
            "在平浪官任上结交的朋友很多,崇明殿对着马衣带着水。",
            "到东瀛去洗剑,有书信送还,我从山崖上返回来,你却已经离去了。"
        ]
    },
    {
        "title": "冬云",
        "type": "七言律诗",
        "paragraph": [
            "雪压冬云白絮飞，万花纷谢一时稀。",
            "高天滚滚寒流急，大地微微暖气吹。",
            "独有英雄驱虎豹，更无豪杰怕熊罴。",
            "梅花欢喜漫天雪，冻死苍蝇未足奇。"
        ],
        "translate": [
            "大雪覆盖了冬天的云层,白絮在空中纷飞,无数的花瓣纷纷凋谢,在这季节里显得格外稀少。",
            "滚滚的寒冷江水像滚滚的浪花一样湍急,而大地却微微有些暖气吹拂着。",
            "只有英雄才能驱赶虎豹,更没有豪杰敢于畏惧熊罴。",
            "漫天飞舞的雪花让梅花欢喜,连那冻死的苍蝇都冻死了也不足为奇。"
        ]
    },
    {
        "title": "游学即景",
        "type": "七言诗",
        "paragraph": [
            "骤雨东风对远湾，滂然遥接石龙关。",
            "野渡苍松横古木，断桥流水动连环。",
            "客行此去遵何路，坐眺长亭意转闲。"
        ],
        "translate": [
            "东风吹拂着远处的河湾,骤雨突然降临,水势浩大,连绵不绝,直达了石龙关。",
            "野外的渡口横卧着苍松和古树,断桥下的流水在连环的曲折地流淌。",
            "客居他乡,从这里起要走哪条路呢?我坐在长亭上眺望,心情变得悠闲起来。"
        ]
    },
    {
        "title": "挽易昌陶",
        "type": "五言诗",
        "paragraph": [
            "去去思君深，思君君不来。",
            "愁杀芳年友，悲叹有余哀。",
            "衡阳雁声彻，湘滨春溜回。",
            "感物念所欢，踯躅南城隈。",
            "城隈草萋萋，涔泪侵双题。",
            "采采余孤景，日落衡云西。",
            "方期沆养游，零落匪所思。",
            "永诀从今始，午夜惊鸣鸡。",
            "鸣鸡一声唱，汗漫东皋上。",
            "冉冉望君来，握手珠眶涨。",
            "关山蹇骥足，飞飙拂灵帐。",
            "我怀郁如楚，放歌依列嶂。",
            "列嶂青且茜，愿言试长剑。",
            "东海有岛夷，北山尽仇怨。",
            "荡涤谁氏子，安得辞浮贱。",
            "子期竟早亡，牙琴从此绝。",
            "琴绝最伤情，朱华春不荣。",
            "后来有千日，谁与共平生？",
            "望灵荐杯酒，惨淡看铭旌。",
            "惆怅中何寄，江天水一泓。"
        ],
        "translate": [
            "离去吧,离去吧,思念你情意深厚;思念你,可你却不来。",
            "满怀愁绪把年高德劭的好友都吓跑了,独自悲伤叹息实在是多么的悲哀。",
            "衡阳城里大雁的鸣叫声已经远远传彻耳边,湘水之滨春水缓缓流回。",
            "感慨万物,怀念自己所喜爱的人,徘徊在南城的角落中。",
            "城墙的边上长满了茂盛的野草,我流着眼泪把这首诗题写在两行中。",
            "采呀,采呀,我独自一人在夕阳西下的时候,抬头望去,是那高耸入云的西方。",
            "我正期望能像洪波一样悠闲地游览,如今已经零落无存,不再是我所想要的了。",
            "与你永别的日子从今天开始,夜半时分你会被鸡鸣惊醒。",
            "公鸡一叫,我的汗水就沾满了东边的田野。",
            "我慢慢地盼望着你归来,紧紧握住你的手泪水直流。",
            "关山阻隔,骏马的脚步曲折艰难;狂风呼啸,轻拂着灵帐。",
            "我的忧愁像楚国一样深重,只能依傍着高高的山峰放声高歌。",
            "巍峨的群山青翠如黛,我真想用长剑来试一试。",
            "东海有岛屿上的少数民族,北方的群山上都充满了仇恨。",
            "洗涤尘世的是谁家之子?怎么能摆脱污浊卑贱的生活呢?",
            "子期竟然死得早,牙琴也从此断绝了音调。",
            "琴声凄绝最能使人伤感,春天里红花凋谢再也看不到光彩。",
            "以后再过千日,谁能和我共度这一生呢?",
            "遥望先祖灵位敬献美酒,看着那刻有铭文的旌旗黯然神伤。",
            "满怀惆怅又能寄托什么呢?只有那碧蓝的江天和一泓清澈的碧水罢了。"
        ]
    },
    {
        "title": "井",
        "type": "五言诗",
        "paragraph": [
            "天井四四方，周围是高墙。",
            "清清见卵石，小鱼囿中央。",
            "只喝井里水，永远养不长。"
        ],
        "translate": [
            "天井四四方方,周围是高墙。",
            "清澈见底的石头像卵一样大小,小鱼在石头中央游动嬉戏。",
            "一个人只要喝井里的水,就永远不会长大。"
        ]
    },
    {
        "title": "四言诗",
        "type": "四言诗",
        "paragraph": [
            "春草碧色，春水绿波。",
            "送君延安，快如之何！"
        ],
        "translate": [
            "春天的草色一片碧绿,春水泛起一圈圈绿色的涟漪。",
            "送你到延安去,那心情是多么的痛快,又有什么办法呢?"
        ]
    },
    {
        "title": "四言诗·题《中国妇女》之出版",
        "type": "四言诗",
        "paragraph": [
            "妇女解决，突起异军。",
            "两万万众，奋发为雄。",
            "男女并驾，如日方东。",
            "以此制敌，何敌不倾。",
            "到之之法，艰苦斗争。",
            "世无难事，有志竟成。",
            "有妇人焉，如旱望云。",
            "此编之作，伫看风行。"
        ],
        "translate": [
            "妇女们在战斗中拼命挣扎,突然间又发起了一支突围的军队。",
            "有两万万人马,奋勇杀敌才是真正的英雄。",
            "男女乘车并驾齐驱,就像太阳正向东方升起一样。",
            "用这种方法制服敌人,什么样的敌人不会倾覆呢?",
            "达到目的的方法,在于通过艰苦的战斗来实现自己的抱负。",
            "世界上没有一件难办的事情,只要有志向,就能成功。",
            "有个妇人在那里,像在干旱的时候盼望着云彩。",
            "我将此书编写出来,等待着看到它是否能随着风向发展。"
        ]
    },
    {
        "title": "六言诗·给彭德怀同志",
        "type": "六言诗",
        "paragraph": [
            "山高路远坑深，大军纵横驰奔。",
            "谁敢横刀立马？",
            "唯我彭大将军。"
        ],
        "translate": [
            "山高路远坑谷深,大军纵横驰骋在战场上。",
            "谁还敢横刀立马抗敌呢?",
            "只有我彭大将军才能做得更好。"
        ]
    }
]