[
    {
        "title": "次萤斋晚眺韵二首",
        "type": "五言诗",
        "paragraph": [
            "枫叶堕残霞，片片归根急。",
            "落日趁行人，百里半九十。",
            "云壑惬幽怀，万象随取给。",
            "小航截晚潮，客心徒岌岌。",
            "暝色垂天衣，苍然四无缝。",
            "破空冷月来，大地疑合冻。",
            "暮云还自佳，散作千峰梦。",
            "逍遥接闲吟，倦语倘惊众。"
        ],
        "translate": [
            "枫树的叶子像残霞一样坠落在天边,一片一片地向着自己的归宿急切盼望。",
            "落日追赶着走在路上的人,走了一百里还有九十里。",
            "在云雾缭绕的山谷中心情舒畅,万物都随心所欲地取而代之。",
            "小船拦截着傍晚的潮水,旅客的心情白白地忧心忡忡。",
            "昏暗的夜色下垂着天边的衣裳,苍茫一片四周没有缝隙。",
            "一轮破空的冷月从天上升起,大地仿佛要被冰雪覆盖了一样。",
            "傍晚时分,天空中的云彩依然格外美丽,它们散去后又呈现出万千山峰的美好梦境。",
            "闲来无事时,我与你一起悠闲地吟诗作赋,若是疲倦了的话语,也许会惊动众人。"
        ]
    },
    {
        "title": "游山杂诗三首",
        "type": "七言诗",
        "paragraph": [
            "随分看山有寄庐，老樵乍见未为疏。",
            "閒谈五百年前事，笑道先生也姓涂。",
            "清净长留劫外身，此山终古不能臣。",
            "一筇踏遍千峰翠，但觉烟霞为我新。",
            "小店山腰卓酒旗，凭栏一笑更何辞。",
            "兴酣拍手高歌去，万壑千岩听我诗。"
        ],
        "translate": [
            "慢慢地看到山上有我的茅庐,老樵夫刚一看见我还算不稀疏。",
            "闲来无事谈起五百年前的往事,笑着说先生也姓涂。",
            "清高洁净的本性永远留在世俗之外,这座山自古以来就不能使我臣服。",
            "拄着拐杖走遍了千山万岭,只觉得青山绿水都为我带来新意。",
            "山腰上小亭子高举着酒旗,我倚着栏干一笑又有什么话可说。",
            "兴致正浓时拍着手高歌一曲而去,在万壑千岩中听我吟诗。"
        ]
    },
    {
        "title": "乡居杂咏七首",
        "type": "七言诗",
        "paragraph": [
            "晓日曈曈照屋山，东窗竹影上斑斑。",
            "先生一笑梦初觉，目送清阴自往还。",
            "高柳鸣蜩昼转凉，芰荷出水透幽香。",
            "投竿坐挹千峰翠，鱼我悠悠意两忘。",
            "露痕如洗鸟频啼，行遍南溪又北溪。",
            "朝日未生云气好，微吟独立小桥西。",
            "村前村后趁凉游，物外闲观兴转幽。",
            "满地花光初过雨，手扶新竹上牵牛。",
            "早稻将登插晚秧，天然图界界青黄。",
            "开门便拟江乡老，菡萏风生午枕凉。",
            "青草湖头涨晚潮，阴云不雨树萧萧。",
            "放船南下如飞鸟，知过江村第几桥。",
            "菱芡初花绝可怜，鸣蛙田岸草芊芊。",
            "南塘日出无人到，十里晓风开白莲。"
        ],
        "translate": [
            "清晨的阳光明亮皎洁地照在屋脊上,东窗下的竹子影子斑斑点点。",
            "先生一笑,从梦中醒来,目送着清幽的阴影,不由自主地往来。",
            "高高的柳树上,蝉在鸣叫,白天变得凉爽了。菱角、荷叶从水中冒出,散发出阵阵幽香。",
            "放下钓竿坐着舀取千山万峰的青翠之色,鱼儿和我悠然自得地玩耍,全然忘却了彼此的情意。",
            "清澈的溪水流过,露水沾湿了它的痕迹,像洗过的一样。鸟儿不停地鸣叫着,我走遍了南溪,又走遍了北溪。",
            "早晨的太阳还未升起,云气很美,我独自一人在小桥西边低声吟诵。",
            "在村前、村后趁着天气的凉爽去游览,在各种景物之外悠闲地观赏景色,兴致变得更加幽雅。",
            "雨后初晴,满地绽放的花朵沐浴在细雨中,我手扶着新长的竹子,登上了牛背。",
            "初夏的稻子将要插入秋季的秧苗中,在天上呈现出一幅青黄相间的图画。",
            "刚一开门就想回到家乡老去,微风吹来午间枕上感到凉爽。",
            "青草湖边晚潮上涨,阴云密布,不下雨,树木在风中萧萧作响。",
            "放船南下就像鸟儿飞一样容易,不知道经过江边的村庄还有多少座桥梁?",
            "菱角和芡实刚刚开花十分可爱,田边青蛙在叫声中鸣叫着,野草长得密密稠稠。",
            "太阳从南塘升起时没有人赶到,十里之内的白莲迎着晨风绽放。"
        ]
    },
    {
        "title": "山居四首",
        "type": "五言诗",
        "paragraph": [
            "残菊不辞晚，犹开三两花。",
            "东篱多处士，知否忆陶家。",
            "泉自云根下，松从石上生。",
            "高吟山不答，惊我意峥嵘。",
            "晚笛穿云起，田家乐事多。",
            "可知牛背稳，无处著风波。",
            "归寻牛矢路，黄叶满山村。",
            "野径无人到，斜阳自闭门。"
        ],
        "translate": [
            "已经凋谢的菊花不怕天色晚了,还能有两三朵开放的花。",
            "东篱边有很多隐士,不知道他们是否还记得陶渊明的家呢?",
            "泉水从云母的根部奔泻而下,松树在岩石上生长。",
            "我高声地吟诗,山却不作答复,惊讶我的心意是多么的峥嵘。",
            "傍晚时分,悠扬的笛声穿过云雾而起,田间小院里农家常乐的事情很多。",
            "由此可知,牛的脊背安稳无比,不会遭到风波的摧残。",
            "回到家乡去寻找经过牛矢山的路,只见黄叶飘落满山村。",
            "荒野小路旁没有人来,夕阳斜照独自关着门。"
        ]
    },
    {
        "title": "夏窗书事六首",
        "type": "七言诗",
        "paragraph": [
            "乱蝉声里晚霞明，逭暑幽居绝送迎。",
            "薪爨微劳分妇稚，笑谈杂作半乡城。",
            "蔬缘手撷味尤隽，事以经多气转平。",
            "溪柳无风凉意足，可能重缔野鸥盟。",
            "书生投老百无成，一枕甜然梦不惊。",
            "偶为剖瓜伤国事，聊因种竹惜清名。",
            "四山主我皆孙稚，万卷相从若友生。",
            "帘外轻雷风乍起，自浇苦茗倚南荣。",
            "竹榻风清不动尘，随宜端可寄闲身。",
            "丝连屋角蜂投网，露缀枝头鸟哢晨。",
            "尽日语人无所隐，有时落笔觉如神。",
            "归来健饭妻儿喜，斗室长留万古春。",
            "一杯初发醉颜酡，眼底庭垣即涧阿。",
            "清咏乍闻知我返，足音坐久辨谁过。",
            "雨馀败壁蜗添篆，风急深林鸟唤囮。",
            "闲里作忙缘底事，诗情自笑晚来多。",
            "自汲清泉浸碧瓜，醰醰乡味尽堪誇。",
            "墙头风偃东西草，屋角晴开早晚霞。",
            "高树蝉鸣惊雀啄，小园花发闹蜂衙。",
            "宵来一雨添新涨，门外苍波没短葭。",
            "诗成信手未须删，长日如年自掩关。",
            "学道念生儒墨外，处身思在惠夷间。",
            "还家愧见鸡豚壮，思母空馀涕泪潸。",
            "暮雨萧萧风撼木，归耕终傍大嵊山。"
        ],
        "translate": [
            "阵阵蝉鸣声中,晚霞显得格外明亮。在这酷热的夏天,我独自一人在幽静的家里,没有人来迎接我。",
            "烧火做饭的微薄劳作分给了媳妇和小孩子,叽叽喳喳地议论着在半个乡城里。",
            "摘下新鲜蔬菜,味道特别鲜美;做事要经过许多次的努力,才能使精神转为平和。",
            "溪边的柳树没有风,凉意已经很充足了,可以重新和野鸥结下团盟。",
            "书生到了老年百无所成,安然一枕在梦中却没有被惊醒。",
            "偶尔因为剖瓜而伤感国家大事,姑且因为种竹而珍惜美好的名声。",
            "四座山的主人我和我的孙辈都还很小,在万卷书中跟随我就像是朋友一样。",
            "帘外突然传来阵阵轻雷般的微风,我独自一人在南边栏杆上喝着苦茗。",
            "竹制的床榻在清风中静静地躺着不沾满灰尘,随心所欲地安适地寄托自己悠闲的身影。",
            "蛛丝缠绕着屋角,蜜蜂在上面投下网;露水点缀着树枝,鸟儿在清晨鸣叫。",
            "我整天对人说起话来毫不隐瞒,有时一挥而就觉得简直是神采飞扬。",
            "我从北方回来,吃得饱饱的,妻子儿女都欢喜雀跃;我的斗室可以永远留下万古千秋的春光。",
            "刚刚喝完一杯酒,满脸是醉意,眼前的庭院墙壁就是山涧小道。",
            "刚刚听到你清雅的吟咏就知道我已经返回故乡,坐了很久才分辨出是谁经过。",
            "雨后枯败的墙壁上,蜗牛在上面添上了篆字;狂风呼啸,深林中的鸟儿正在呼唤猎物。",
            "闲来无事时为什么这样忙碌呢?我自己却笑话自己晚年写得太多了。",
            "自己汲取清澈的泉水浸泡在碧绿的瓜中,味道醇厚美好的家乡风味完全可以向人夸耀。",
            "墙头的风吹倒了东西两边的野草,屋角的阳光照耀下早晨和傍晚的晚霞分外明亮。",
            "高高的树上,蝉的叫声惊动了鸟雀的啄食;小园里的花开得正盛,蜜蜂正在忙着打草求蜜。",
            "夜里下了一场雨,水面又增添了新涨的潮水,门外的苍茫江水淹没了短小的芦苇。",
            "诗写成后,我就亲手抄录,不需要再删改了。我把门关上,日理万机,整天静静地欣赏着这美妙的诗歌。",
            "学习儒家学说应该在儒家墨家之外,立身处世应该在仁义和平民百姓中间。",
            "回家后惭愧地看见家中的鸡和猪都已经长大成人,思念起母亲空自流下眼泪。",
            "傍晚时分,雨声萧萧,风声震撼着树木,我归来耕作,最终还是依傍着大嵊山继续耕作。"
        ]
    },
    {
        "title": "石灰桥暮春杂咏十首选六",
        "type": "五言诗",
        "paragraph": [
            "经年聊避地，借宅未须占。",
            "在客无多取，于诗似不廉。",
            "荒村谁与语，老树自生髯。",
            "料是宵来雨，流泉百道添。",
            "滚滚禾川水，绵绵义岭岚。",
            "风雷鸣古涧，花竹媚新庵。",
            "妆借鱼池镜，丝抽野树蚕。",
            "无端生白发，谁唱望江南。",
            "山势波澜阔，乾坤蔚至文。",
            "冈峦开日月，草木郁风云。",
            "客燕将安托，哀笳不忍闻。",
            "中宵空起舞，满目尚妖氛。",
            "出门酬一笑，倦读卷随抛。",
            "水净风梳发，沙虚鸟布爻。",
            "幽花红未落，古蔓翠相交。",
            "得句何嫌晚，归灯手自抄。",
            "故乡无此景，烟雨数归樵。",
            "荒厕多于屋，新苔长过桥。",
            "莺花疑梦寐，儿女擅歌谣。",
            "何限登楼感，孤愁不可浇。",
            "小市集蔬米，初惊活计艰。",
            "深耕杂健妇，力作半娇鬟。",
            "青簇包头布，银摇坠耳环。",
            "古风流不尽，浒水自弯弯。"
        ],
        "translate": [
            "一年多来姑且避开乡间小路,借住的房子不需要再占为己有。",
            "在客居他乡时不要多取豪夺,写诗看来似乎不够清廉。",
            "在荒凉的村庄里,有谁能和我交谈呢?只有老树上长满了胡子。",
            "料想今晚将会下起雨来,百道泉水从天上涌出,增添了许多泉水。",
            "滚滚的禾川河水,绵延不断的义山岭上云岚。",
            "古老的山涧里风声雷鸣,新建的庵堂上花草竹子鲜艳动人。",
            "梳妆时借镜子照一照鱼池的美丽容颜,又从野外树上拔出蚕丝来梳妆打扮。",
            "我无缘无故地头上长满了白发,是谁在高唱着《望江南》这首诗呢?",
            "巍峨的泰山,波涛滚滚,浩瀚无边;苍茫的天地之间,蔚为壮美,文采奕奕。",
            "山冈上日月照耀,草木茂盛,风吹云散。",
            "客居他乡,将要寄托什么呢?哀怨的胡笳声实在不忍听。",
            "半夜里我白白地起身跳舞,满眼都是妖娆迷人的景象。",
            "出门去应酬一声笑,书卷疲倦了就随手抛开。",
            "清澈的河水,微风拂过,好像在为我梳理头发。沙滩上空空荡荡的一片汪洋,静静地栖息着一群群鸟儿,叽叽喳喳地念着爻辞。",
            "幽静的花儿还未凋谢,古老的藤蔓与翠绿的枝条交相辉映。",
            "写出这样的诗句为什么要嫌晚呢?我正好挑灯归来,手里亲自动手抄写。",
            "故乡没有这样的美景,在烟雨迷蒙中我屡次回家打柴。",
            "荒废的厕所比房屋还多,新长出的青苔越长越过了小桥。",
            "黄莺和鲜花好像是在睡梦中一样,一群群小儿女在不停地唱着歌谣。",
            "登上高楼的感慨有何限量,孤独的愁思无法排遣。",
            "在一个小小的集市上,人们正在买些蔬菜和米,刚一吃起,就觉得谋生太难了。",
            "在深山里耕作的妇女们夹杂着强健的丈夫,她们努力耕作的力气有一半是娇美的发髻。",
            "青色花纹的包头布,镶银的耳环轻轻摇动。",
            "古往今来的风尚至今流传不尽,只有那泅水悠悠地流着。"
        ]
    },
    {
        "title": "足疾经月出避空袭感作",
        "type": "七言律诗",
        "paragraph": [
            "挟杖惊呼夔一足，仰天宁叹出无车。",
            "苍鹰掠野憎秋眼，玄鸟栖林惜旅居。",
            "欲咒山云行作雨，乍看溪柳净如梳。",
            "仇深九世终当复，三户亡秦可启馀。"
        ],
        "translate": [
            "拄着拐杖惊呼夔的一只脚,仰天长叹出门无车可坐。",
            "苍鹰掠过旷野讨厌秋天的视线,玄鸟栖息在树林中珍惜自己的旅居。",
            "想用咒语把山上的云化作雨,忽然看见溪边的柳树洁净得像梳子一样。",
            "秦朝的仇恨已经深重九代了,最终还是应当收复失地。三户灭亡的秦朝后,可以重新启用剩余的百姓。"
        ]
    },
    {
        "title": "旅夜有怀潜渊外兄",
        "type": "五言诗",
        "paragraph": [
            "苟全托乱世，苦吟谁与邻。",
            "对此灯火光，辄复思所亲。",
            "羽翼不可假，云树徒怆神。",
            "眷念山中客，高歌如可闻。",
            "用舍亦何常，此理难具陈。",
            "剩取眼前乐，身外何足论。",
            "嗟我亦守拙，抖擞历邅迍。",
            "鸿毛遗万事，但矜佳句新。",
            "或当稍有得，以谢吾故人。",
            "举世竞终南，争登要路津。",
            "枉道自不能，要以全其真。",
            "已矣复何说，吾徒当贱贫。"
        ],
        "translate": [
            "苟全性命托付给乱世,苦吟诗篇又有谁能与我为邻?",
            "面对这明亮的灯光,我总是怀念那最亲的人儿。",
            "飞鸟的翅膀是不能借给别人的,飘浮在空中的树木徒然使神灵悲伤。",
            "怀念山中隐居的人,高声地唱着歌声好像可以听到。",
            "君主的任用与罢免有什么固定不变的规则呢?这种道理很难一一陈述出来。",
            "只求眼前的快乐,身外之事又有什么值得一提的呢?",
            "可叹我还是谨守拙劣之道,奋发有为经历了许多艰难险阻。",
            "鸿雁的毛笔留给世间万事,只可惜这首诗句清新。",
            "也许我能稍微有所收获,以此向老朋友道谢吧。",
            "举世之人都争着去终南山游玩,争着登上交通要道的渡口。",
            "歪曲道是自己做不到的,关键是要保全自己的真性。",
            "算了吧还有什么可说的呢?我们这些人应当轻视贫穷。"
        ]
    },
    {
        "title": "冒雪过东湖",
        "type": "五言诗",
        "paragraph": [
            "湖面泼羊脂，瑟瑟欲合冻。",
            "野鸭时一下，奋掌裂银瓮。",
            "玉戏迷大千，六合凭葬送。",
            "我身果何在，指点若凿空。",
            "仙灵冉冉趋，泠然蹑飞鞚。",
            "球琳灿可数，意作明堂贡。",
            "长桥卧不兴，潜虬孰能控？",
            "杂树列湖壖，僵立俨翁仲。",
            "西山忽皤然，际天明螮蝀。",
            "诸峰跽其下，簇簇攒角粽。",
            "大块气不噫，万族入帡幪。",
            "人天音阒然，肃将谁敢哄。",
            "霏霏韵转绝，洗耳谢俗哢。",
            "收心到初地，闵默神为恫。",
            "毁室叹鸱枭，栖枳伤鸾凤。",
            "四海足酸呻，豳诗寓微讽。",
            "我为猎食出，生事苦倥偬。",
            "冷毡成坐大，羞作参军弄。",
            "挟书十载过，鉴面馀一恸。",
            "春秋想佳日，绿蚁浮杯㔶。",
            "湔洗归平澹，此景冠吾赣。",
            "谁云金瓯缺，粉饰无罅洞。",
            "桃李不成春，大厦待梁栋。",
            "斧斤偶有施，意觉所全众。",
            "腐儒求自了，遑问邹鲁閧。",
            "归来把梅花，清圣时一中。",
            "醉卧拥汤婆，觅我罗浮梦。"
        ],
        "translate": [
            "湖面上撒满了白色的羊脂,雪花纷纷扬扬,似乎要冻结成冰。",
            "一只野鸭子不时地掉下来,它用手一挥,就撕开了银色的瓮。",
            "玉石嬉戏迷了大千,天地四方都凭着它来安葬送别。",
            "我的身子现在究竟在哪里呢?我所指点的地方就像是用凿空的一样。",
            "仙女缓缓行走在飞驰的马鞍上,轻轻地踩着那装饰华丽的马辔头。",
            "梅花的颜色鲜艳可数不清,我真想把它作为明堂的贡品。",
            "卧在长桥上不能动,潜伏着的虬龙谁能控制它?",
            "杂树丛生排列在湖边堤坝上,高大挺拔的树木俨然像个老翁。",
            "西山忽然变得苍茫无光,与天相接的地方天空已明亮得像螮蝀。",
            "群峰高高地耸立在山脚下,成群结队的山峰像角和粽子一样聚集在一起。",
            "大块的土地上没有什么怨气,众多的民族都安居乐业。",
            "人天的声音静悄悄地回荡着,恭敬严肃的将领有谁敢于喧哗呢?",
            "清澈明净的空气中,悠扬的音调随着时间的流逝而消失,我用它来洗耳解闷,摒弃庸俗的歌唱。",
            "要使自己的心境恢复到最初的状态,忧愁、沉默不语会使精神感到恐惧。",
            "被摧毁的房屋令人叹息是鸱枭在作恶,栖息在枳树上使鸾凤感到悲伤。",
            "普天之下,人人都感到酸楚可叹,《豳风》的诗句寄托了深刻的讽谏思想。",
            "我为了打猎而外出打猎,生活上各种事情都非常艰难繁忙。",
            "凉飕飕的毡子结成了坐垫那么大,简直是羞于被参军所戏弄。",
            "手里拿着书信已经十多年过去了,镜子照着面容只剩下一次痛苦。",
            "春秋两季总想着美好的日子,绿蚂蚁在杯中不停地爬动。",
            "洗过脸以后,心情才变得清静澹泊起来,这景色使我感到最欣慰。",
            "谁说美酒的杯子会缺口呢?因为它粉饰得没有一点缝隙和漏洞。",
            "桃李不能长成春天,大厦要等到有栋梁才能建成。",
            "用斧头和木棍偶尔施展一下作用,心里觉得可以保全很多人。",
            "我这个迂腐的儒生,只求自我完善,哪里还顾得上问邹、鲁之间的是非曲直呢?",
            "归来拿着梅花,在清明和圣明的时代欣赏到它。",
            "喝醉了酒躺在拥抱着热水的婆婆身上,她正寻找我在罗浮山上的梦境。"
        ]
    },
    {
        "title": "次萤斋晚眺韵二首 其一",
        "type": "五言律诗",
        "paragraph": [
            "枫叶堕残霞，片片归根急。",
            "落日趁行人，百里半九十。",
            "云壑惬幽怀，万象随取给。",
            "小航截晚潮，客心徒岌岌。"
        ],
        "translate": [
            "枫树的叶子像残霞一样坠落在天边,一片一片地向着自己的归宿急切盼望。",
            "落日追赶着走在路上的人,走了一百里还有九十里。",
            "在云雾缭绕的山谷中心情舒畅,万物都随心所欲地取而代之。",
            "小船拦截着傍晚的潮水,旅客的心情白白地忧心忡忡。"
        ]
    },
    {
        "title": "次萤斋晚眺韵二首 其二",
        "type": "五言律诗",
        "paragraph": [
            "暝色垂天衣，苍然四无缝。",
            "破空冷月来，大地疑合冻。",
            "暮云还自佳，散作千峰梦。",
            "逍遥接闲吟，倦语倘惊众。"
        ],
        "translate": [
            "昏暗的夜色下垂着天边的衣裳,苍茫一片四周没有缝隙。",
            "一轮破空的冷月从天上升起,大地仿佛要被冰雪覆盖了一样。",
            "傍晚时分,天空中的云彩依然格外美丽,它们散去后又呈现出万千山峰的美好梦境。",
            "闲来无事时,我与你一起悠闲地吟诗作赋,若是疲倦了的话语,也许会惊动众人。"
        ]
    },
    {
        "title": "宛社初集分均得作字",
        "type": "五言诗",
        "paragraph": [
            "匡蠡美不收，间时诗豪作。",
            "首出数陶公，上与风骚薄。",
            "踵武双井黄，开宗为木铎。",
            "殿之散原翁，万流归其壑。",
            "江西忠义邦，馀事犹卓荦。",
            "三峰仰太华，闻天九皋鹤。",
            "沾溉到后生，起废一丸药。",
            "烟消春景明，盍簪趋北郭，夹衢树向荣，风定鸟声乐。",
            "城中十万家，草木影萧索。",
            "岂意丧乱馀，萍踪偶同泊。",
            "飞鸿送远音，高举谢矰缴。",
            "一片西山云，霖雨梦如昨。",
            "呴濡情何殷，寸语千金博。",
            "尤喜近老成，一树占百穫。",
            "从容文字饮，描画羞头脚。",
            "呼吸万灵通，性命疑可托。",
            "叩钟大小鸣，馀兴肆挥霍。",
            "宗风瓣香在，山木工所度。",
            "馀兴且饯春，高花红未落。",
            "更待荷钱生，东湖泛清酌。"
        ],
        "translate": [
            "匡衡、范蠡的诗作没有被收录,闲暇之时却有豪放不羁的诗作。",
            "我首先列举陶渊明的功绩,他与《风骚》诗篇格外亲近。",
            "继承先王的事业,功绩卓著,像双井那样光彩夺目;开创宗族基业,用木铎声威震人。",
            "殿堂前的原野上,一位老翁早已去世,江河水流纷纷,都汇聚到他的山谷中去了。",
            "长江以南是忠义之邦,其余的政事还是卓绝不凡的。",
            "登上华山,仰望太华山顶;从九皋传来鹤唳的声音,仿佛听到了天上的仙鹤。",
            "父母的恩泽一直浸润到后代,甚至连一丸药都废弃不用。",
            "暮霭渐渐消散,春天的景色更加明丽。我头戴盍簪奔向北城,两边的街道上树木正争奇斗艳,春风停歇时,鸟鸣声也显得格外悦耳。",
            "长安城里有十万户人家,草木的影子在萧索的景象下显得格外美丽。",
            "哪里料到在战乱之后,江河中的浮萍偶然一同停泊下来。",
            "远飞的鸿雁向我传递音讯,我高高举起缴获的箭镞感谢你的恩德。",
            "西山上一片乌云遮天蔽日,连绵不断的雨水打湿了我的梦魂,就像昨晚一样。",
            "温柔婉转的情谊是多么深厚,每一句话都值得千金珍重。",
            "最喜的是近老成的人,一棵树可以预兆百谷丰登。",
            "从容不迫地在书房里写字饮酒,用手描绘自己头发和脚趾头都感到羞耻。",
            "人的呼吸可以与万事万物相通,人的性命也许可以托付给谁呢?",
            "敲响大钟,让钟声从小到大地轰鸣,余兴正浓,随心所欲地任意挥霍。",
            "春风吹来,花瓣飘落,散发着阵阵清香,这是山林中的木匠把它吹过的地方。",
            "趁着余兴暂且为春天饯行,百花盛开红艳艳的花朵还没有凋落。",
            "等到荷叶长出来,在东湖上泛一池清酒,自得其乐。"
        ]
    },
    {
        "title": "偕剑鸣毅庵夜泛东湖",
        "type": "七言诗",
        "paragraph": [
            "澄湖如练不可唾，一叶忽教琉璃破。",
            "森然寒碧浸毛发，偃仰明月照高卧。",
            "出手芙蓉三尺强，亭亭濯秀谁能涴。",
            "鸂鶒鵁鶄了无猜，宛晚花间自鸣和。",
            "隔岸灯火烂秋星，飞光摇绿如椀大。",
            "笑语闲闲不知晚，滩横水激双桨挫。",
            "了知此乐千载无，火速追摹聊自贺。"
        ],
        "translate": [
            "清澈的湖水像一匹白色的白绢,不能用嘴把它涂在污秽的地方。忽然有一片叶子掉下来,把那琉璃瓦都弄破了。",
            "碧绿的山色笼罩着我的毛发,我仰卧在明月下,沐浴在清凉的月光下。",
            "伸出手来,那三尺长的芙蓉花,亭亭玉立,谁能将它洗涤干净呢?",
            "鸂鶒鵁鶄全然没有猜疑,宛如傍晚时分在花丛中自然鸣叫和鸣。",
            "江岸的灯火照亮了秋天的星星,它的光芒在绿色的树叶上闪耀,就像一只大碗那样。",
            "闲来无事,谈笑自如,不知不觉已是傍晚。河滩横着,水流湍急,两只桨被激起的浪花打断了。",
            "知道这首词千载难得,火速地追摹它姑且自我庆贺。"
        ]
    },
    {
        "title": "题玄楼雪夜联句图",
        "type": "七言诗",
        "paragraph": [
            "玄宇沉沉欲翻雪，一夜严城锢寒铁。",
            "灯前相濡炉不温，俄惊瓦上飘玉屑。",
            "小楼冻压诗作魔，外冷宁敌此心热。",
            "陈侯英英笔有神，手抉地肺探虎穴。",
            "看人白眼双鬓皤。",
            "灵光夜炯心头血。",
            "紫髯后人工写生，弹指台阁生丘垤。",
            "西山挂梦一角青，坐令猿鹤笑人拙。",
            "灯前叉手领二豪，茫茫尘海皆虮虱。",
            "短歌长吟接咿嚘，花面为说阿难偈。",
            "吾曹端合生太平，随分耕凿歌帝德。",
            "不然自甘作殷顽，麦秀之章写哀烈。",
            "乱世偷活鸡犬羞，吾生邂逅应结舌。",
            "马耳东风且休论，方寸未觉桃源隔。",
            "传真偶留指爪痕，照坐峨峨屋山洁。"
        ],
        "translate": [
            "天空沉沉茫茫好似要翻滚的白雪,一夜之间坚固的城墙被寒铁所阻挡。",
            "在灯前互相浸湿,炉子却不暖。不一会儿,惊醒了,瓦上飘落下玉屑。",
            "小楼上的寒气把我压得要发诗作魔,外面的寒冷怎么能抵得过内心的炎热呢?",
            "陈侯的大手笔真是神采飞扬,他亲手挖地肺去掏老虎的洞穴。",
            "看人眼珠白了,鬓发也变得稀疏。",
            "月亮在黑夜里发出耀眼的光芒,闪烁着令人心碎的鲜血。",
            "紫色胡须以后,我用手在画像上描绘自己的形体,那弹指间画出的台阁像丘垤一样奇丽。",
            "西山像在梦中一样青翠,坐下来让猿猴仙鹤讥笑我愚笨无能。",
            "在灯前叉着手领着两个豪杰,茫茫的尘世上都长满了虱子。",
            "用短歌和长吟来迎接咿嚘的叫声,我面带花纹为她诵读《阿难偈》。",
            "我们应该安居乐业以求获得天下太平,努力耕作开凿河道以歌颂尧舜的功德。",
            "如果不是这样,那就应该甘愿做殷纣王那样的顽劣之人,像麦秀那样的诗篇来抒发自己的哀痛和悲愤吧。",
            "在乱世里苟且偷生,鸡犬都感到羞耻;人生短暂,与君邂逅相遇,就应该结舌而别。",
            "马耳和东风暂且不要再多说了,方寸之内还感觉不到桃源被阻隔。",
            "传真偶尔留有脚趾爪的痕迹,照着座位高耸入云的屋顶山色明净。"
        ]
    },
    {
        "title": "城东老媪行",
        "type": "五言诗",
        "paragraph": [
            "树老怕心空，人老怕路穷。",
            "衰媪年七十，茕茕家城东。",
            "衣食数间屋，送养若孙童。",
            "邻人切切言，所苦双耳聋。",
            "须臾警吏来，云当马路冲。",
            "大府限时日，拆让莫从容。",
            "媪闻无可语，俯首泪横纵。",
            "警吏出门去，兀坐犹忡忡。",
            "邻人乃相谓，官言法即从。",
            "自拆木石完，官拆尘土封。",
            "举首谢邻人，数载沐情浓。",
            "今当从此别，消息各飞蓬。",
            "夜月照床头，束带悬其中。",
            "阁阁声未绝，媪已返幽宫。",
            "观者窃悲叹，死生理亦同。",
            "末世会有此，谁云非令终。",
            "客闻起长喟，独往吊悲风。",
            "媪骨想未冷，寒日明败墉。"
        ],
        "translate": [
            "树木一棵棵地长大了,就怕它的枝干枯萎凋零;人到老了,就怕路途遥远无路可走。",
            "一个衰老的老婆婆已经七十岁了,独自一人在城东面守着家。",
            "衣食住有好几间屋子,奉养像孙子、童子一样。",
            "邻居严厉地责备我说,我所痛恨的是双耳聋。",
            "不一会儿,一个警卫小吏来了,说:你应当在马路上冲击敌人。",
            "大官府的任免期限有明确的期限,拆除职权不要太从容。",
            "老妇人听了无言以对,低头哭泣泪水纵横交错。",
            "看守警戒的官吏已经出门离去,我兀自端坐在那里仍然忧虑忡忡。",
            "邻居们互相议论,官府说出了法律就依从了。",
            "自己拆除的木头和石头都已完好无损,官府拆掉灰尘把它封起来了。",
            "举起头来向邻居道歉,他多年相处情意浓厚。",
            "今天就要从这里告别了,你们之间的音讯就如同飞蓬一样各自散去。",
            "夜晚的月光照在床头,我系好腰间的束带悬挂在床上。",
            "阁阁的鸣叫声还没有断绝,老妇人已经回到幽静的宫中去了。",
            "围观的人私下里暗自悲叹,死和生也是一样的。",
            "衰败的时代总会有这样的事情,谁说它不会有好结果呢?",
            "客人听了这番话,立即起身长叹,独自前往,凭吊那悲凉的秋风。",
            "老妇人的骨头料想还未受过寒冷,严寒的太阳一照就已经毁坏了墙壁。"
        ]
    },
    {
        "title": "己卯三月舟发永泰赴永新石灰桥",
        "type": "五言诗",
        "paragraph": [
            "江南寇益骄，贤者思避地。",
            "偷生非吾徒，弦歌宁可废？",
            "堂堂复兴业，以此孕元气。",
            "西山圉未固，坐闻南昌弃。",
            "安义传失守，奉靖复相继。",
            "含泪决再迁，校中顿如沸。",
            "师生黯然别，覆巢惨无异。",
            "明发携妇弱，聊作买舟计。",
            "江边接舳舻，一一来封示。",
            "破漏虽幸得，唇舌既云敝。",
            "南风久不竞，欸乃惜濡滞。",
            "回望文昌塔，依依有馀思。",
            "橘林云与平，千家隔苍翠。",
            "薄暮舣峡江，两岸山夹峙。",
            "盈盈一水通，天险疑可制。",
            "草木郁春城，中蕴荒凉意。",
            "昏灯刺眼明，狂鼾妒人睡。",
            "怅望月影斜，梦竟为我避。",
            "舀水煮江鱼，朝餐殊不费。",
            "佐以土产粉，大嚼有馀味。",
            "行近三曲滩，风雨压头至。",
            "涛山互推排，枕席为移位。",
            "老媪悲诵佛，小儿啼弃饵。",
            "而我展杜诗，甘吟了无畏。",
            "呼吸千帆定，南奔如渴骥。",
            "槃槃吉安城，倏已来眼际。",
            "登岸一徘徊，精华委凋瘵。",
            "敌机时肆虐，白日门多闭。",
            "居者侧耳听，行人翘首视。",
            "警笛一悲鸣，忽忽忘所自。",
            "林迷鸟乱投，予亦匿沟次。",
            "日影下青萝，风定自摇曳。",
            "静观意若忘，悠悠成妙契。",
            "偷眼瓦砾场，中有万人泪。",
            "死者骨已灰，青烟犹若燧。",
            "痛心念人言，昨日午前事。",
            "亚东久并立，同种一文字。",
            "相煎无乃愚，自伐尤不智。",
            "求生出孤注，匹夫不夺志。",
            "屠灭及后方，横暴古无例。",
            "月上万灯华，裙屐转都媚。",
            "乘夜各有营，憧憧俨狐魅。",
            "微闻丝竹声，悠扬出高第。",
            "从知生死关，中亦有人醉。",
            "惊定议易舟，未敢失交臂。",
            "仰天索价昂，出门诚不易。",
            "乱世视太平，千里在庭砌。",
            "逆水挽危樯，帆楫失其利。",
            "滞重去若牛，进钝退何锐。",
            "半日抵神冈，敌机见青霭。",
            "轧轧声在顶，一弹下平濑。",
            "望之不十寻，浪花涌澎湃。",
            "大鱼浮满江，价贱未须卖。",
            "虎口庆重生，安命复何赖。",
            "过此滩渐多，处处藏机械。",
            "一滩一滩高，一滩一滩隘。",
            "张吻如有伺，磨牙疑不耐。",
            "败舟散前流，飘蓬知何届？",
            "纤夫五六人，力疲神亦败。",
            "尻高出林表，首乃埋草内。",
            "啁哳劳者歌，时引村尨吠。",
            "两岸山连镳，两山树张盖。",
            "峰回水异流，路转鱼逐队。",
            "参差绿成围，高下红相对。",
            "花花香自升，叶叶光可爱。",
            "妆出晚春容，妖韶有馀态。",
            "遥指化骨滩，舟子色相戒。",
            "滩侧横鱼梁，银涛相击汰。",
            "白日奋雷霆，晴空弄阴晦。",
            "大石扼中流，孤航下其背。",
            "虎痒竟可揩，拍手真一快。",
            "步步度荆棘，过此意无碍。",
            "枪声忽撼篷，速舣谁敢懈。",
            "赳赳四五夫，封船肆狡狯。",
            "竟欲夺吾有，逍遥供彼载。",
            "宛转相与求，强辞杂诟谇。",
            "世乱理久亡，即此安足怪。",
            "不见老榜人，两腿饱皮带。",
            "有勇当杀故，卫民顾为害。",
            "传闻吾丰城，警队竟哗溃。",
            "从未见一敌，焚掠出阛阓。",
            "沿途鸡犬绝，流民更谁绘？",
            "嗟嗟保甲疏，豺狼成啸聚。",
            "训练复无方，吾事焉不坏？",
            "摇兀及兼旬，始入永新界。",
            "江山益雄秀，花竹何暗暧。",
            "交通辟新途，团圞荫松桧。",
            "不闻喊弟兄，但闻呼姊妹。",
            "跣足赤双颊，谁能施粉黛？",
            "勤非男子及，力堪男子赛。",
            "种作泥中者，粥粥皆此辈。",
            "乃知天生材，元不限流派。",
            "人力诚已充，物力自丰沛。",
            "抗敌同一心，胜不待蓍蔡。",
            "试展历史看，外侮非一代。",
            "忧患生之徒，古人有良诲。",
            "大痛忍眼前，此心应不昧。",
            "请听杀敌歌，四船何慷慨。",
            "江风浩荡吹，红日已西迈。",
            "民气茁已长，吾兴殊未艾。",
            "终当饮榑桑，一蹴樱花碎。",
            "泱泱起亚东，万国仰风拜！"
        ],
        "translate": [
            "江南的敌寇越来越骄横,贤能的人也都想逃避到别的地方去。",
            "苟且偷生不是我的同类,弹琴唱歌怎么可以废弃呢?",
            "堂堂正正地振兴了大唐的基业,用它来孕育天地间万物的元气。",
            "西山的险要之处还未牢固,却坐听到南昌城被放弃的消息。",
            "安义寺传来失守的消息,奉靖寺的事件又接连发生。",
            "我含着眼泪决心再升迁,军营里的人顿时像沸水一样地涌出。",
            "师生们悲伤地分别了,跟翻了巢的惨景没有什么两样。",
            "明天早晨起来携带妻子走路,姑且想着买一叶小舟渡江。",
            "在江边接连不断地停泊着的船只,我把它们一一封好交给你们看。",
            "破漏虽然是幸运的,但嘴唇舌头却已经很破旧了。",
            "南风吹来已经很长时间了,可是它却始终不肯与我争先。唉呀!可怜它被吹得湿透了又停滞不前啊!",
            "回头眺望文昌塔,那高耸入云的古塔令人思绪万千。",
            "翠绿的橘林与天平线相连,千家万户隔着碧绿的橘林居住。",
            "傍晚时分,我乘船顺着峡江而上,两岸的群山夹峙相对。",
            "圆圆的河水互相贯通,天险似乎可以制伏。",
            "春天的长安城中,草木茂盛,郁郁葱葱,其中蕴藏着一种荒凉之意。",
            "昏暗的灯光刺人眼神明亮,狂呼乱叫的鼾声嫉妒别人睡得好。",
            "惆怅地望着斜斜的月影,梦中竟然为了我躲避了。",
            "用勺子舀水来煮江中的鱼,吃上早餐一点也不费力气。",
            "再用土产的粉末佐食,细细地咀嚼后还有余味。",
            "行至三曲滩时,忽然风雨骤起,把我逼得头昏目眩。",
            "波涛像山一样互相推排,枕头和席子也因此而移动位置。",
            "老妇人悲伤地诵读佛经,小孩哭泣着扔掉食物。",
            "而我却展开《杜甫诗》,甘愿吟诵它,毫不畏惧。",
            "呼吸之间,千万只船儿就停下来了,像渴了的千里马一样向南奔跑。",
            "繁华富丽的吉安城,一下子就来到我的眼前。",
            "登上岸后徘徊不前,只见满身的花朵凋谢枯萎。",
            "敌人乘着时机不时地施加暴虐,白天很多城门都紧闭着。",
            "居住在家里的人侧着耳朵倾听,走路的人翘首远望。",
            "当警笛一声悲切的呜叫时,我忽然忘记了它是从哪里吹来的。",
            "树林迷离了,鸟儿四处乱蹦乱跳,我也躲藏在沟渠旁边。",
            "夕阳的影子从青翠的藤萝上缓缓落下,微风停息后藤萝依然在轻轻摇曳。",
            "静静地观看书本,好像把思想内容全都忘记了,悠然自得地与书本上的精妙意境相契合。",
            "在偷眼看到的瓦砾场,里面有上万个人的泪水。",
            "死去的人的骨头已经化成了灰烬,但那青色的烟雾仍然像烽火台上的烽烟。",
            "我伤心不已,回想起昨天早晨所说的话,心中十分痛苦。",
            "《亚东传》和《墨子闲诂》已经很久没有两样并立了,它们的文字是同一个种类的。",
            "互相残害并非是愚蠢,自我夸耀却更不聪明。",
            "为了求得生存,他孤零零地站在原野上,即使是普通的人也不能改变他的志向。",
            "周武王的残暴统治一直延续到后世,自古以来对周武王的横行霸道从未有过先例。",
            "皎洁的月光下,万盏明亮的灯火闪耀着光芒,少女们的裙子和鞋子也变得十分妩媚。",
            "在黑夜里,每个人都各有自己的营盘,神情恍惚,好像狐狸和妖怪一样。",
            "耳边仿佛听到了悠扬的丝竹乐声,它那悠扬的乐声好像是出自高雅之处。",
            "你看这生死关口有多么紧迫,其中也有人把我灌醉了。",
            "惊讶地决定换乘这条船,不敢失掉朋友的手臂。",
            "抬头仰望天空,求购的东西价格昂贵,出门做买卖确实不易。",
            "在动乱的时代看待太平盛世,即使有千里之遥的国土也在庭院台阶上。",
            "逆流而上,撑着高大的桅杆,船只和小船都失去了航行中的便利。",
            "滞留不前就像牛一样,前进迟钝后退又何等的敏捷。",
            "半天功夫抵达神冈山,敌人进攻的阵地已经呈现出青霭般的云气。",
            "轧轧的声音从头顶传来,一根弹弓射向平坦的沙滩。",
            "从远处看不到十寻,浪花就汹涌澎湃地涌来。",
            "大鱼漂浮在江面上,价格便宜不需要出卖。",
            "在虎口祝贺自己能够复活,安享天命还有什么可依赖呢?",
            "从这里经过的河滩逐渐增多,到处都隐藏着一些阴谋诡计。",
            "一滩一滩地势高,一滩一滩地势低。",
            "张开嘴巴好像是在等待,磨掉牙齿又怀疑它不能忍受。",
            "一只破败的船儿在前面漂流,飘泊不定的蓬草不知到哪里去呢?",
            "身材矮小的人有五六个,体力用尽了精神也就衰败了。",
            "屁股高高地伸出树林之外,脑袋却埋藏在杂草丛中。",
            "乡间劳民伤财的人在唱歌,不时地还引来村里的狗的叫声。",
            "两岸的山峦绵延不断,两边的山上树木高高地耸立在树梢上。",
            "山峰回环,河水流向不同方向,山路曲折,鱼儿成群结队地游来游去。",
            "参差不齐的绿树成行成围,高低起伏的红花相对绽放。",
            "每一朵花都散发着清幽的香气,每一片叶子都闪耀着光芒,可爱无比。",
            "她梳妆打扮出了晚春的容颜,妖娆艳丽的姿态还带着余韵。",
            "船夫远远地指向化骨滩,船上的人脸色都变了,互相告诫。",
            "河滩旁边横架着一条鱼梁,银白色的波涛在水面上相互冲击荡涤。",
            "阳光照耀下像雷霆一样振奋,在晴朗的天空中拨弄着阴暗。",
            "巨石扼守着江心的中心,一只小船顺流而下,停泊在巨石的背后。",
            "老虎咬得太厉害,竟然可以用揩拭的办法去除掉它,拍手真是痛快。",
            "脚步小心翼翼地越过荆棘,走过这里心情就不会有什么阻碍。",
            "枪声忽然把船篷震撼起来,快马赶路谁还敢松懈?",
            "气宇轩昂的四五个壮士,把船封闭起来放肆地玩弄狡猾的金人。",
            "你竟然要夺走我所有的东西,让我逍遥自在地供他乘坐车子。",
            "曲意逢迎,互相求情,勉强推辞,遭到各种辱骂。",
            "世道动乱,治国之道已经衰亡很久了,就是这样又有什么值得奇怪的呢?",
            "看不见那老榜人,只见他两腿上扎满了皮带。",
            "勇敢的人应当杀掉过去的仇敌,可是保卫自己的百姓却反而会成为祸害。",
            "传说我住在丰城,守卫京城的警卫队竟然大吵大闹溃逃了。",
            "从未见过一个敌人,被他们焚烧抢劫的财物逃出了集市。",
            "沿途的鸡犬已经断绝,流亡在外的百姓还有谁来为我画像?",
            "唉呀,守卫的盔甲太稀少了,豺狼成群地在呼啸着聚集起来。",
            "教育又没有一定的方法,我的事情怎么能不败坏呢?",
            "漂泊不定已有十多天时间,才进入永新县界。",
            "江山越发雄伟秀丽,花草竹子为什么这样暗淡无光呢?",
            "交通要道开辟了一条新路,山坡上松树和桧树的树荫都遮盖住了。",
            "我听不到弟兄们呼喊的声音,只听到姊妹们呼唤的声音。",
            "光着脚赤着双颊的少女,谁能为她涂抹胭脂呢?",
            "勤劳是男子汉所赶不上的,但力量却可以和男子汉相匹敌。",
            "播种在泥土中的作物,成熟的果实累累都像这种东西。",
            "由此可知,天生有才华的人,本来就不会受到世人的流传和差别。",
            "人的精力确实已经充足,物力自然就丰富充沛了。",
            "同心协力,与敌人决一死战,取胜不用占卜就行了。",
            "试着翻开历史来看,被外族所侵略的并非同一朝代。",
            "忧患滋生的人,古人对他们都有好的教诲。",
            "眼前的痛苦忍不住涌上心头,我的内心一定不会愚昧。",
            "请听一听那《杀敌歌》,那四只战船的将士多么慷慨激昂。",
            "江风浩荡地吹着,红日已经向西而去。",
            "百姓的士气已经日渐增多,我的事业兴旺发达还未来得及。",
            "我终究要喝烂了的桑叶,一踢樱花就把它打碎。",
            "泰山巍然耸立在东方,天下万国都仰望着泰山向泰山朝拜。"
        ]
    },
    {
        "title": "山居四首 其一",
        "type": "五言绝句",
        "paragraph": [
            "残菊不辞晚，犹开三两花。",
            "东篱多处士，知否忆陶家。"
        ],
        "translate": [
            "已经凋谢的菊花不怕天色晚了,还能有两三朵开放的花。",
            "东篱边有很多隐士,不知道他们是否还记得陶渊明的家呢?"
        ]
    },
    {
        "title": "山居四首 其二",
        "type": "五言绝句",
        "paragraph": [
            "泉自云根下，松从石上生。",
            "高吟山不答，惊我意峥嵘。"
        ],
        "translate": [
            "泉水从云母的根部奔泻而下,松树在岩石上生长。",
            "我高声地吟诗,山却不作答复,惊讶我的心意是多么的峥嵘。"
        ]
    },
    {
        "title": "山居四首 其三",
        "type": "五言绝句",
        "paragraph": [
            "晚笛穿云起，田家乐事多。",
            "可知牛背稳，无处著风波。"
        ],
        "translate": [
            "傍晚时分,悠扬的笛声穿过云雾而起,田间小院里农家常乐的事情很多。",
            "由此可知,牛的脊背安稳无比,不会遭到风波的摧残。"
        ]
    },
    {
        "title": "山居四首 其四",
        "type": "五言绝句",
        "paragraph": [
            "归寻牛矢路，黄叶满山村。",
            "野径无人到，斜阳自闭门。"
        ],
        "translate": [
            "回到家乡去寻找经过牛矢山的路,只见黄叶飘落满山村。",
            "荒野小路旁没有人来,夕阳斜照独自关着门。"
        ]
    },
    {
        "title": "乡居杂咏七首 其一",
        "type": "七言绝句",
        "paragraph": [
            "晓日曈曈照屋山，东窗竹影上斑斑。",
            "先生一笑梦初觉，目送清阴自往还。"
        ],
        "translate": [
            "清晨的阳光明亮皎洁地照在屋脊上,东窗下的竹子影子斑斑点点。",
            "先生一笑,从梦中醒来,目送着清幽的阴影,不由自主地往来。"
        ]
    },
    {
        "title": "乡居杂咏七首 其二",
        "type": "七言绝句",
        "paragraph": [
            "高柳鸣蜩昼转凉，芰荷出水透幽香。",
            "投竿坐挹千峰翠，鱼我悠悠意两忘。"
        ],
        "translate": [
            "高高的柳树上,蝉在鸣叫,白天变得凉爽了。菱角、荷叶从水中冒出,散发出阵阵幽香。",
            "放下钓竿坐着舀取千山万峰的青翠之色,鱼儿和我悠然自得地玩耍,全然忘却了彼此的情意。"
        ]
    },
    {
        "title": "乡居杂咏七首 其三",
        "type": "七言绝句",
        "paragraph": [
            "露痕如洗鸟频啼，行遍南溪又北溪。",
            "朝日未生云气好，微吟独立小桥西。"
        ],
        "translate": [
            "清澈的溪水流过,露水沾湿了它的痕迹,像洗过的一样。鸟儿不停地鸣叫着,我走遍了南溪,又走遍了北溪。",
            "早晨的太阳还未升起,云气很美,我独自一人在小桥西边低声吟诵。"
        ]
    },
    {
        "title": "乡居杂咏七首 其四",
        "type": "七言绝句",
        "paragraph": [
            "村前村后趁凉游，物外闲观兴转幽。",
            "满地花光初过雨，手扶新竹上牵牛。"
        ],
        "translate": [
            "在村前、村后趁着天气的凉爽去游览,在各种景物之外悠闲地观赏景色,兴致变得更加幽雅。",
            "雨后初晴,满地绽放的花朵沐浴在细雨中,我手扶着新长的竹子,登上了牛背。"
        ]
    },
    {
        "title": "乡居杂咏七首 其五",
        "type": "七言绝句",
        "paragraph": [
            "早稻将登插晚秧，天然图界界青黄。",
            "开门便拟江乡老，菡萏风生午枕凉。"
        ],
        "translate": [
            "初夏的稻子将要插入秋季的秧苗中,在天上呈现出一幅青黄相间的图画。",
            "刚一开门就想回到家乡老去,微风吹来午间枕上感到凉爽。"
        ]
    },
    {
        "title": "乡居杂咏七首 其六",
        "type": "七言绝句",
        "paragraph": [
            "青草湖头涨晚潮，阴云不雨树萧萧。",
            "放船南下如飞鸟，知过江村第几桥。"
        ],
        "translate": [
            "青草湖边晚潮上涨,阴云密布,不下雨,树木在风中萧萧作响。",
            "放船南下就像鸟儿飞一样容易,不知道经过江边的村庄还有多少座桥梁?"
        ]
    },
    {
        "title": "乡居杂咏七首 其七",
        "type": "七言绝句",
        "paragraph": [
            "菱芡初花绝可怜，鸣蛙田岸草芊芊。",
            "南塘日出无人到，十里晓风开白莲。"
        ],
        "translate": [
            "菱角和芡实刚刚开花十分可爱,田边青蛙在叫声中鸣叫着,野草长得密密稠稠。",
            "太阳从南塘升起时没有人赶到,十里之内的白莲迎着晨风绽放。"
        ]
    },
    {
        "title": "游山杂诗三首 其一",
        "type": "七言绝句",
        "paragraph": [
            "随分看山有寄庐，老樵乍见未为疏。",
            "閒谈五百年前事，笑道先生也姓涂。"
        ],
        "translate": [
            "慢慢地看到山上有我的茅庐,老樵夫刚一看见我还算不稀疏。",
            "闲来无事谈起五百年前的往事,笑着说先生也姓涂。"
        ]
    },
    {
        "title": "游山杂诗三首 其二",
        "type": "七言绝句",
        "paragraph": [
            "清净长留劫外身，此山终古不能臣。",
            "一筇踏遍千峰翠，但觉烟霞为我新。"
        ],
        "translate": [
            "清高洁净的本性永远留在世俗之外,这座山自古以来就不能使我臣服。",
            "拄着拐杖走遍了千山万岭,只觉得青山绿水都为我带来新意。"
        ]
    },
    {
        "title": "游山杂诗三首 其三",
        "type": "七言绝句",
        "paragraph": [
            "小店山腰卓酒旗，凭栏一笑更何辞。",
            "兴酣拍手高歌去，万壑千岩听我诗。"
        ],
        "translate": [
            "山腰上小亭子高举着酒旗,我倚着栏干一笑又有什么话可说。",
            "兴致正浓时拍着手高歌一曲而去,在万壑千岩中听我吟诗。"
        ]
    },
    {
        "title": "寓庐抒怀六首选一",
        "type": "五言律诗",
        "paragraph": [
            "莫问中原事，忧时鬓欲斑。",
            "旌旗思父老，骨肉滞关山。",
            "战伐夷歌起，流离大道艰。",
            "濡毫咏诸将，静听唱刀环。"
        ],
        "translate": [
            "不要问中原一带的战事,忧虑时局的变化,两鬓已经斑白了。",
            "挥动旌旗思念着远方的父老乡亲,可惜我们这些骨肉兄弟长期滞留在边关山岭。",
            "在战争和征伐中,少数民族的歌声四起,人民流离失所,是多么的艰难。",
            "用笔蘸着泪水歌咏各位将领,静静地听他们高唱《刀环》的曲子。"
        ]
    },
    {
        "title": "石灰桥暮春杂咏十首选六 其一",
        "type": "五言律诗",
        "paragraph": [
            "经年聊避地，借宅未须占。",
            "在客无多取，于诗似不廉。",
            "荒村谁与语，老树自生髯。",
            "料是宵来雨，流泉百道添。"
        ],
        "translate": [
            "一年多来姑且避开乡间小路,借住的房子不需要再占为己有。",
            "在客居他乡时不要多取豪夺,写诗看来似乎不够清廉。",
            "在荒凉的村庄里,有谁能和我交谈呢?只有老树上长满了胡子。",
            "料想今晚将会下起雨来,百道泉水从天上涌出,增添了许多泉水。"
        ]
    },
    {
        "title": "石灰桥暮春杂咏十首选六 其二",
        "type": "五言律诗",
        "paragraph": [
            "滚滚禾川水，绵绵义岭岚。",
            "风雷鸣古涧，花竹媚新庵。",
            "妆借鱼池镜，丝抽野树蚕。",
            "无端生白发，谁唱望江南。"
        ],
        "translate": [
            "滚滚的禾川河水,绵延不断的义山岭上云岚。",
            "古老的山涧里风声雷鸣,新建的庵堂上花草竹子鲜艳动人。",
            "梳妆时借镜子照一照鱼池的美丽容颜,又从野外树上拔出蚕丝来梳妆打扮。",
            "我无缘无故地头上长满了白发,是谁在高唱着《望江南》这首诗呢?"
        ]
    },
    {
        "title": "石灰桥暮春杂咏十首选六 其三",
        "type": "五言律诗",
        "paragraph": [
            "山势波澜阔，乾坤蔚至文。",
            "冈峦开日月，草木郁风云。",
            "客燕将安托，哀笳不忍闻。",
            "中宵空起舞，满目尚妖氛。"
        ],
        "translate": [
            "巍峨的泰山,波涛滚滚,浩瀚无边;苍茫的天地之间,蔚为壮美,文采奕奕。",
            "山冈上日月照耀,草木茂盛,风吹云散。",
            "客居他乡,将要寄托什么呢?哀怨的胡笳声实在不忍听。",
            "半夜里我白白地起身跳舞,满眼都是妖娆迷人的景象。"
        ]
    },
    {
        "title": "石灰桥暮春杂咏十首选六 其四",
        "type": "五言律诗",
        "paragraph": [
            "出门酬一笑，倦读卷随抛。",
            "水净风梳发，沙虚鸟布爻。",
            "幽花红未落，古蔓翠相交。",
            "得句何嫌晚，归灯手自抄。"
        ],
        "translate": [
            "出门去应酬一声笑,书卷疲倦了就随手抛开。",
            "清澈的河水,微风拂过,好像在为我梳理头发。沙滩上空空荡荡的一片汪洋,静静地栖息着一群群鸟儿,叽叽喳喳地念着爻辞。",
            "幽静的花儿还未凋谢,古老的藤蔓与翠绿的枝条交相辉映。",
            "写出这样的诗句为什么要嫌晚呢?我正好挑灯归来,手里亲自动手抄写。"
        ]
    },
    {
        "title": "石灰桥暮春杂咏十首选六 其五",
        "type": "五言律诗",
        "paragraph": [
            "故乡无此景，烟雨数归樵。",
            "荒厕多于屋，新苔长过桥。",
            "莺花疑梦寐，儿女擅歌谣。",
            "何限登楼感，孤愁不可浇。"
        ],
        "translate": [
            "故乡没有这样的美景,在烟雨迷蒙中我屡次回家打柴。",
            "荒废的厕所比房屋还多,新长出的青苔越长越过了小桥。",
            "黄莺和鲜花好像是在睡梦中一样,一群群小儿女在不停地唱着歌谣。",
            "登上高楼的感慨有何限量,孤独的愁思无法排遣。"
        ]
    },
    {
        "title": "石灰桥暮春杂咏十首选六 其六",
        "type": "五言律诗",
        "paragraph": [
            "小市集蔬米，初惊活计艰。",
            "深耕杂健妇，力作半娇鬟。",
            "青簇包头布，银摇坠耳环。",
            "古风流不尽，浒水自弯弯。"
        ],
        "translate": [
            "在一个小小的集市上,人们正在买些蔬菜和米,刚一吃起,就觉得谋生太难了。",
            "在深山里耕作的妇女们夹杂着强健的丈夫,她们努力耕作的力气有一半是娇美的发髻。",
            "青色花纹的包头布,镶银的耳环轻轻摇动。",
            "古往今来的风尚至今流传不尽,只有那泅水悠悠地流着。"
        ]
    },
    {
        "title": "闻五叔病卒全州军次移葬湘潭述哀",
        "type": "五言律诗",
        "paragraph": [
            "未见匈奴灭，先凋报国身。",
            "青灯前日事，白发梦中人。",
            "岭表鹃徒唤，湘郊草不春。",
            "临风空写泪，谁与诉酸辛？"
        ],
        "translate": [
            "没等到匈奴被消灭,就先为报效国家而牺牲了生命。",
            "在青灯下回忆往事,如今已是白发苍苍的梦中人。",
            "岭南杜鹃鸟徒然地鸣叫着,湘江的郊野连青草都看不到了春天。",
            "面对着风只能徒然地流泪,有谁能和我倾诉心中的辛酸?"
        ]
    },
    {
        "title": "病中妇戒作诗赋答",
        "type": "七言律诗",
        "paragraph": [
            "二十年来意所私，天高地厚更何之。",
            "拟将注海倾河泪，写作回天返日辞。",
            "事有不为从我好，世无可语待谁知。",
            "烦卿别示安心法，花竹清愁许自医。"
        ],
        "translate": [
            "二十年来我的心思被你所偏爱,天高地厚又能到哪里去呢?",
            "我本想把那注海倾河的泪水,写成《回天返日辞》。",
            "有些事情如果不顺从我的心意,那么世上没有什么可说的了,我等待着谁知道呢?",
            "烦劳你别告诉我安定心神的方法,花竹清愁请你自己去医治。"
        ]
    },
    {
        "title": "乙酉元旦赋示三弟",
        "type": "七言律诗",
        "paragraph": [
            "开岁春归梅柳新，六街喜气净微尘。",
            "笙歌乍入承平梦，啼笑难为乱世人。",
            "异地椒盘从吉颂，当前歧路慎迷津。",
            "吟成一笑阿兄醉，掉臂应知未肯驯。"
        ],
        "translate": [
            "新年刚过,春天就过去了,梅树和柳树都长得又嫩又茂盛。长安街上一片喜悦之气,洁净了大街小巷的灰尘。",
            "笙歌悠扬,忽然进入了太平盛世的梦境,可悲啊,这乱世中的人是多么的难能可贵呀!",
            "在异地采摘椒盘可以得到吉庆的颂扬,面临岔路口要谨慎对待迷路渡口。",
            "吟完诗后阿兄一笑大醉,掉臂应知不肯驯服。"
        ]
    },
    {
        "title": "次简盦师春尽日野望元韵",
        "type": "七言律诗",
        "paragraph": [
            "插天苍翠倚崚嶒，弹指春光感不胜。",
            "一壑一丘供日课，三薰三沐护吟灯。",
            "闲云出岫期为雨，热抱违时近欲冰。",
            "怅望苏门天咫尺，追随杖履想犹能。"
        ],
        "translate": [
            "青翠的山峰耸立在天边,我用手指一指就感觉到春天的景致,真是难以承受。",
            "在山谷和山丘上供奉着我每天的课业,用薰香、沐浴来保护我的灯盏。",
            "悠闲的云从山峰上飘出,预示着要下一场雨;天气炎热,却违背了季节,似乎要结成冰。",
            "惆怅地望着远离家乡的苏门,只觉得天边近在咫尺;想要拄着手杖、穿鞋去追赶,想来还是可以的。"
        ]
    },
    {
        "title": "夏窗书事六首 其一",
        "type": "七言律诗",
        "paragraph": [
            "乱蝉声里晚霞明，逭暑幽居绝送迎。",
            "薪爨微劳分妇稚，笑谈杂作半乡城。",
            "蔬缘手撷味尤隽，事以经多气转平。",
            "溪柳无风凉意足，可能重缔野鸥盟。"
        ],
        "translate": [
            "阵阵蝉鸣声中,晚霞显得格外明亮。在这酷热的夏天,我独自一人在幽静的家里,没有人来迎接我。",
            "烧火做饭的微薄劳作分给了媳妇和小孩子,叽叽喳喳地议论着在半个乡城里。",
            "摘下新鲜蔬菜,味道特别鲜美;做事要经过许多次的努力,才能使精神转为平和。",
            "溪边的柳树没有风,凉意已经很充足了,可以重新和野鸥结下团盟。"
        ]
    },
    {
        "title": "夏窗书事六首 其二",
        "type": "七言律诗",
        "paragraph": [
            "书生投老百无成，一枕甜然梦不惊。",
            "偶为剖瓜伤国事，聊因种竹惜清名。",
            "四山主我皆孙稚，万卷相从若友生。",
            "帘外轻雷风乍起，自浇苦茗倚南荣。"
        ],
        "translate": [
            "书生到了老年百无所成,安然一枕在梦中却没有被惊醒。",
            "偶尔因为剖瓜而伤感国家大事,姑且因为种竹而珍惜美好的名声。",
            "四座山的主人我和我的孙辈都还很小,在万卷书中跟随我就像是朋友一样。",
            "帘外突然传来阵阵轻雷般的微风,我独自一人在南边栏杆上喝着苦茗。"
        ]
    },
    {
        "title": "夏窗书事六首 其三",
        "type": "七言律诗",
        "paragraph": [
            "竹榻风清不动尘，随宜端可寄闲身。",
            "丝连屋角蜂投网，露缀枝头鸟哢晨。",
            "尽日语人无所隐，有时落笔觉如神。",
            "归来健饭妻儿喜，斗室长留万古春。"
        ],
        "translate": [
            "竹制的床榻在清风中静静地躺着不沾满灰尘,随心所欲地安适地寄托自己悠闲的身影。",
            "蛛丝缠绕着屋角,蜜蜂在上面投下网;露水点缀着树枝,鸟儿在清晨鸣叫。",
            "我整天对人说起话来毫不隐瞒,有时一挥而就觉得简直是神采飞扬。",
            "我从北方回来,吃得饱饱的,妻子儿女都欢喜雀跃;我的斗室可以永远留下万古千秋的春光。"
        ]
    },
    {
        "title": "夏窗书事六首 其四",
        "type": "七言律诗",
        "paragraph": [
            "一杯初发醉颜酡，眼底庭垣即涧阿。",
            "清咏乍闻知我返，足音坐久辨谁过。",
            "雨馀败壁蜗添篆，风急深林鸟唤囮。",
            "闲里作忙缘底事，诗情自笑晚来多。"
        ],
        "translate": [
            "刚刚喝完一杯酒,满脸是醉意,眼前的庭院墙壁就是山涧小道。",
            "刚刚听到你清雅的吟咏就知道我已经返回故乡,坐了很久才分辨出是谁经过。",
            "雨后枯败的墙壁上,蜗牛在上面添上了篆字;狂风呼啸,深林中的鸟儿正在呼唤猎物。",
            "闲来无事时为什么这样忙碌呢?我自己却笑话自己晚年写得太多了。"
        ]
    },
    {
        "title": "夏窗书事六首 其五",
        "type": "七言律诗",
        "paragraph": [
            "自汲清泉浸碧瓜，醰醰乡味尽堪誇。",
            "墙头风偃东西草，屋角晴开早晚霞。",
            "高树蝉鸣惊雀啄，小园花发闹蜂衙。",
            "宵来一雨添新涨，门外苍波没短葭。"
        ],
        "translate": [
            "自己汲取清澈的泉水浸泡在碧绿的瓜中,味道醇厚美好的家乡风味完全可以向人夸耀。",
            "墙头的风吹倒了东西两边的野草,屋角的阳光照耀下早晨和傍晚的晚霞分外明亮。",
            "高高的树上,蝉的叫声惊动了鸟雀的啄食;小园里的花开得正盛,蜜蜂正在忙着打草求蜜。",
            "夜里下了一场雨,水面又增添了新涨的潮水,门外的苍茫江水淹没了短小的芦苇。"
        ]
    },
    {
        "title": "夏窗书事六首 其六",
        "type": "七言律诗",
        "paragraph": [
            "诗成信手未须删，长日如年自掩关。",
            "学道念生儒墨外，处身思在惠夷间。",
            "还家愧见鸡豚壮，思母空馀涕泪潸。",
            "暮雨萧萧风撼木，归耕终傍大嵊山。"
        ],
        "translate": [
            "诗写成后,我就亲手抄录,不需要再删改了。我把门关上,日理万机,整天静静地欣赏着这美妙的诗歌。",
            "学习儒家学说应该在儒家墨家之外,立身处世应该在仁义和平民百姓中间。",
            "回家后惭愧地看见家中的鸡和猪都已经长大成人,思念起母亲空自流下眼泪。",
            "傍晚时分,雨声萧萧,风声震撼着树木,我归来耕作,最终还是依傍着大嵊山继续耕作。"
        ]
    },
    {
        "title": "楼居遣怀",
        "type": "七言律诗",
        "paragraph": [
            "萧然心自辨淄渑，疏懒从教与日增。",
            "一树浓阴分犬豕，八窗清气断蚊蝇。",
            "相须患难书千卷，写以高寒月半掕。",
            "双井龙州惭邑子，宗风谁为證传灯。"
        ],
        "translate": [
            "心绪萧条,无法分辨淄水与渑水的深浅;懒散无力,听从教导,一天比一天增添烦恼。",
            "满树的浓荫把狗和猪分开了,八面窗户的清凉气息吹断了蚊子和苍蝇。",
            "与你相处要经历千卷忧患和艰难,在严寒的月光下写下这篇书吧。",
            "在雙井和龍州作邑子我感到羞愧,有誰能為我證實傳燈的意義呢?"
        ]
    },
    {
        "title": "徙居杏村校宅",
        "type": "七言律诗",
        "paragraph": [
            "难为匝月三迁计，却羡蜗牛戴屋行。",
            "种树满疑随地好，酌泉真觉在山清。",
            "野花含笑敷朝气，古柏烘香逗晚晴。",
            "袖手微吟心自适，弦歌弹压鼓鼙声。"
        ],
        "translate": [
            "一个多月的时间里,我难以为一月之内三次搬迁做打算,却羡慕蜗牛戴着屋顶在天上行走。",
            "种满了树,让人怀疑随地而生;喝下泉水,真觉得山中泉水清。",
            "野花含笑绽放,散发着清晨的清新空气;古柏树在阳光的照耀下发出阵阵香气,逗留着傍晚的晴天。",
            "袖手轻轻地吟诵,心里感到很舒畅,弹奏的琴声压抑着鼓角和鼙鼓之声。"
        ]
    },
    {
        "title": "小住泰和感赋",
        "type": "七言律诗",
        "paragraph": [
            "涪翁不作龙渊死，顿觉词人一代空。",
            "绝世风流馀想像，劳人星火惜倥偬。",
            "澄江月色何今古，大宋文章托始终。",
            "酹酒无言天正醉，斜阳烟柳断肠中。"
        ],
        "translate": [
            "涪溪的陶潜如果不死在龙渊,顿时让人觉得词人这一代就已经空虚了。",
            "绝代佳人的风流倜傥,我还想着继续追寻;辛劳的星火使人感到艰难困苦,只可惜路途遥远。",
            "澄江的月色无论从古到今,依旧是那么的明亮。大宋朝的文治武功都寄托在它始终如一的美好时代。",
            "洒下酒杯默默无语,只有苍天正沉醉在酒中。夕阳西下,烟雾笼罩着柳树,令人断肠悲凉。"
        ]
    },
    {
        "title": "晓望",
        "type": "七言律诗",
        "paragraph": [
            "高原为谷谷为陵，莽莽坤舆大气蒸。",
            "替月一星回夜色，偃风百草试霜掕。",
            "朱楼梦觉寒如许，白雁南来感可胜。",
            "背岭村鸡催晓角，玉华天半蔚崚嶒。"
        ],
        "translate": [
            "高原变为山谷,山谷变为丘陵,高大雄伟的坤舆气象万千,天地间的气息蒸腾弥漫。",
            "月亮代替月亮的是一颗流星,使夜色变得更暗。微风吹来,百草开始凋零,秋霜已经降临。",
            "从梦中醒来感到寒气如此之大,白雁从南飞来触动我的愁思真是难以承受。",
            "背靠山岭的村子,鸡在催促着天亮。天空中蔚蓝的天空有一半是蔚蓝得可怕的。"
        ]
    },
    {
        "title": "得三弟南城书",
        "type": "七言律诗",
        "paragraph": [
            "烽烟行役冒深寒，择食从知一啄难。",
            "世乱倚天全骨肉，时穷为国惜衣冠。",
            "窗梅破萼春非远，客梦飘灯夜向阑。",
            "风雨鸡鸣同此感，新亭有泪只偷弹。"
        ],
        "translate": [
            "在烽烟弥漫的原野上,冒着凛冽的寒风,挑拣食物知道自己吃不饱就难了。",
            "国家动乱时依靠上天保全自己的骨肉至亲,时局窘迫时为了国家顾惜士大夫们衣冠。",
            "窗外的梅花已经破开了花萼,春天的脚步还很遥远。在客居他乡的梦中,只见孤灯飘动,夜已深了。",
            "面对风雨鸡鸣,我也有同样的感慨,在新亭上默默地流下眼泪偷偷地弹。"
        ]
    },
    {
        "title": "偕四弟步月",
        "type": "七言律诗",
        "paragraph": [
            "破空一鉴净初揩，冉冉春痕上柳钗。",
            "丛荟风生疑过虎，荒原霜早似铺秸。",
            "乱离岁月占双鬓，烽火饔飧惜寸阶。",
            "剩喜中年兄弟好，步趋犹得畅天怀。"
        ],
        "translate": [
            "镜子刚刚擦拭干净,柳树枝上渐渐长出了春意。",
            "树丛中春风吹来,让人怀疑它比老虎还要猛烈;荒凉的原野上,霜雪已经降得很早,就像铺上一层秸秆。",
            "遭逢战乱岁月侵占了我的双鬓,为了躲避战火和吃喝都舍不得寸步难行。",
            "最是高兴的是中年兄弟之间情谊深厚,即使走起路来也能够使心胸开阔、畅快。"
        ]
    }
]