[
    {
        "title": "句",
        "type": "五言诗",
        "paragraph": [
            "宁舍济川航。"
        ],
        "translate": [
            "怎么能舍弃渡河的船只呢?"
        ]
    },
    {
        "title": "与杜秀才",
        "type": "五言律诗",
        "paragraph": [
            "南极多老人，及见九代孙。",
            "君今古儋州，气质清且温。",
            "今年八十二，颇觉行步奔。",
            "白须映红颊，疑是羲皇人。"
        ],
        "translate": [
            "南方极远的地方有很多年高德劭的老人,等到见到他们已经是九代子孙了。",
            "你住在古时的儋州,气质既清雅又温文尔雅。",
            "今年我已经八十二岁了,却感觉到自己步履匆匆,好像在奔跑。",
            "白胡须映照着红颊,让人怀疑她一定是伏羲时代的人。"
        ]
    }
]