[
    {
        "title": "句 其十",
        "type": "五言诗",
        "paragraph": [
            "蚕寒冰茧瘦，蜂老露房攲。"
        ],
        "translate": [
            "寒冷的冬天,蚕茧被冻得消瘦了;蜜蜂已经老了,露水湿透了窝巢,不停地鸣叫着。"
        ]
    },
    {
        "title": "句 其七",
        "type": "七言诗",
        "paragraph": [
            "张亢触墙成八字。"
        ],
        "translate": [
            "《张亢卦》的卦象是坎下震上,为触墙而成八字之表象。"
        ]
    },
    {
        "title": "句 其十一",
        "type": "七言诗",
        "paragraph": [
            "鱼寒不食清池钓，鹭静频惊小阁棋。"
        ],
        "translate": [
            "寒冷的池塘里鱼儿不吃东西,白鹭静静地栖息在小阁楼上时常被围棋声惊醒。"
        ]
    },
    {
        "title": "句 其四",
        "type": "七言诗",
        "paragraph": [
            "陇雁半惊天在水，征人相顾月如霜。"
        ],
        "translate": [
            "陇山上的大雁半数受惊,天空已经在水面上消失了。出征的将士们互相望着,月亮就像白霜一样晶莹剔透。"
        ]
    },
    {
        "title": "句 其十三",
        "type": "七言诗",
        "paragraph": [
            "凉吹易成团扇恨，夕阳偏结小窗愁。"
        ],
        "translate": [
            "秋风吹来,容易引起团扇的怨恨;夕阳斜照,偏偏又勾起了小窗下的忧愁。"
        ]
    },
    {
        "title": "句 其十六",
        "type": "七言诗",
        "paragraph": [
            "枫迷楚客伤春野，山晦荆王梦雨天。"
        ],
        "translate": [
            "枫树迷离,楚地的游子为春天的郊野而伤感;暮色笼罩着山峦,楚王在雨中做梦,却只能在雨天里睡觉。"
        ]
    },
    {
        "title": "句 其一",
        "type": "五言诗",
        "paragraph": [
            "春风吹孤云。"
        ],
        "translate": [
            "春风轻轻地吹拂着孤零零的白云,好一派美好的景色。"
        ]
    },
    {
        "title": "句 其十五",
        "type": "七言诗",
        "paragraph": [
            "鱼上晚潮沙市合，鸦啼寒树石城昏。"
        ],
        "translate": [
            "傍晚时分,潮水上涨,沙洲上的集市上鱼儿聚集在一起;寒冷的树木上,乌鸦不停地啼叫,石城里一片昏暗。"
        ]
    },
    {
        "title": "句 其十二",
        "type": "五言诗",
        "paragraph": [
            "露槿东西照，风荷向背愁。"
        ],
        "translate": [
            "夕阳的余晖把木槿树向东和西照耀,微风吹来荷叶向背发出阵阵忧愁。"
        ]
    },
    {
        "title": "句 其二",
        "type": "七言诗",
        "paragraph": [
            "万壑松声山雨过，一川花气水风生。"
        ],
        "translate": [
            "山谷里松涛声阵阵传来,雨过天晴,满川的花香沐浴在春风中,焕发着清新的气息。"
        ]
    },
    {
        "title": "句 其六",
        "type": "七言诗",
        "paragraph": [
            "结伴不禁鸳瓦冷，羞明常怯玉钩斜。"
        ],
        "translate": [
            "与心上人相伴,不禁感到鸳鸯瓦的寒冷;面对明亮的月光,常常害怕玉钩斜挂。"
        ]
    },
    {
        "title": "句 其九",
        "type": "七言诗",
        "paragraph": [
            "谁将水调歌秋雁，不遣君王待曲终。"
        ],
        "translate": [
            "是谁用《水调》来谱写《秋雁》的曲子呢?不让君王等到曲终才停止。"
        ]
    },
    {
        "title": "句 其八",
        "type": "七言诗",
        "paragraph": [
            "疾风甚雨青春老，瘦马疲牛绿野深。"
        ],
        "translate": [
            "狂风大作,大雨倾盆,春天已经过去。瘦弱的马匹和疲惫的牛儿,田野里长满了绿草。"
        ]
    },
    {
        "title": "句 其五",
        "type": "七言诗",
        "paragraph": [
            "蜀江雪浪来天际，一派泉舂宝钗碎。"
        ],
        "translate": [
            "蜀江上雪白的浪花从天边涌来,泉水像舂米一样把宝钗舂得粉碎。"
        ]
    },
    {
        "title": "句 其十四",
        "type": "七言诗",
        "paragraph": [
            "山花冷隔何堪折，一曲红梅字字香。"
        ],
        "translate": [
            "山花被寒冷的气候阻隔,怎么能够摘取呢?一曲《红梅》,每一枝都散发着阵阵清香。"
        ]
    },
    {
        "title": "题招隐寺",
        "type": "五言诗",
        "paragraph": [
            "苍崖何蟠回，尝为隐君宅。",
            "孰谓人琴亡，松风正萧瑟。",
            "花闲雪英舞，鹿去岩泉冽。",
            "经声草堂迥，天香中夜发。",
            "月落山气深，清猿啸亦绝。",
            "如何人外迹，轻为世网别。"
        ],
        "translate": [
            "苍翠的山崖怎么盘曲曲折,它曾经是隐士王羲之的住宅。",
            "谁说琴声已经失去,松树上的秋风正瑟瑟作响。",
            "花儿悠闲地在雪花纷飞中开放,鹿儿离去后岩泉清冽而寒冷。",
            "在幽静的草堂听着悠扬的经书声,天上的香气在半夜里四处散发。",
            "月亮已经落下,山中云气更加浓厚,清脆的猿啼也停止了鸣叫。",
            "为什么人世间的行迹,会被世俗的网罗轻易地抛弃呢?"
        ]
    },
    {
        "title": "清辉殿观唐明皇山水石字歌",
        "type": "七言诗",
        "paragraph": [
            "皇家四叶恢圣功，天临日烛清华戎。",
            "汉条静治洽柔教，老心稽古开神聪。",
            "有唐英主称好文，仙毫洒落驱风云。",
            "壮哉山水有奇字，焕乎八法存翠珉。",
            "自从弃置咸阳道，藓驳烟滋委宫草。",
            "天开神赞会休辰，甄收再作皇居宝。",
            "如何沦弃三百春，迎逢睿鉴来紫宸。",
            "奎钩粲粲光华动，群玉森森气象新。",
            "丹籞春妍瑞霭深，文梁藻栋结芳林。",
            "鸿翔凤翥径方丈，杯流泉涌蒙亲临。",
            "鲰臣荣幸从金舆，钩婉魂惊拭目初。",
            "多惭揽笔非清藻，唯庆千龄际帝图。"
        ],
        "translate": [
            "东晋四代帝王的功业历经四代,如今皇上驾临,日月照耀,使中原地区太平无事。",
            "汉代条理清静无为而治,融会贯通柔和的教化;我以老练的心思研习古代典籍,使心灵开阔,耳聪目明。",
            "唐朝英明的君主称赞他的文章,他挥笔写出如仙的笔墨,直驱风云。",
            "山水的景色多么壮美,它那“奇字”的八种色彩也都焕然一新,呈现出美好的景色。",
            "自从废弃了通往咸阳的大道,苔藓、杂草和烟雾逐渐滋长蔓延到宫殿旁的野草。",
            "上天赐福,神灵赞美,正是美好的时节,甄收再次被封为皇太子,成为京城的珍宝。",
            "我怎么沦落三百余年,却又恰好遇到圣明的君主来到京城长安。",
            "奎钩星光彩夺目,闪动着灿烂的光芒;众多的玉石排列森严,气象更新。",
            "红漆的池塘春光明媚,祥瑞的云气弥漫在深深的烟霭之中;华美的屋梁和雕饰华丽的栋梁紧紧相连,如同茂密的芳林。",
            "鸿雁在空中飞翔,凤凰在山路旁翱翔,杯水像泉水一样涌动,我亲眼目睹了这件事。",
            "鲰鱼之臣荣幸地跟随皇帝乘坐金舆,惊醒了钩婉之女的魂魄擦拭了眼睛。",
            "我常常惭愧自己拿起笔来写文章并不能表达内心的情感,只希望能活到百岁才能成就帝王之业。"
        ]
    },
    {
        "title": "秋日白鹭亭向夕有感",
        "type": "五言诗",
        "paragraph": [
            "白鹭敞西轩，檐宇穷爽垲。",
            "千峰若连环，翠色不可解。",
            "是时天宇旷，六幕无纤霭。",
            "金斗熨秋江，素练横衣带。",
            "乾坤清且敛，气象朝昏改。",
            "芦花作雪风，飞舞来沧海。",
            "九霄汀鹭起，万里樯乌快。",
            "月上三山头，鸟没横塘外。",
            "苍茫洲渚寥，错落星斗大。",
            "开尊屏丝竹，披襟向萧籁。",
            "余生本江湖，偃蹇欣所会。",
            "清兴虽自废，苦嗜亦吾累。",
            "鱼龙凭夜涛，四面忽滂湃。",
            "安得燃犀灯，煌煌发水怪。"
        ],
        "translate": [
            "白鹭栖息在宽敞的西窗下,檐宇尽头是清爽明净的屋舍。",
            "千山万岭好像连在一起的玉环,翠绿的山色让人无法理解。",
            "这时天空空旷无边,天上的云彩从六面遮盖下来,丝毫没有一点云气。",
            "金色的斗柄熨烫着秋天的江水,白色的丝带横放在衣带上。",
            "从早到晚,天地间万物都呈现出清朗和收敛的景象,这样一来,日月星辰的运行就朝着东方、暮色向西或向东发生了变化。",
            "芦花在雪夜的风中翩翩起舞,飘飞到辽阔的大海。",
            "高入云霄的沙滩上白鹭翩翩起飞,远望万里船上的乌鸦正欢快地嬉戏。",
            "一轮明月升上三山头,一只鸟儿在横塘外沉没。",
            "苍茫的沙洲上空一片寂静,远处错落的星斗似乎比天上的银河还要大。",
            "打开酒杯,屏风上放着丝竹乐器,敞开衣襟听那萧瑟的乐声。",
            "我的一生本来生活在江湖之中,每当遇到志趣相投的人我都高兴地与他们相会。",
            "清明时节的兴致虽然自己荒废了,但苦涩的嗜好也只是我的过错。",
            "夜幕降临,江面波涛汹涌,水天相接,鱼龙在水中嬉戏,四周浪花猛烈地涌动。",
            "怎么能点燃犀牛角做的灯呢?它发出的亮光像发水虫一样神奇。"
        ]
    },
    {
        "title": "咏玉蕊花",
        "type": "五言诗",
        "paragraph": [
            "玉蕊生禁林，地崇姿亦贵。",
            "散漫阴谷中，蓬茨复何异。",
            "清芬信幽远，素彩非妖丽。",
            "苍烟蔽山日，琼瑶为之晦。",
            "岁久自扶疏，岩深愈凝邃。",
            "请观唐相吟，俗眼无轻视。"
        ],
        "translate": [
            "玉蕊生长在宫禁的树林里,地势高峻姿态也显得尊贵。",
            "在阴冷的山谷中四处飘荡,与蓬草和茅草没有什么两样。",
            "清幽的香气确实很深远,白色的花朵并不是妖娆艳丽。",
            "苍茫的烟雾遮住了终南山的太阳,山上的琼玉树也因此变得暗淡了。",
            "年岁渐长,树木的枝叶逐渐疏落,山岩越加幽深,显得格外凝重。",
            "请看唐代的宰相李白吟咏诗篇,世俗之人的眼光是不会轻视他的。"
        ]
    },
    {
        "title": "送安公归顶山瑞石庵",
        "type": "五言律诗",
        "paragraph": [
            "谈空一纪馀，重出访岩居。",
            "身是汾阳嗣，囊惟郭璞书。",
            "公侯倒屣后，泉石结茆初。",
            "山顶收榛栗，经秋信莫疏。"
        ],
        "translate": [
            "我谈论玄理已经有十二年了,现在又出来探访隐居的山野之人。",
            "我本人是汾阳王的后代,我的行囊中只有郭璞写的书。",
            "公侯们倒屣之后,就好像泉石在茆前结成那样坚固。",
            "山顶上已经收割完许多的榛树和栗子了,经过一整年的秋季,我的心音再也难以流传下去了。"
        ]
    },
    {
        "title": "金陵赏心亭",
        "type": "七言律诗",
        "paragraph": [
            "千里秦淮在玉壶，江山清丽壮吴都。",
            "昔人已化辽天鹤，旧画难寻卧雪图。",
            "冉冉流年去京国，萧萧华发老江湖。",
            "残蝉不会登临意，又噪西风入座隅。"
        ],
        "translate": [
            "巍峨的秦淮河绵延千里,犹如玉壶般雄伟壮观;秀丽的江山清澈见底,使吴都显得格外雄伟壮观。",
            "昔日的仙鹤已经化为辽天上的白鹤,旧时的画中再也找不到那卧雪图了。",
            "时光慢慢地流逝,我就像萧萧的白发漂泊在江湖上一样衰老。",
            "树枝上的残蝉不知道我登临山顶的用意,又在西风中呼啸着扑入我的座位角落。"
        ]
    },
    {
        "title": "九曲池",
        "type": "五言律诗",
        "paragraph": [
            "越调隋家曲，当年亦九成。",
            "哀音已亡国，废诏尚留名。",
            "仪凤终沉影，鸣蛙祇沸声。",
            "凄凉不可问，落日背芜城。"
        ],
        "translate": [
            "《越调》是隋朝的乐曲,隋炀帝时也曾演奏了九成。",
            "《哀音》已经使国家灭亡了,但是废弃的诏书却还保留着它的名字。",
            "凤凰的仪容终究要沉落在水底,青蛙的叫声只能是沸腾的响声。",
            "凄凉之情无法去追问,夕阳西下,我背向着芜城。"
        ]
    },
    {
        "title": "暮春游小园",
        "type": "七言绝句",
        "paragraph": [
            "一丛梅粉褪残妆，涂抹新红上海棠。",
            "开到荼蘼花事了，丝丝天棘出莓墙。"
        ],
        "translate": [
            "一丛丛梅花褪去了残妆,刚刚涂抹上新红的海棠花,显得格外娇美。",
            "等到荼蘼花开的时候,天上的荆条从莓墙里长出来了。"
        ]
    },
    {
        "title": "答永叔问",
        "type": "七言绝句",
        "paragraph": [
            "班班疏雨寒无定，皎皎圆蟾望欲阑。",
            "应在浮云尽深处，更凭丝竹一催看。"
        ],
        "translate": [
            "稀疏的雨点纷纷飘洒,寒气袭人无定处。皎洁的月光照耀着天空,令人极目远望,但见它已快要西沉了。",
            "你应该站在浮云的尽头,再凭着丝竹助兴,催促着欣赏这首词。"
        ]
    },
    {
        "title": "绝句 其一",
        "type": "七言绝句",
        "paragraph": [
            "香溪春老误寻芳，只有愁云映夕阳。",
            "今日重来已如此，何须更问海生桑。"
        ],
        "translate": [
            "香溪的春天已经过去,错把花儿找回来了,只剩下愁云在夕阳下笼罩着。",
            "今天我重新来到这里已经到了这种地步,还用得着再去问那海里生长的桑树呢?"
        ]
    },
    {
        "title": "绝句 其二",
        "type": "七言绝句",
        "paragraph": [
            "正月初弦二月赊，小园春事已如麻。",
            "强誇力健因移石，不减公忙为种花。"
        ],
        "translate": [
            "二月的弦音刚刚开始,小园里的春花已经凋谢得像麻一样。",
            "我夸耀自己力气大,是因为能移动石头,不亚于您忙着为我种花。"
        ]
    },
    {
        "title": "垂虹亭",
        "type": "七言绝句",
        "paragraph": [
            "红桥跨浪二千尺，桥上危亭在水心。",
            "六月火云烧万里，夜来风细似秋深。"
        ],
        "translate": [
            "红桥跨过波浪高达二千尺,桥上的高楼亭阁坐落在水中央。",
            "六月的烈火和乌云在万里之外燃烧,夜晚的风细细得好似深秋时节。"
        ]
    },
    {
        "title": "红梅",
        "type": "七言绝句",
        "paragraph": [
            "馆娃宫里旧精神，粉瘦琼寒露蕊新。",
            "园吏无端偷折去，凤城从此有双身。"
        ],
        "translate": [
            "馆娃宫里旧日的神采依旧,粉白瘦弱像玉石般寒冷,露珠般的花蕊又呈现出新的面容。",
            "园林的官吏无缘无故地把她偷偷折了去,从此凤城公主有了双身。"
        ]
    },
    {
        "title": "无弦琴",
        "type": "五言绝句",
        "paragraph": [
            "寂寞之淳音，其为乐至深。",
            "应嫌鼓腹者，独自抚弦琴。"
        ],
        "translate": [
            "寂寞无声的纯正之音,它带来的快乐是那样的深远。",
            "应该嫌弃鼓腹之苦的人,独自一人抚弄琴弦。"
        ]
    },
    {
        "title": "和王季安作",
        "type": "五言律诗",
        "paragraph": [
            "僻处因耽道，读书获我心。",
            "为嫌牵俗累，不厌入山深。",
            "野趣聊荒遁，才名岂陆沈。",
            "圣朝思梦卜，终忍卧园林。"
        ],
        "translate": [
            "僻静的居处让我沉溺于道教,读书能够领悟我的心意。",
            "因为嫌疑而受到世俗的牵累,不厌烦进入深山里去隐居。",
            "纵情于山野之趣,姑且去荒远地隐居;有才华和名望的人,怎会沉溺于水深火热之中?",
            "在圣明的朝代,我常常想通过梦中来占卜吉凶,到底怎么忍心躺卧在园林里呢?"
        ]
    },
    {
        "title": "绝句",
        "type": "七言律诗",
        "paragraph": [
            "香溪春老误寻芳，只有愁云映夕阳。",
            "今日重来已如此，何须更问海生桑。",
            "正月初弦二月赊，小园春事已如麻。",
            "强誇力健因移石，不减公忙为种花。"
        ],
        "translate": [
            "香溪的春天已经过去,错把花儿找回来了,只剩下愁云在夕阳下笼罩着。",
            "今天我重新来到这里已经到了这种地步,还用得着再去问那海里生长的桑树呢?",
            "二月的弦音刚刚开始,小园里的春花已经凋谢得像麻一样。",
            "我夸耀自己力气大,是因为能移动石头,不亚于您忙着为我种花。"
        ]
    }
]